ANIDS/anids_defines.vh
// ANIDS Defines
// Clock Period, this is 5ns period (200MHz clock)
`define CLK_PERIOD				16'd5


// APB can work with 8, 16, 32 bit data width
`define APB_DATA_WIDTH			8
`define APB_ADDR_WIDTH			16 							// 15 bits needed, but we use 16.


// DMA Data Width is input vector size, which is 128 bits
`define DMA_DATA_WIDTH			128

// Memory Fetch Unit widths
`define MFU_DATA_WIDTH			`DMA_DATA_WIDTH
`define MFU_FEATURE_WIDTH		`MFU_DATA_WIDTH				// stored feature vector width

// Pipeline Manager widths and history depth
`define PIPELINE_VECTOR_WIDTH	`MFU_FEATURE_WIDTH			// vector width propagated through pipeline manager
`define PIPELINE_COUNTER_WIDTH	7							// counter width for indices 0..127
`define PIPELINE_HISTORY_DEPTH	2							// number of coarse vector buffers before validation
`define PIPELINE_STAGE_CYCLES	64							// 128-bit vector processed over 64 cycles
`define PIPELINE_STAGE_COUNT_W	6							// counter width for 0..63 stage timing

// Input layer widths
`define INPUT_LAYER_FEATURE_WIDTH	`PIPELINE_VECTOR_WIDTH	// full feature vector width seen by input layer
`define INPUT_LAYER_PAIR_WIDTH		2						// number of feature bits processed per counter step

// Hidden layer unit widths
`define HL_FEATURE_PAIR_WIDTH		`INPUT_LAYER_PAIR_WIDTH	// number of feature bits consumed per cycle
`define HL_WEIGHT_WIDTH				8						// signed Q0.7 weight width
`define HL_BIAS_WIDTH				8						// signed Q0.7 bias width
`define HL_RESULT_WIDTH				8						// signed Q0.7 hidden neuron output width
`define HL_PAIR_SUM_WIDTH			9						// sum of two weighted feature contributions
`define HL_ACC_WIDTH				15						// accumulation register width before truncation

// Output layer unit widths
`define OL_INPUT_WIDTH				8						// signed Q0.7 hidden-layer input width
`define OL_WEIGHT_WIDTH				8						// signed Q0.7 output-layer weight width
`define OL_BIAS_WIDTH				8						// signed Q0.7 output-layer bias width
`define OL_RESULT_WIDTH				8						// signed Q0.7 output-layer result width
`define OL_PRODUCT_WIDTH			16						// full signed 8x8 multiply width
`define OL_TRUNC_PRODUCT_WIDTH		8						// product truncated back to Q0.7
`define OL_ACC_WIDTH				15						// accumulation width before final truncation

// Loss function widths
`define LF_FEATURE_PAIR_WIDTH		`INPUT_LAYER_PAIR_WIDTH	// number of original feature bits consumed per cycle
`define LF_RESULT_IN_WIDTH			8						// compared result width
`define LF_ABS_WIDTH				8						// absolute delta width
`define LF_PAIR_SUM_WIDTH			9						// sum of two absolute deltas
`define LF_ACC_WIDTH				15						// accumulation register width before truncation

// Sigmoid LUT address mapper widths
`define MMAP_IN_WIDTH				8						// signed Q0.7 value width before LUT lookup
`define MMAP_ADDR_WIDTH				`LUT_ADDR_WIDTH		// LUT address width after mapping

// LUT Address and Data Sizes
`define LUT_ADDR_WIDTH			8
`define LUT_DATA_WIDTH			8

`define RELU_WIDTH 				8
`define LF_OUT_WIDTH			8



// Weight & Bias Counts
`define HL_WEIGHT_COUNT   		64 * 128   	// 8192
`define HL_BIAS_COUNT      		64       	// 64
`define OL_WEIGHT_COUNT    		128 * 64   	// 8192
`define OL_BIAS_COUNT      		128      	// 128


// ANIDS Control Register Addresses
`define START_REG				0
`define N_REG					1
`define THRESHOLD_REG			2
`define RESULT_REG				3


// Indirect LUT Read/Write Registers
`define LUT_ADDR				4
`define LUT_DATA				5
`define LUT_CTRL				6
`define FREE_REG				7


// Hidden Layer Register Mapping
`define HL_WEIGHT_BASE			8 // we have 128 * 64 of these
`define HL_BIAS_BASE			`HL_WEIGHT_BASE + `HL_WEIGHT_COUNT // and 64 of these


// Output Layer Register Mapping
`define OL_WEIGHT_BASE			`HL_BIAS_BASE + `HL_BIAS_COUNT
`define OL_BIAS_BASE			`OL_WEIGHT_BASE + `OL_WEIGHT_COUNT


// ANIDS memory map borders
`define ANIDS_MAP_START   		`HL_WEIGHT_BASE
`define ANIDS_MAP_END     		`OL_BIAS_BASE + `OL_BIAS_COUNT
`define REG_COUNT				`ANIDS_MAP_END 	// (correct count due to 0-based indexing)


// Pipeline Stage Cycles
`define INPUT_LAYER_CYCLES 		1
`define HIDDEN_LAYER_CYCLES 	64
`define OUTPUT_LAYER_CYCLES 	64
`define LOOKUP_LAYER_CYCLES 	64
`define LOSS_FUNCTION_CYCLES 	64
`define OUTLIER_CYCLES 			1
`define RESULT_CYCLES 			1


// Pipeline Fill and Latency in cycles (pipefill = 259, latency = 130)
`define PIPE_FILL_CYCLES 		(`INPUT_LAYER_CYCLES + `HIDDEN_LAYER_CYCLES + `OUTPUT_LAYER_CYCLES + `LOOKUP_LAYER_CYCLES + `LOSS_FUNCTION_CYCLES + `OUTLIER_CYCLES + `RESULT_CYCLES)
`define LATENCY_IN_CYCLES 		(`LOOKUP_LAYER_CYCLES + `LOSS_FUNCTION_CYCLES + `OUTLIER_CYCLES + `RESULT_CYCLES )

ANIDS/src/core/input_layer.sv
// ANIDS Input Layer
`include "anids_defines.vh"

module input_layer (
		clk,
		resetN,
		enable,
		features,
		counter,
		current_features
	);

	parameter FEATURE_WIDTH = `INPUT_LAYER_FEATURE_WIDTH;
	parameter COUNTER_WIDTH = `PIPELINE_COUNTER_WIDTH;
	parameter PAIR_WIDTH    = `INPUT_LAYER_PAIR_WIDTH;

	// ----------------------------------------------------------------------
	//                  		I/O Ports
	// ----------------------------------------------------------------------
	input  wire                         clk;
	input  wire                         resetN;
	input  wire                         enable;
	input  wire [FEATURE_WIDTH-1:0]     features;
	input  wire [COUNTER_WIDTH-1:0]     counter;
	output reg  [PAIR_WIDTH-1:0]        current_features;

	// ----------------------------------------------------------------------
	//                  		Feature Pair Selection
	// ----------------------------------------------------------------------
	always @(posedge clk or negedge resetN) begin
		if (!resetN) begin
			current_features <= #1 {PAIR_WIDTH{1'b0}};
		end
		else if (!enable) begin
			current_features <= #1 {PAIR_WIDTH{1'b0}};
		end
		else begin
			current_features <= #1 {features[(counter * PAIR_WIDTH) + 1], features[counter * PAIR_WIDTH]};
		end
	end
endmodule

ANIDS/tb/input_layer_tb.v
// ANIDS - Input Layer Testbench
`timescale 1ns/100ps
`include "anids_defines.vh"

module input_layer_tb;

	localparam FEATURE_WIDTH = `INPUT_LAYER_FEATURE_WIDTH;
	localparam COUNTER_WIDTH = `PIPELINE_COUNTER_WIDTH;
	localparam PAIR_WIDTH    = `INPUT_LAYER_PAIR_WIDTH;

	reg                         clk;
	reg                         resetN;
	reg                         enable;
	reg  [FEATURE_WIDTH-1:0]    features;
	reg  [COUNTER_WIDTH-1:0]    counter;
	wire [PAIR_WIDTH-1:0]       current_features;

	input_layer #(
		.FEATURE_WIDTH(FEATURE_WIDTH),
		.COUNTER_WIDTH(COUNTER_WIDTH),
		.PAIR_WIDTH   (PAIR_WIDTH)
	) dut (
		.clk              (clk),
		.resetN           (resetN),
		.enable           (enable),
		.features         (features),
		.counter          (counter),
		.current_features (current_features)
	);

	always #2.5 clk = ~clk;

	initial begin
		$dumpfile("input_layer_tb.vcd");
		$dumpvars(0, input_layer_tb);

		clk      = 1'b0;
		resetN   = 1'b0;
		enable   = 1'b0;
		features = 128'hFEDCBA98765432100123456789ABCDEF;
		counter  = {COUNTER_WIDTH{1'b0}};

		#2;
		check_output(2'b00, "reset clears output");

		resetN <= 1'b1;
		@(posedge clk);
		#2;
		check_output(2'b00, "enable low outputs zeros");

		enable  <= 1'b1;
		counter <= 7'd0;
		@(posedge clk);
		#2;
		check_output(2'b11, "counter 0 selects bits 1:0");

		counter <= 7'd1;
		@(posedge clk);
		#2;
		check_output(2'b11, "counter 1 selects bits 3:2");

		counter <= 7'd2;
		@(posedge clk);
		#2;
		check_output(2'b10, "counter 2 selects bits 5:4");

		counter <= 7'd63;
		@(posedge clk);
		#2;
		check_output(2'b11, "counter 63 selects bits 127:126");

		enable <= 1'b0;
		@(posedge clk);
		#2;
		check_output(2'b00, "enable low clears output after activity");

		$display("INPUT_LAYER TB PASSED");
		$finish;
	end

	task check_output(
		input [PAIR_WIDTH-1:0] expected,
		input [255:0]          test_name
	);
	begin
		if (current_features !== expected) begin
			$error("FAIL: %0s | got=%0b expected=%0b counter=%0d enable=%0b",
				test_name, current_features, expected, counter, enable);
			$finish;
		end
		else begin
			$display("PASS: %0s", test_name);
		end
	end
	endtask

endmodule

Outputs/vcd/input_layer_tb.vcd
$date
	Tue Jun 09 14:54:13 2026
$end
$version
	Icarus Verilog
$end
$timescale
	100ps
$end
$scope module input_layer_tb $end
$var wire 2 ! current_features [1:0] $end
$var parameter 32 " COUNTER_WIDTH $end
$var parameter 32 # FEATURE_WIDTH $end
$var parameter 32 $ PAIR_WIDTH $end
$var reg 1 % clk $end
$var reg 7 & counter [6:0] $end
$var reg 1 ' enable $end
$var reg 128 ( features [127:0] $end
$var reg 1 ) resetN $end
$scope module dut $end
$var wire 1 % clk $end
$var wire 7 * counter [6:0] $end
$var wire 1 ' enable $end
$var wire 128 + features [127:0] $end
$var wire 1 ) resetN $end
$var parameter 32 , COUNTER_WIDTH $end
$var parameter 32 - FEATURE_WIDTH $end
$var parameter 32 . PAIR_WIDTH $end
$var reg 2 / current_features [1:0] $end
$upscope $end
$scope task check_output $end
$var reg 2 0 expected [1:0] $end
$var reg 256 1 test_name [255:0] $end
$upscope $end
$upscope $end
$enddefinitions $end
$comment Show the parameter values. $end
$dumpall
b10 .
b10000000 -
b111 ,
b10 $
b10000000 #
b111 "
$end
#0
$dumpvars
bx 1
bx 0
bx /
b11111110110111001011101010011000011101100101010000110010000100000000000100100011010001010110011110001001101010111100110111101111 +
b0 *
0)
b11111110110111001011101010011000011101100101010000110010000100000000000100100011010001010110011110001001101010111100110111101111 (
0'
b0 &
0%
bx !
$end
#10
b0 !
b0 /
#20
1)
b1110010011001010111001101100101011101000010000001100011011011000110010101100001011100100111001100100000011011110111010101110100011100000111010101110100 1
b0 0
#25
1%
#45
1'
b11001010110111001100001011000100110110001100101001000000110110001101111011101110010000001101111011101010111010001110000011101010111010001110011001000000111101001100101011100100110111101110011 1
#50
0%
#75
1%
#85
b11 !
b11 /
#95
b1 &
b1 *
b110001101101111011101010110111001110100011001010111001000100000001100000010000001110011011001010110110001100101011000110111010001110011001000000110001001101001011101000111001100100000001100010011101000110000 1
b11 0
#100
0%
#125
1%
#145
b10 &
b10 *
b110001101101111011101010110111001110100011001010111001000100000001100010010000001110011011001010110110001100101011000110111010001110011001000000110001001101001011101000111001100100000001100110011101000110010 1
#150
0%
#175
1%
#185
b10 !
b10 /
#195
b111111 &
b111111 *
b110001101101111011101010110111001110100011001010111001000100000001100100010000001110011011001010110110001100101011000110111010001110011001000000110001001101001011101000111001100100000001101010011101000110100 1
b10 0
#200
0%
#225
1%
#235
b11 !
b11 /
#245
0'
b1100011011011110111010101101110011101000110010101110010001000000011011000110011001000000111001101100101011011000110010101100011011101000111001100100000011000100110100101110100011100110010000000110001001100100011011100111010001100010011001000110110 1
b11 0
#250
0%
#275
1%
#285
b0 !
b0 /
#295
b110110001101111011101110010000001100011011011000110010101100001011100100111001100100000011011110111010101110100011100000111010101110100001000000110000101100110011101000110010101110010001000000110000101100011011101000110100101110110011010010111010001111001 1
b0 0
