ANIDS/anids_defines.vh
// ANIDS Defines
// Clock Period, this is 5ns period (200MHz clock)
`define CLK_PERIOD				16'd5


// APB can work with 8, 16, 32 bit data width
`define APB_DATA_WIDTH			8
`define APB_ADDR_WIDTH			16 							// 15 bits needed, but we use 16.


// DMA Data Width is input vector size, which is 128 bits
`define DMA_DATA_WIDTH			128

// Memory Fetch Unit widths
`define MFU_DATA_WIDTH			`DMA_DATA_WIDTH
`define MFU_FEATURE_WIDTH		`MFU_DATA_WIDTH				// stored feature vector width

// Pipeline Manager widths and history depth
`define PIPELINE_VECTOR_WIDTH	`MFU_FEATURE_WIDTH			// vector width propagated through pipeline manager
`define PIPELINE_COUNTER_WIDTH	7							// counter width for indices 0..127
`define PIPELINE_HISTORY_DEPTH	2							// number of coarse vector buffers before validation
`define PIPELINE_STAGE_CYCLES	64							// 128-bit vector processed over 64 cycles
`define PIPELINE_STAGE_COUNT_W	6							// counter width for 0..63 stage timing

// Input layer widths
`define INPUT_LAYER_FEATURE_WIDTH	`PIPELINE_VECTOR_WIDTH	// full feature vector width seen by input layer
`define INPUT_LAYER_PAIR_WIDTH		2						// number of feature bits processed per counter step

// Hidden layer unit widths
`define HL_FEATURE_PAIR_WIDTH		`INPUT_LAYER_PAIR_WIDTH	// number of feature bits consumed per cycle
`define HL_WEIGHT_WIDTH				8						// signed Q0.7 weight width
`define HL_BIAS_WIDTH				8						// signed Q0.7 bias width
`define HL_RESULT_WIDTH				8						// signed Q0.7 hidden neuron output width
`define HL_PAIR_SUM_WIDTH			9						// sum of two weighted feature contributions
`define HL_ACC_WIDTH				15						// accumulation register width before truncation

// Output layer unit widths
`define OL_INPUT_WIDTH				8						// signed Q0.7 hidden-layer input width
`define OL_WEIGHT_WIDTH				8						// signed Q0.7 output-layer weight width
`define OL_BIAS_WIDTH				8						// signed Q0.7 output-layer bias width
`define OL_RESULT_WIDTH				8						// signed Q0.7 output-layer result width
`define OL_PRODUCT_WIDTH			16						// full signed 8x8 multiply width
`define OL_TRUNC_PRODUCT_WIDTH		8						// product truncated back to Q0.7
`define OL_ACC_WIDTH				15						// accumulation width before final truncation

// Loss function widths
`define LF_FEATURE_PAIR_WIDTH		`INPUT_LAYER_PAIR_WIDTH	// number of original feature bits consumed per cycle
`define LF_RESULT_IN_WIDTH			8						// compared result width
`define LF_ABS_WIDTH				8						// absolute delta width
`define LF_PAIR_SUM_WIDTH			9						// sum of two absolute deltas
`define LF_ACC_WIDTH				15						// accumulation register width before truncation

// Sigmoid LUT address mapper widths
`define MMAP_IN_WIDTH				8						// signed Q0.7 value width before LUT lookup
`define MMAP_ADDR_WIDTH				`LUT_ADDR_WIDTH		// LUT address width after mapping

// LUT Address and Data Sizes
`define LUT_ADDR_WIDTH			8
`define LUT_DATA_WIDTH			8

`define RELU_WIDTH 				8
`define LF_OUT_WIDTH			8



// Weight & Bias Counts
`define HL_WEIGHT_COUNT   		64 * 128   	// 8192
`define HL_BIAS_COUNT      		64       	// 64
`define OL_WEIGHT_COUNT    		128 * 64   	// 8192
`define OL_BIAS_COUNT      		128      	// 128


// ANIDS Control Register Addresses
`define START_REG				0
`define N_REG					1
`define THRESHOLD_REG			2
`define RESULT_REG				3


// Indirect LUT Read/Write Registers
`define LUT_ADDR				4
`define LUT_DATA				5
`define LUT_CTRL				6
`define FREE_REG				7


// Hidden Layer Register Mapping
`define HL_WEIGHT_BASE			8 // we have 128 * 64 of these
`define HL_BIAS_BASE			`HL_WEIGHT_BASE + `HL_WEIGHT_COUNT // and 64 of these


// Output Layer Register Mapping
`define OL_WEIGHT_BASE			`HL_BIAS_BASE + `HL_BIAS_COUNT
`define OL_BIAS_BASE			`OL_WEIGHT_BASE + `OL_WEIGHT_COUNT


// ANIDS memory map borders
`define ANIDS_MAP_START   		`HL_WEIGHT_BASE
`define ANIDS_MAP_END     		`OL_BIAS_BASE + `OL_BIAS_COUNT
`define REG_COUNT				`ANIDS_MAP_END 	// (correct count due to 0-based indexing)


// Pipeline Stage Cycles
`define INPUT_LAYER_CYCLES 		1
`define HIDDEN_LAYER_CYCLES 	64
`define OUTPUT_LAYER_CYCLES 	64
`define LOOKUP_LAYER_CYCLES 	64
`define LOSS_FUNCTION_CYCLES 	64
`define OUTLIER_CYCLES 			1
`define RESULT_CYCLES 			1


// Pipeline Fill and Latency in cycles (pipefill = 259, latency = 130)
`define PIPE_FILL_CYCLES 		(`INPUT_LAYER_CYCLES + `HIDDEN_LAYER_CYCLES + `OUTPUT_LAYER_CYCLES + `LOOKUP_LAYER_CYCLES + `LOSS_FUNCTION_CYCLES + `OUTLIER_CYCLES + `RESULT_CYCLES)
`define LATENCY_IN_CYCLES 		(`LOOKUP_LAYER_CYCLES + `LOSS_FUNCTION_CYCLES + `OUTLIER_CYCLES + `RESULT_CYCLES )

ANIDS/src/core/loss_function.sv
// ANIDS Loss Function
`include "anids_defines.vh"

module loss_function (
		clk,
		resetN,
		enable,
		N,
		counter,
		x_in,
		function_0,
		function_1,
		result,
		ready
	);

	parameter FEATURE_PAIR_WIDTH = `LF_FEATURE_PAIR_WIDTH;
	parameter RESULT_IN_WIDTH    = `LF_RESULT_IN_WIDTH;
	parameter RESULT_WIDTH       = `LF_OUT_WIDTH;
	parameter COUNTER_WIDTH      = `PIPELINE_COUNTER_WIDTH;
	parameter ABS_WIDTH          = `LF_ABS_WIDTH;
	parameter PAIR_SUM_WIDTH     = `LF_PAIR_SUM_WIDTH;
	parameter ACC_WIDTH          = `LF_ACC_WIDTH;

	// ----------------------------------------------------------------------
	//                  		I/O Ports
	// ----------------------------------------------------------------------
	input  wire                                clk;
	input  wire                                resetN;
	input  wire                                enable;
	input  wire [`APB_DATA_WIDTH-1:0]          N;
	input  wire [COUNTER_WIDTH-1:0]            counter;
	input  wire [FEATURE_PAIR_WIDTH-1:0]       x_in;
	input  wire signed [RESULT_IN_WIDTH-1:0]   function_0;
	input  wire signed [RESULT_IN_WIDTH-1:0]   function_1;
	output reg  signed [RESULT_WIDTH-1:0]      result;
	output reg                                 ready;

	// ----------------------------------------------------------------------
	//                  		Datapath
	// ----------------------------------------------------------------------
	reg signed [ACC_WIDTH-1:0] acc;

	// Last valid pair-step for the current vector length.
	wire [COUNTER_WIDTH-1:0] last_pair_index =
		((N >> 1) - 1'b1);

	// Extend original feature bits into the same numeric space as the looked-up values.
	wire signed [RESULT_IN_WIDTH:0] x0_ext = x_in[0] ? 9'sd1 : 9'sd0;
	wire signed [RESULT_IN_WIDTH:0] x1_ext = x_in[1] ? 9'sd1 : 9'sd0;
	wire signed [RESULT_IN_WIDTH:0] r0_ext = {function_0[RESULT_IN_WIDTH-1], function_0};
	wire signed [RESULT_IN_WIDTH:0] r1_ext = {function_1[RESULT_IN_WIDTH-1], function_1};

	// Per-feature reconstruction error before magnitude.
	wire signed [RESULT_IN_WIDTH:0] delta_0 = x0_ext - r0_ext;
	wire signed [RESULT_IN_WIDTH:0] delta_1 = x1_ext - r1_ext;

	// Absolute error for each feature in the pair.
	wire [ABS_WIDTH-1:0] abs_0 = delta_0[RESULT_IN_WIDTH] ? -delta_0 : delta_0;
	wire [ABS_WIDTH-1:0] abs_1 = delta_1[RESULT_IN_WIDTH] ? -delta_1 : delta_1;

	// Combined per-cycle loss increment.
	wire [PAIR_SUM_WIDTH-1:0] pair_sum = abs_0 + abs_1;

	// Running accumulated loss value.
	wire signed [ACC_WIDTH-1:0] acc_next =
		acc + $signed({{(ACC_WIDTH-PAIR_SUM_WIDTH){1'b0}}, pair_sum});

	// TRUN8 keeps the sign bit and the top 7 remaining bits.
	wire signed [RESULT_WIDTH-1:0] trunc8 = acc_next[ACC_WIDTH-1 -: RESULT_WIDTH];

	// ----------------------------------------------------------------------
	//                  		Sequential Logic
	// ----------------------------------------------------------------------
	always @(posedge clk or negedge resetN) begin
		if (!resetN) begin
			acc    <= #1 {ACC_WIDTH{1'b0}};
			result <= #1 {RESULT_WIDTH{1'b0}};
			ready  <= #1 1'b0;
		end
		else if (!enable) begin
			acc   <= #1 {ACC_WIDTH{1'b0}};
			ready <= #1 1'b0;
		end
		else begin
			ready <= #1 1'b0;

			if (counter == last_pair_index) begin
				acc    <= #1 {ACC_WIDTH{1'b0}};
				result <= #1 trunc8;
				ready  <= #1 1'b1;
			end
			else begin
				acc <= #1 acc_next;
			end
		end
	end
endmodule

ANIDS/tb/integration/loss_function_tb.sv
// Purpose: verifies loss accumulation over feature/function pairs, signed values, truncation, and ready timing.
// ANIDS - Loss Function Testbench
`timescale 1ns/100ps
`include "anids_defines.vh"

module loss_function_tb;

	localparam FEATURE_PAIR_WIDTH = `LF_FEATURE_PAIR_WIDTH;
	localparam RESULT_IN_WIDTH    = `LF_RESULT_IN_WIDTH;
	localparam RESULT_WIDTH       = `LF_OUT_WIDTH;
	localparam COUNTER_WIDTH      = `PIPELINE_COUNTER_WIDTH;

	reg                               clk;
	reg                               resetN;
	reg                               enable;
	reg  [`APB_DATA_WIDTH-1:0]        N;
	reg  [COUNTER_WIDTH-1:0]          counter;
	reg  [FEATURE_PAIR_WIDTH-1:0]     x_in;
	reg  signed [RESULT_IN_WIDTH-1:0] function_0;
	reg  signed [RESULT_IN_WIDTH-1:0] function_1;
	wire signed [RESULT_WIDTH-1:0]    result;
	wire                              ready;

	integer                           acc_model;

	loss_function dut (
		.clk        (clk),
		.resetN     (resetN),
		.enable     (enable),
		.N          (N),
		.counter    (counter),
		.x_in       (x_in),
		.function_0 (function_0),
		.function_1 (function_1),
		.result     (result),
		.ready      (ready)
	);

	always #2.5 clk = ~clk;

	initial begin
		$dumpfile("loss_function_tb.vcd");
		$dumpvars(0, loss_function_tb);

		clk        = 1'b0;
		resetN     = 1'b0;
		enable     = 1'b0;
		N          = 8'd2;
		counter    = {COUNTER_WIDTH{1'b0}};
		x_in       = {FEATURE_PAIR_WIDTH{1'b0}};
		function_0 = '0;
		function_1 = '0;
		acc_model  = 0;

		#2;
		check_outputs(1'b0, 8'sd0, "reset clears outputs");

		resetN = 1'b1;
		@(posedge clk);
		#2;
		check_outputs(1'b0, 8'sd0, "idle after reset");

		run_single_pair_test;
		run_two_pair_accumulation_test;
		run_negative_function_test;
		run_disable_clears_accumulator_test;

		$display("LOSS_FUNCTION TB PASSED");
		$finish;
	end

	task run_single_pair_test;
		integer expected;
	begin
		$display("SECTION: single pair");
		reset_runtime_only;

		N          = 8'd2;
		enable     = 1'b1;
		counter    = 7'd0;
		x_in       = 2'b01;
		function_0 = 8'sd0;
		function_1 = 8'sd1;

		expected = trunc8_value(model_pair_loss(x_in, function_0, function_1));

		@(posedge clk);
		#2;
		check_outputs(1'b1, expected[RESULT_WIDTH-1:0], "single pair result matches");

		enable = 1'b0;
		@(posedge clk);
		#2;
		check_outputs(1'b0, expected[RESULT_WIDTH-1:0], "result holds after disable");
	end
	endtask

	task run_two_pair_accumulation_test;
		integer expected;
	begin
		$display("SECTION: two-pair accumulation");
		reset_runtime_only;

		N          = 8'd4;
		enable     = 1'b1;
		counter    = 7'd0;
		x_in       = 2'b11;
		function_0 = -8'sd32;
		function_1 = 8'sd20;
		acc_model  = model_pair_loss(x_in, function_0, function_1);

		@(posedge clk);
		#2;
		check_outputs(1'b0, 8'sd0, "first pair accumulates without ready");

		counter    = 7'd1;
		x_in       = 2'b10;
		function_0 = 8'sd64;
		function_1 = -8'sd64;
		acc_model  = acc_model + model_pair_loss(x_in, function_0, function_1);
		expected   = trunc8_value(acc_model);

		@(posedge clk);
		#2;
		check_outputs(1'b1, expected[RESULT_WIDTH-1:0], "two-pair accumulation matches");
	end
	endtask

	task run_negative_function_test;
		integer expected;
	begin
		$display("SECTION: signed looked-up values");
		reset_runtime_only;

		N          = 8'd2;
		enable     = 1'b1;
		counter    = 7'd0;
		x_in       = 2'b00;
		function_0 = -8'sd32;
		function_1 = -8'sd64;

		expected = trunc8_value(model_pair_loss(x_in, function_0, function_1));

		@(posedge clk);
		#2;
		check_outputs(1'b1, expected[RESULT_WIDTH-1:0], "negative looked-up values are sign-extended correctly");
	end
	endtask

	task run_disable_clears_accumulator_test;
	begin
		$display("SECTION: disable clears accumulator");
		reset_runtime_only;

		N          = 8'd4;
		enable     = 1'b1;
		counter    = 7'd0;
		x_in       = 2'b11;
		function_0 = 8'sd32;
		function_1 = 8'sd32;

		@(posedge clk);
		#2;
		check_outputs(1'b0, 8'sd0, "partial accumulation still not ready");

		enable = 1'b0;
		@(posedge clk);
		#2;
		check_outputs(1'b0, 8'sd0, "disable clears in-flight accumulation");

		enable     = 1'b1;
		N          = 8'd2;
		counter    = 7'd0;
		x_in       = 2'b01;
		function_0 = 8'sd0;
		function_1 = 8'sd0;

		@(posedge clk);
		#2;
		check_outputs(1'b1, 8'sd0, "restart begins from a clean accumulator");
	end
	endtask

	task reset_runtime_only;
	begin
		enable     = 1'b0;
		counter    = {COUNTER_WIDTH{1'b0}};
		x_in       = {FEATURE_PAIR_WIDTH{1'b0}};
		function_0 = '0;
		function_1 = '0;
		acc_model  = 0;
		@(posedge clk);
		#2;
	end
	endtask

	function integer abs_int;
		input integer value;
	begin
		if (value < 0)
			abs_int = -value;
		else
			abs_int = value;
	end
	endfunction

	function integer model_pair_loss;
		input [FEATURE_PAIR_WIDTH-1:0]            pair_x;
		input signed [RESULT_IN_WIDTH-1:0]        pair_f0;
		input signed [RESULT_IN_WIDTH-1:0]        pair_f1;
	begin
		model_pair_loss =
			abs_int((pair_x[0] ? 1 : 0) - pair_f0) +
			abs_int((pair_x[1] ? 1 : 0) - pair_f1);
	end
	endfunction

	function integer trunc8_value;
		input integer acc_value;
	begin
		trunc8_value = acc_value >>> 7;
	end
	endfunction

	task check_outputs(
		input                              expected_ready,
		input signed [RESULT_WIDTH-1:0]    expected_result,
		input [255:0]                      test_name
	);
	begin
		if (ready !== expected_ready || result !== expected_result) begin
			$error("FAIL: %0s | ready=%0b expected_ready=%0b result=%0d expected_result=%0d",
				test_name, ready, expected_ready, result, expected_result);
			$finish;
		end
		else begin
			$display("PASS: %0s", test_name);
		end
	end
	endtask

endmodule

Outputs/vcd/loss_function_tb.vcd
$date
	Tue Jun 09 14:53:37 2026
$end
$version
	Icarus Verilog
$end
$timescale
	100ps
$end
$scope module loss_function_tb $end
$var wire 8 ! result [7:0] $end
$var wire 1 " ready $end
$var parameter 32 # COUNTER_WIDTH $end
$var parameter 32 $ FEATURE_PAIR_WIDTH $end
$var parameter 32 % RESULT_IN_WIDTH $end
$var parameter 32 & RESULT_WIDTH $end
$var reg 8 ' N [7:0] $end
$var reg 1 ( clk $end
$var reg 7 ) counter [6:0] $end
$var reg 1 * enable $end
$var reg 8 + function_0 [7:0] $end
$var reg 8 , function_1 [7:0] $end
$var reg 1 - resetN $end
$var reg 2 . x_in [1:0] $end
$var integer 32 / acc_model [31:0] $end
$scope function abs_int $end
$var integer 32 0 value [31:0] $end
$upscope $end
$scope function model_pair_loss $end
$var reg 8 1 pair_f0 [7:0] $end
$var reg 8 2 pair_f1 [7:0] $end
$var reg 2 3 pair_x [1:0] $end
$upscope $end
$scope function trunc8_value $end
$var integer 32 4 acc_value [31:0] $end
$upscope $end
$scope module dut $end
$var wire 8 5 N [7:0] $end
$var wire 1 ( clk $end
$var wire 7 6 counter [6:0] $end
$var wire 1 * enable $end
$var wire 8 7 function_0 [7:0] $end
$var wire 8 8 function_1 [7:0] $end
$var wire 1 - resetN $end
$var wire 2 9 x_in [1:0] $end
$var wire 9 : x1_ext [8:0] $end
$var wire 9 ; x0_ext [8:0] $end
$var wire 8 < trunc8 [7:0] $end
$var wire 9 = r1_ext [8:0] $end
$var wire 9 > r0_ext [8:0] $end
$var wire 9 ? pair_sum [8:0] $end
$var wire 7 @ last_pair_index [6:0] $end
$var wire 9 A delta_1 [8:0] $end
$var wire 9 B delta_0 [8:0] $end
$var wire 15 C acc_next [14:0] $end
$var wire 8 D abs_1 [7:0] $end
$var wire 8 E abs_0 [7:0] $end
$var parameter 32 F ABS_WIDTH $end
$var parameter 32 G ACC_WIDTH $end
$var parameter 32 H COUNTER_WIDTH $end
$var parameter 32 I FEATURE_PAIR_WIDTH $end
$var parameter 32 J PAIR_SUM_WIDTH $end
$var parameter 32 K RESULT_IN_WIDTH $end
$var parameter 32 L RESULT_WIDTH $end
$var reg 15 M acc [14:0] $end
$var reg 1 " ready $end
$var reg 8 N result [7:0] $end
$upscope $end
$scope task check_outputs $end
$var reg 1 O expected_ready $end
$var reg 8 P expected_result [7:0] $end
$var reg 256 Q test_name [255:0] $end
$upscope $end
$scope task reset_runtime_only $end
$upscope $end
$scope task run_disable_clears_accumulator_test $end
$upscope $end
$scope task run_negative_function_test $end
$var integer 32 R expected [31:0] $end
$upscope $end
$scope task run_single_pair_test $end
$var integer 32 S expected [31:0] $end
$upscope $end
$scope task run_two_pair_accumulation_test $end
$var integer 32 T expected [31:0] $end
$upscope $end
$upscope $end
$enddefinitions $end
$comment Show the parameter values. $end
$dumpall
b1000 L
b1000 K
b1001 J
b10 I
b111 H
b1111 G
b1000 F
b1000 &
b1000 %
b10 $
b111 #
$end
#0
$dumpvars
bx T
bx S
bx R
bx Q
bx P
xO
bx N
bx M
b0 E
b0 D
bx C
b0 B
b0 A
b0 @
b0 ?
b0 >
b0 =
bx <
b0 ;
b0 :
b0 9
b0 8
b0 7
b0 6
b10 5
bx 4
bx 3
bx 2
bx 1
bx 0
b0 /
b0 .
0-
b0 ,
b0 +
0*
b0 )
0(
b10 '
x"
bx !
$end
#10
b0 <
0"
b0 !
b0 N
b0 C
b0 M
#20
1-
b111001001100101011100110110010101110100001000000110001101101100011001010110000101110010011100110010000001101111011101010111010001110000011101010111010001110011 Q
b0 P
0O
#25
1(
#45
b1101001011001000110110001100101001000000110000101100110011101000110010101110010001000000111001001100101011100110110010101110100 Q
#50
0(
#75
1(
#95
b1 E
b0 <
b10 C
b10 ?
b1 D
b1 B
b1 ;
b0 S
b10 4
b11111111111111111111111111111111 0
b1 3
b0 1
b1 2
b111111111 A
b1 =
b1 ,
b1 8
b1 .
b1 9
1*
#100
0(
#125
1(
#135
1"
#145
0*
b111001101101001011011100110011101101100011001010010000001110000011000010110100101110010001000000111001001100101011100110111010101101100011101000010000001101101011000010111010001100011011010000110010101110011 Q
1O
#150
0(
#175
1(
#185
0"
#195
b0 E
b0 C
b0 ?
b0 D
b0 B
b0 ;
b0 A
b0 =
b0 ,
b0 8
b0 .
b0 9
b111001001100101011100110111010101101100011101000010000001101000011011110110110001100100011100110010000001100001011001100111010001100101011100100010000001100100011010010111001101100001011000100110110001100101 Q
0O
#200
0(
#225
1(
#245
b0 <
b10011 D
b110100 C
b110100 ?
b100001 E
b1 ;
b1 :
b1 @
b110100 /
b11111111111111111111111111101101 0
b11 3
b11100000 1
b10100 2
b111101101 A
b10100 =
b10100 ,
b10100 8
b100001 B
b111100000 >
b11100000 +
b11100000 7
b11 .
b11 9
1*
b100 '
b100 5
#250
0(
#275
1(
#285
b1101000 C
b110100 M
#295
b1 <
b1000001 D
b10110101 C
b10000001 ?
b1000000 E
b0 ;
b1 T
b10110101 4
b10110101 /
b1000001 0
b10 3
b1000000 1
b11000000 2
b1000001 A
b111000000 =
b11000000 ,
b11000000 8
b111000000 B
b1000000 >
b1000000 +
b1000000 7
b10 .
b10 9
b1 )
b1 6
b111010000100000011100000110000101101001011100100010000001100001011000110110001101110101011011010111010101101100011000010111010001100101011100110010000001110111011010010111010001101000011011110111010101110100001000000111001001100101011000010110010001111001 Q
#300
0(
#325
1(
#335
1"
b1 !
b1 N
b10000001 C
b0 M
#345
b0 <
b0 D
b0 C
b0 ?
b0 E
b0 :
b0 /
b0 A
b0 =
b0 ,
b0 8
b0 B
b0 >
b0 +
b0 7
b0 .
b0 9
b0 )
b0 6
0*
b111010001110111011011110010110101110000011000010110100101110010001000000110000101100011011000110111010101101101011101010110110001100001011101000110100101101111011011100010000001101101011000010111010001100011011010000110010101110011 Q
b1 P
1O
#350
0(
#375
1(
#385
0"
#395
b0 <
b1000000 D
b1100000 C
b1100000 ?
b100000 E
b0 @
b0 R
b1100000 4
b1000000 0
b0 3
b11100000 1
b1000000 A
b111000000 =
b11000000 ,
b11000000 8
b100000 B
b111100000 >
b11100000 +
b11100000 7
1*
b10 '
b10 5
#400
0(
#425
1(
#435
1"
b0 !
b0 N
#445
b0 D
b0 C
b0 ?
b0 E
b0 A
b0 =
b0 ,
b0 8
b0 B
b0 >
b0 +
b0 7
0*
b110110001110101011001010111001100100000011000010111001001100101001000000111001101101001011001110110111000101101011001010111100001110100011001010110111001100100011001010110010000100000011000110110111101110010011100100110010101100011011101000110110001111001 Q
b0 P
#450
0(
#475
1(
#485
0"
#495
b0 <
b11111 D
b111110 C
b111110 ?
b11111 E
b1 ;
b1 :
b1 @
b111100001 A
b100000 =
b100000 ,
b100000 8
b111100001 B
b100000 >
b100000 +
b100000 7
b11 .
b11 9
1*
b100 '
b100 5
#500
0(
#525
1(
#535
b1111100 C
b111110 M
#545
0*
b110100101100001011011000010000001100001011000110110001101110101011011010111010101101100011000010111010001101001011011110110111000100000011100110111010001101001011011000110110000100000011011100110111101110100001000000111001001100101011000010110010001111001 Q
0O
#550
0(
#575
1(
#585
b111110 C
b0 M
#595
b0 <
b0 D
b1 C
b1 ?
b1 E
b0 :
b0 @
b0 A
b0 =
b0 ,
b0 8
b1 B
b0 >
b0 +
b0 7
b1 .
b1 9
b10 '
b10 5
1*
b110110001100101001000000110001101101100011001010110000101110010011100110010000001101001011011100010110101100110011011000110100101100111011010000111010000100000011000010110001101100011011101010110110101110101011011000110000101110100011010010110111101101110 Q
#600
0(
#625
1(
#635
1"
#645
b10000001100010011001010110011101101001011011100111001100100000011001100111001001101111011011010010000001100001001000000110001101101100011001010110000101101110001000000110000101100011011000110111010101101101011101010110110001100001011101000110111101110010 Q
1O
