ANIDS/anids_defines.vh
// ANIDS Defines
// Clock Period, this is 5ns period (200MHz clock)
`define CLK_PERIOD				16'd5


// APB can work with 8, 16, 32 bit data width
`define APB_DATA_WIDTH			8
`define APB_ADDR_WIDTH			16 							// 15 bits needed, but we use 16.


// DMA Data Width is input vector size, which is 128 bits
`define DMA_DATA_WIDTH			128

// Memory Fetch Unit widths
`define MFU_DATA_WIDTH			`DMA_DATA_WIDTH
`define MFU_FEATURE_WIDTH		`MFU_DATA_WIDTH				// stored feature vector width

// Pipeline Manager widths and history depth
`define PIPELINE_VECTOR_WIDTH	`MFU_FEATURE_WIDTH			// vector width propagated through pipeline manager
`define PIPELINE_COUNTER_WIDTH	7							// counter width for indices 0..127
`define PIPELINE_HISTORY_DEPTH	2							// number of coarse vector buffers before validation
`define PIPELINE_STAGE_CYCLES	64							// 128-bit vector processed over 64 cycles
`define PIPELINE_STAGE_COUNT_W	6							// counter width for 0..63 stage timing

// Input layer widths
`define INPUT_LAYER_FEATURE_WIDTH	`PIPELINE_VECTOR_WIDTH	// full feature vector width seen by input layer
`define INPUT_LAYER_PAIR_WIDTH		2						// number of feature bits processed per counter step

// Hidden layer unit widths
`define HL_FEATURE_PAIR_WIDTH		`INPUT_LAYER_PAIR_WIDTH	// number of feature bits consumed per cycle
`define HL_WEIGHT_WIDTH				8						// signed Q0.7 weight width
`define HL_BIAS_WIDTH				8						// signed Q0.7 bias width
`define HL_RESULT_WIDTH				8						// signed Q0.7 hidden neuron output width
`define HL_PAIR_SUM_WIDTH			9						// sum of two weighted feature contributions
`define HL_ACC_WIDTH				15						// accumulation register width before truncation

// Output layer unit widths
`define OL_INPUT_WIDTH				8						// signed Q0.7 hidden-layer input width
`define OL_WEIGHT_WIDTH				8						// signed Q0.7 output-layer weight width
`define OL_BIAS_WIDTH				8						// signed Q0.7 output-layer bias width
`define OL_RESULT_WIDTH				8						// signed Q0.7 output-layer result width
`define OL_PRODUCT_WIDTH			16						// full signed 8x8 multiply width
`define OL_TRUNC_PRODUCT_WIDTH		8						// product truncated back to Q0.7
`define OL_ACC_WIDTH				15						// accumulation width before final truncation

// Loss function widths
`define LF_FEATURE_PAIR_WIDTH		`INPUT_LAYER_PAIR_WIDTH	// number of original feature bits consumed per cycle
`define LF_RESULT_IN_WIDTH			8						// compared result width
`define LF_ABS_WIDTH				8						// absolute delta width
`define LF_PAIR_SUM_WIDTH			9						// sum of two absolute deltas
`define LF_ACC_WIDTH				15						// accumulation register width before truncation

// Sigmoid LUT address mapper widths
`define MMAP_IN_WIDTH				8						// signed Q0.7 value width before LUT lookup
`define MMAP_ADDR_WIDTH				`LUT_ADDR_WIDTH		// LUT address width after mapping

// LUT Address and Data Sizes
`define LUT_ADDR_WIDTH			8
`define LUT_DATA_WIDTH			8

`define RELU_WIDTH 				8
`define LF_OUT_WIDTH			8



// Weight & Bias Counts
`define HL_WEIGHT_COUNT   		64 * 128   	// 8192
`define HL_BIAS_COUNT      		64       	// 64
`define OL_WEIGHT_COUNT    		128 * 64   	// 8192
`define OL_BIAS_COUNT      		128      	// 128


// ANIDS Control Register Addresses
`define START_REG				0
`define N_REG					1
`define THRESHOLD_REG			2
`define RESULT_REG				3


// Indirect LUT Read/Write Registers
`define LUT_ADDR				4
`define LUT_DATA				5
`define LUT_CTRL				6
`define FREE_REG				7


// Hidden Layer Register Mapping
`define HL_WEIGHT_BASE			8 // we have 128 * 64 of these
`define HL_BIAS_BASE			`HL_WEIGHT_BASE + `HL_WEIGHT_COUNT // and 64 of these


// Output Layer Register Mapping
`define OL_WEIGHT_BASE			`HL_BIAS_BASE + `HL_BIAS_COUNT
`define OL_BIAS_BASE			`OL_WEIGHT_BASE + `OL_WEIGHT_COUNT


// ANIDS memory map borders
`define ANIDS_MAP_START   		`HL_WEIGHT_BASE
`define ANIDS_MAP_END     		`OL_BIAS_BASE + `OL_BIAS_COUNT
`define REG_COUNT				`ANIDS_MAP_END 	// (correct count due to 0-based indexing)


// Pipeline Stage Cycles
`define INPUT_LAYER_CYCLES 		1
`define HIDDEN_LAYER_CYCLES 	64
`define OUTPUT_LAYER_CYCLES 	64
`define LOOKUP_LAYER_CYCLES 	64
`define LOSS_FUNCTION_CYCLES 	64
`define OUTLIER_CYCLES 			1
`define RESULT_CYCLES 			1


// Pipeline Fill and Latency in cycles (pipefill = 259, latency = 130)
`define PIPE_FILL_CYCLES 		(`INPUT_LAYER_CYCLES + `HIDDEN_LAYER_CYCLES + `OUTPUT_LAYER_CYCLES + `LOOKUP_LAYER_CYCLES + `LOSS_FUNCTION_CYCLES + `OUTLIER_CYCLES + `RESULT_CYCLES)
`define LATENCY_IN_CYCLES 		(`LOOKUP_LAYER_CYCLES + `LOSS_FUNCTION_CYCLES + `OUTLIER_CYCLES + `RESULT_CYCLES )

ANIDS/src/core/spram8x256_cb.sv

// this is a dummy module so we can actually compile the project.
// the real project uses the lab memory file (which is under NDA).
module spram8x256_cb (
	CEB,	// clock input used by the real macro wrapper
	CSB,	// chip select, active low
	WEB,	// write enable, active low
	OEB,	// output enable, active low
	A,		// address
	I, 		// write input
	O 		// read output
);

	localparam integer DATA_WIDTH = 8;
	localparam integer DEPTH      = 256;
	localparam integer ADDR_WIDTH = 8;

	input  wire                  CEB;
	input  wire                  CSB;
	input  wire                  WEB;
	input  wire                  OEB;
	input  wire [ADDR_WIDTH-1:0] A;
	input  wire [DATA_WIDTH-1:0] I;
	output reg  [DATA_WIDTH-1:0] O;

	reg [DATA_WIDTH-1:0] mem [0:DEPTH-1];
	integer i;

	initial begin
		O = {DATA_WIDTH{1'b0}};
		for (i = 0; i < DEPTH; i = i + 1)
			mem[i] = {DATA_WIDTH{1'b0}};
	end

	always @(negedge CEB) begin
		if (!CSB) begin
			if (!WEB) begin
				mem[A] <= I;
			end
			else if (!OEB) begin
				O <= mem[A];
			end
		end
	end

endmodule

ANIDS/tb/integration/lut_ram_tb.sv
// Purpose: verifies full-address read/write behavior of the LUT RAM macro used by the lookup layer.
// ANIDS - LUT RAM Read/Write Testbench
`timescale 1ns/100ps
`include "anids_defines.vh"

module lut_ram_tb;

  localparam DATA_WIDTH = `LUT_DATA_WIDTH;
  localparam ADDR_WIDTH = `LUT_ADDR_WIDTH;
  localparam RAM_DEPTH  = 1 << ADDR_WIDTH;

  // DUT signals
  reg                       CEB;
  reg                       CSB;
  reg                       WEB;
  reg                       OEB;
  reg  [ADDR_WIDTH-1:0]     A;
  reg  [DATA_WIDTH-1:0]     I;
  wire [DATA_WIDTH-1:0]     O;

  // Clock generation: 200 MHz (period 5ns)
  always #2.5 CEB = ~CEB;

  // DUT
  spram8x256_cb dut (
    .CEB      (CEB),
    .CSB      (CSB),
    .WEB      (WEB),
    .OEB      (OEB),
    .A        (A),
    .I        (I),
    .O        (O)
  );

  integer idx;
  integer errors;

  initial begin
    $dumpfile("lut_ram_tb.vcd");
    $dumpvars(0, lut_ram_tb);

    // Reset and defaults
    CEB     = 1'b0;
    CSB     = 1'b1;
    WEB     = 1'b1;
    OEB     = 1'b0;
    A       = {ADDR_WIDTH{1'b0}};
    I       = {DATA_WIDTH{1'b0}};
    errors  = 0;

    // Initial idle cycles before access
    repeat (2) @(negedge CEB);

    // Write phase: write each location with its address value
    for (idx = 0; idx < RAM_DEPTH; idx = idx + 1) begin
      CSB <= 1'b0;
      WEB <= 1'b0;
      A   <= idx[ADDR_WIDTH-1:0];
      I   <= idx[DATA_WIDTH-1:0];
      @(negedge CEB);
    end

    // Return the RAM to idle before the read phase.
    CSB <= 1'b1;
    WEB <= 1'b1;
    @(negedge CEB);

    // Read/verify phase.
    for (idx = 0; idx < RAM_DEPTH; idx = idx + 1) begin
      CSB <= 1'b0;
      WEB <= 1'b1;
      A   <= idx[ADDR_WIDTH-1:0];
      @(negedge CEB);
      #1;
      if (O !== idx[DATA_WIDTH-1:0]) begin
        $error("Mismatch at addr %0d: got %0h expected %0h",
               idx, O, idx[DATA_WIDTH-1:0]);
        errors = errors + 1;
      end else begin
        $display("PASS addr %0d data %0h", idx, O);
      end
    end

    if (errors == 0) begin
      $display("LUT_RAM TB PASSED (%0d entries)", RAM_DEPTH);
    end
    else begin
      $display("LUT_RAM TB FAILED with %0d errors", errors);
      $fatal(1);
    end

    $finish;
  end
endmodule

Outputs/vcd/lut_ram_tb.vcd
$date
	Tue Jun 09 14:53:38 2026
$end
$version
	Icarus Verilog
$end
$timescale
	100ps
$end
$scope module lut_ram_tb $end
$var wire 8 ! O [7:0] $end
$var parameter 32 " ADDR_WIDTH $end
$var parameter 32 # DATA_WIDTH $end
$var parameter 40 $ RAM_DEPTH $end
$var reg 8 % A [7:0] $end
$var reg 1 & CEB $end
$var reg 1 ' CSB $end
$var reg 8 ( I [7:0] $end
$var reg 1 ) OEB $end
$var reg 1 * WEB $end
$var integer 32 + errors [31:0] $end
$var integer 32 , idx [31:0] $end
$scope module dut $end
$var wire 8 - A [7:0] $end
$var wire 1 & CEB $end
$var wire 1 ' CSB $end
$var wire 8 . I [7:0] $end
$var wire 1 ) OEB $end
$var wire 1 * WEB $end
$var parameter 32 / ADDR_WIDTH $end
$var parameter 32 0 DATA_WIDTH $end
$var parameter 32 1 DEPTH $end
$var reg 8 2 O [7:0] $end
$var integer 32 3 i [31:0] $end
$upscope $end
$upscope $end
$enddefinitions $end
$comment Show the parameter values. $end
$dumpall
b100000000 1
b1000 0
b1000 /
b100000000 $
b1000 #
b1000 "
$end
#0
$dumpvars
b100000000 3
b0 2
b0 .
b0 -
bx ,
b0 +
1*
0)
b0 (
1'
0&
b0 %
b0 !
$end
#25
1&
#50
0&
#75
1&
#100
0*
0'
b0 ,
0&
#125
1&
#150
b1 (
b1 .
b1 %
b1 -
b1 ,
0&
#175
1&
#200
b10 (
b10 .
b10 %
b10 -
b10 ,
0&
#225
1&
#250
b11 (
b11 .
b11 %
b11 -
b11 ,
0&
#275
1&
#300
b100 (
b100 .
b100 %
b100 -
b100 ,
0&
#325
1&
#350
b101 (
b101 .
b101 %
b101 -
b101 ,
0&
#375
1&
#400
b110 (
b110 .
b110 %
b110 -
b110 ,
0&
#425
1&
#450
b111 (
b111 .
b111 %
b111 -
b111 ,
0&
#475
1&
#500
b1000 (
b1000 .
b1000 %
b1000 -
b1000 ,
0&
#525
1&
#550
b1001 (
b1001 .
b1001 %
b1001 -
b1001 ,
0&
#575
1&
#600
b1010 (
b1010 .
b1010 %
b1010 -
b1010 ,
0&
#625
1&
#650
b1011 (
b1011 .
b1011 %
b1011 -
b1011 ,
0&
#675
1&
#700
b1100 (
b1100 .
b1100 %
b1100 -
b1100 ,
0&
#725
1&
#750
b1101 (
b1101 .
b1101 %
b1101 -
b1101 ,
0&
#775
1&
#800
b1110 (
b1110 .
b1110 %
b1110 -
b1110 ,
0&
#825
1&
#850
b1111 (
b1111 .
b1111 %
b1111 -
b1111 ,
0&
#875
1&
#900
b10000 (
b10000 .
b10000 %
b10000 -
b10000 ,
0&
#925
1&
#950
b10001 (
b10001 .
b10001 %
b10001 -
b10001 ,
0&
#975
1&
#1000
b10010 (
b10010 .
b10010 %
b10010 -
b10010 ,
0&
#1025
1&
#1050
b10011 (
b10011 .
b10011 %
b10011 -
b10011 ,
0&
#1075
1&
#1100
b10100 (
b10100 .
b10100 %
b10100 -
b10100 ,
0&
#1125
1&
#1150
b10101 (
b10101 .
b10101 %
b10101 -
b10101 ,
0&
#1175
1&
#1200
b10110 (
b10110 .
b10110 %
b10110 -
b10110 ,
0&
#1225
1&
#1250
b10111 (
b10111 .
b10111 %
b10111 -
b10111 ,
0&
#1275
1&
#1300
b11000 (
b11000 .
b11000 %
b11000 -
b11000 ,
0&
#1325
1&
#1350
b11001 (
b11001 .
b11001 %
b11001 -
b11001 ,
0&
#1375
1&
#1400
b11010 (
b11010 .
b11010 %
b11010 -
b11010 ,
0&
#1425
1&
#1450
b11011 (
b11011 .
b11011 %
b11011 -
b11011 ,
0&
#1475
1&
#1500
b11100 (
b11100 .
b11100 %
b11100 -
b11100 ,
0&
#1525
1&
#1550
b11101 (
b11101 .
b11101 %
b11101 -
b11101 ,
0&
#1575
1&
#1600
b11110 (
b11110 .
b11110 %
b11110 -
b11110 ,
0&
#1625
1&
#1650
b11111 (
b11111 .
b11111 %
b11111 -
b11111 ,
0&
#1675
1&
#1700
b100000 (
b100000 .
b100000 %
b100000 -
b100000 ,
0&
#1725
1&
#1750
b100001 (
b100001 .
b100001 %
b100001 -
b100001 ,
0&
#1775
1&
#1800
b100010 (
b100010 .
b100010 %
b100010 -
b100010 ,
0&
#1825
1&
#1850
b100011 (
b100011 .
b100011 %
b100011 -
b100011 ,
0&
#1875
1&
#1900
b100100 (
b100100 .
b100100 %
b100100 -
b100100 ,
0&
#1925
1&
#1950
b100101 (
b100101 .
b100101 %
b100101 -
b100101 ,
0&
#1975
1&
#2000
b100110 (
b100110 .
b100110 %
b100110 -
b100110 ,
0&
#2025
1&
#2050
b100111 (
b100111 .
b100111 %
b100111 -
b100111 ,
0&
#2075
1&
#2100
b101000 (
b101000 .
b101000 %
b101000 -
b101000 ,
0&
#2125
1&
#2150
b101001 (
b101001 .
b101001 %
b101001 -
b101001 ,
0&
#2175
1&
#2200
b101010 (
b101010 .
b101010 %
b101010 -
b101010 ,
0&
#2225
1&
#2250
b101011 (
b101011 .
b101011 %
b101011 -
b101011 ,
0&
#2275
1&
#2300
b101100 (
b101100 .
b101100 %
b101100 -
b101100 ,
0&
#2325
1&
#2350
b101101 (
b101101 .
b101101 %
b101101 -
b101101 ,
0&
#2375
1&
#2400
b101110 (
b101110 .
b101110 %
b101110 -
b101110 ,
0&
#2425
1&
#2450
b101111 (
b101111 .
b101111 %
b101111 -
b101111 ,
0&
#2475
1&
#2500
b110000 (
b110000 .
b110000 %
b110000 -
b110000 ,
0&
#2525
1&
#2550
b110001 (
b110001 .
b110001 %
b110001 -
b110001 ,
0&
#2575
1&
#2600
b110010 (
b110010 .
b110010 %
b110010 -
b110010 ,
0&
#2625
1&
#2650
b110011 (
b110011 .
b110011 %
b110011 -
b110011 ,
0&
#2675
1&
#2700
b110100 (
b110100 .
b110100 %
b110100 -
b110100 ,
0&
#2725
1&
#2750
b110101 (
b110101 .
b110101 %
b110101 -
b110101 ,
0&
#2775
1&
#2800
b110110 (
b110110 .
b110110 %
b110110 -
b110110 ,
0&
#2825
1&
#2850
b110111 (
b110111 .
b110111 %
b110111 -
b110111 ,
0&
#2875
1&
#2900
b111000 (
b111000 .
b111000 %
b111000 -
b111000 ,
0&
#2925
1&
#2950
b111001 (
b111001 .
b111001 %
b111001 -
b111001 ,
0&
#2975
1&
#3000
b111010 (
b111010 .
b111010 %
b111010 -
b111010 ,
0&
#3025
1&
#3050
b111011 (
b111011 .
b111011 %
b111011 -
b111011 ,
0&
#3075
1&
#3100
b111100 (
b111100 .
b111100 %
b111100 -
b111100 ,
0&
#3125
1&
#3150
b111101 (
b111101 .
b111101 %
b111101 -
b111101 ,
0&
#3175
1&
#3200
b111110 (
b111110 .
b111110 %
b111110 -
b111110 ,
0&
#3225
1&
#3250
b111111 (
b111111 .
b111111 %
b111111 -
b111111 ,
0&
#3275
1&
#3300
b1000000 (
b1000000 .
b1000000 %
b1000000 -
b1000000 ,
0&
#3325
1&
#3350
b1000001 (
b1000001 .
b1000001 %
b1000001 -
b1000001 ,
0&
#3375
1&
#3400
b1000010 (
b1000010 .
b1000010 %
b1000010 -
b1000010 ,
0&
#3425
1&
#3450
b1000011 (
b1000011 .
b1000011 %
b1000011 -
b1000011 ,
0&
#3475
1&
#3500
b1000100 (
b1000100 .
b1000100 %
b1000100 -
b1000100 ,
0&
#3525
1&
#3550
b1000101 (
b1000101 .
b1000101 %
b1000101 -
b1000101 ,
0&
#3575
1&
#3600
b1000110 (
b1000110 .
b1000110 %
b1000110 -
b1000110 ,
0&
#3625
1&
#3650
b1000111 (
b1000111 .
b1000111 %
b1000111 -
b1000111 ,
0&
#3675
1&
#3700
b1001000 (
b1001000 .
b1001000 %
b1001000 -
b1001000 ,
0&
#3725
1&
#3750
b1001001 (
b1001001 .
b1001001 %
b1001001 -
b1001001 ,
0&
#3775
1&
#3800
b1001010 (
b1001010 .
b1001010 %
b1001010 -
b1001010 ,
0&
#3825
1&
#3850
b1001011 (
b1001011 .
b1001011 %
b1001011 -
b1001011 ,
0&
#3875
1&
#3900
b1001100 (
b1001100 .
b1001100 %
b1001100 -
b1001100 ,
0&
#3925
1&
#3950
b1001101 (
b1001101 .
b1001101 %
b1001101 -
b1001101 ,
0&
#3975
1&
#4000
b1001110 (
b1001110 .
b1001110 %
b1001110 -
b1001110 ,
0&
#4025
1&
#4050
b1001111 (
b1001111 .
b1001111 %
b1001111 -
b1001111 ,
0&
#4075
1&
#4100
b1010000 (
b1010000 .
b1010000 %
b1010000 -
b1010000 ,
0&
#4125
1&
#4150
b1010001 (
b1010001 .
b1010001 %
b1010001 -
b1010001 ,
0&
#4175
1&
#4200
b1010010 (
b1010010 .
b1010010 %
b1010010 -
b1010010 ,
0&
#4225
1&
#4250
b1010011 (
b1010011 .
b1010011 %
b1010011 -
b1010011 ,
0&
#4275
1&
#4300
b1010100 (
b1010100 .
b1010100 %
b1010100 -
b1010100 ,
0&
#4325
1&
#4350
b1010101 (
b1010101 .
b1010101 %
b1010101 -
b1010101 ,
0&
#4375
1&
#4400
b1010110 (
b1010110 .
b1010110 %
b1010110 -
b1010110 ,
0&
#4425
1&
#4450
b1010111 (
b1010111 .
b1010111 %
b1010111 -
b1010111 ,
0&
#4475
1&
#4500
b1011000 (
b1011000 .
b1011000 %
b1011000 -
b1011000 ,
0&
#4525
1&
#4550
b1011001 (
b1011001 .
b1011001 %
b1011001 -
b1011001 ,
0&
#4575
1&
#4600
b1011010 (
b1011010 .
b1011010 %
b1011010 -
b1011010 ,
0&
#4625
1&
#4650
b1011011 (
b1011011 .
b1011011 %
b1011011 -
b1011011 ,
0&
#4675
1&
#4700
b1011100 (
b1011100 .
b1011100 %
b1011100 -
b1011100 ,
0&
#4725
1&
#4750
b1011101 (
b1011101 .
b1011101 %
b1011101 -
b1011101 ,
0&
#4775
1&
#4800
b1011110 (
b1011110 .
b1011110 %
b1011110 -
b1011110 ,
0&
#4825
1&
#4850
b1011111 (
b1011111 .
b1011111 %
b1011111 -
b1011111 ,
0&
#4875
1&
#4900
b1100000 (
b1100000 .
b1100000 %
b1100000 -
b1100000 ,
0&
#4925
1&
#4950
b1100001 (
b1100001 .
b1100001 %
b1100001 -
b1100001 ,
0&
#4975
1&
#5000
b1100010 (
b1100010 .
b1100010 %
b1100010 -
b1100010 ,
0&
#5025
1&
#5050
b1100011 (
b1100011 .
b1100011 %
b1100011 -
b1100011 ,
0&
#5075
1&
#5100
b1100100 (
b1100100 .
b1100100 %
b1100100 -
b1100100 ,
0&
#5125
1&
#5150
b1100101 (
b1100101 .
b1100101 %
b1100101 -
b1100101 ,
0&
#5175
1&
#5200
b1100110 (
b1100110 .
b1100110 %
b1100110 -
b1100110 ,
0&
#5225
1&
#5250
b1100111 (
b1100111 .
b1100111 %
b1100111 -
b1100111 ,
0&
#5275
1&
#5300
b1101000 (
b1101000 .
b1101000 %
b1101000 -
b1101000 ,
0&
#5325
1&
#5350
b1101001 (
b1101001 .
b1101001 %
b1101001 -
b1101001 ,
0&
#5375
1&
#5400
b1101010 (
b1101010 .
b1101010 %
b1101010 -
b1101010 ,
0&
#5425
1&
#5450
b1101011 (
b1101011 .
b1101011 %
b1101011 -
b1101011 ,
0&
#5475
1&
#5500
b1101100 (
b1101100 .
b1101100 %
b1101100 -
b1101100 ,
0&
#5525
1&
#5550
b1101101 (
b1101101 .
b1101101 %
b1101101 -
b1101101 ,
0&
#5575
1&
#5600
b1101110 (
b1101110 .
b1101110 %
b1101110 -
b1101110 ,
0&
#5625
1&
#5650
b1101111 (
b1101111 .
b1101111 %
b1101111 -
b1101111 ,
0&
#5675
1&
#5700
b1110000 (
b1110000 .
b1110000 %
b1110000 -
b1110000 ,
0&
#5725
1&
#5750
b1110001 (
b1110001 .
b1110001 %
b1110001 -
b1110001 ,
0&
#5775
1&
#5800
b1110010 (
b1110010 .
b1110010 %
b1110010 -
b1110010 ,
0&
#5825
1&
#5850
b1110011 (
b1110011 .
b1110011 %
b1110011 -
b1110011 ,
0&
#5875
1&
#5900
b1110100 (
b1110100 .
b1110100 %
b1110100 -
b1110100 ,
0&
#5925
1&
#5950
b1110101 (
b1110101 .
b1110101 %
b1110101 -
b1110101 ,
0&
#5975
1&
#6000
b1110110 (
b1110110 .
b1110110 %
b1110110 -
b1110110 ,
0&
#6025
1&
#6050
b1110111 (
b1110111 .
b1110111 %
b1110111 -
b1110111 ,
0&
#6075
1&
#6100
b1111000 (
b1111000 .
b1111000 %
b1111000 -
b1111000 ,
0&
#6125
1&
#6150
b1111001 (
b1111001 .
b1111001 %
b1111001 -
b1111001 ,
0&
#6175
1&
#6200
b1111010 (
b1111010 .
b1111010 %
b1111010 -
b1111010 ,
0&
#6225
1&
#6250
b1111011 (
b1111011 .
b1111011 %
b1111011 -
b1111011 ,
0&
#6275
1&
#6300
b1111100 (
b1111100 .
b1111100 %
b1111100 -
b1111100 ,
0&
#6325
1&
#6350
b1111101 (
b1111101 .
b1111101 %
b1111101 -
b1111101 ,
0&
#6375
1&
#6400
b1111110 (
b1111110 .
b1111110 %
b1111110 -
b1111110 ,
0&
#6425
1&
#6450
b1111111 (
b1111111 .
b1111111 %
b1111111 -
b1111111 ,
0&
#6475
1&
#6500
b10000000 (
b10000000 .
b10000000 %
b10000000 -
b10000000 ,
0&
#6525
1&
#6550
b10000001 (
b10000001 .
b10000001 %
b10000001 -
b10000001 ,
0&
#6575
1&
#6600
b10000010 (
b10000010 .
b10000010 %
b10000010 -
b10000010 ,
0&
#6625
1&
#6650
b10000011 (
b10000011 .
b10000011 %
b10000011 -
b10000011 ,
0&
#6675
1&
#6700
b10000100 (
b10000100 .
b10000100 %
b10000100 -
b10000100 ,
0&
#6725
1&
#6750
b10000101 (
b10000101 .
b10000101 %
b10000101 -
b10000101 ,
0&
#6775
1&
#6800
b10000110 (
b10000110 .
b10000110 %
b10000110 -
b10000110 ,
0&
#6825
1&
#6850
b10000111 (
b10000111 .
b10000111 %
b10000111 -
b10000111 ,
0&
#6875
1&
#6900
b10001000 (
b10001000 .
b10001000 %
b10001000 -
b10001000 ,
0&
#6925
1&
#6950
b10001001 (
b10001001 .
b10001001 %
b10001001 -
b10001001 ,
0&
#6975
1&
#7000
b10001010 (
b10001010 .
b10001010 %
b10001010 -
b10001010 ,
0&
#7025
1&
#7050
b10001011 (
b10001011 .
b10001011 %
b10001011 -
b10001011 ,
0&
#7075
1&
#7100
b10001100 (
b10001100 .
b10001100 %
b10001100 -
b10001100 ,
0&
#7125
1&
#7150
b10001101 (
b10001101 .
b10001101 %
b10001101 -
b10001101 ,
0&
#7175
1&
#7200
b10001110 (
b10001110 .
b10001110 %
b10001110 -
b10001110 ,
0&
#7225
1&
#7250
b10001111 (
b10001111 .
b10001111 %
b10001111 -
b10001111 ,
0&
#7275
1&
#7300
b10010000 (
b10010000 .
b10010000 %
b10010000 -
b10010000 ,
0&
#7325
1&
#7350
b10010001 (
b10010001 .
b10010001 %
b10010001 -
b10010001 ,
0&
#7375
1&
#7400
b10010010 (
b10010010 .
b10010010 %
b10010010 -
b10010010 ,
0&
#7425
1&
#7450
b10010011 (
b10010011 .
b10010011 %
b10010011 -
b10010011 ,
0&
#7475
1&
#7500
b10010100 (
b10010100 .
b10010100 %
b10010100 -
b10010100 ,
0&
#7525
1&
#7550
b10010101 (
b10010101 .
b10010101 %
b10010101 -
b10010101 ,
0&
#7575
1&
#7600
b10010110 (
b10010110 .
b10010110 %
b10010110 -
b10010110 ,
0&
#7625
1&
#7650
b10010111 (
b10010111 .
b10010111 %
b10010111 -
b10010111 ,
0&
#7675
1&
#7700
b10011000 (
b10011000 .
b10011000 %
b10011000 -
b10011000 ,
0&
#7725
1&
#7750
b10011001 (
b10011001 .
b10011001 %
b10011001 -
b10011001 ,
0&
#7775
1&
#7800
b10011010 (
b10011010 .
b10011010 %
b10011010 -
b10011010 ,
0&
#7825
1&
#7850
b10011011 (
b10011011 .
b10011011 %
b10011011 -
b10011011 ,
0&
#7875
1&
#7900
b10011100 (
b10011100 .
b10011100 %
b10011100 -
b10011100 ,
0&
#7925
1&
#7950
b10011101 (
b10011101 .
b10011101 %
b10011101 -
b10011101 ,
0&
#7975
1&
#8000
b10011110 (
b10011110 .
b10011110 %
b10011110 -
b10011110 ,
0&
#8025
1&
#8050
b10011111 (
b10011111 .
b10011111 %
b10011111 -
b10011111 ,
0&
#8075
1&
#8100
b10100000 (
b10100000 .
b10100000 %
b10100000 -
b10100000 ,
0&
#8125
1&
#8150
b10100001 (
b10100001 .
b10100001 %
b10100001 -
b10100001 ,
0&
#8175
1&
#8200
b10100010 (
b10100010 .
b10100010 %
b10100010 -
b10100010 ,
0&
#8225
1&
#8250
b10100011 (
b10100011 .
b10100011 %
b10100011 -
b10100011 ,
0&
#8275
1&
#8300
b10100100 (
b10100100 .
b10100100 %
b10100100 -
b10100100 ,
0&
#8325
1&
#8350
b10100101 (
b10100101 .
b10100101 %
b10100101 -
b10100101 ,
0&
#8375
1&
#8400
b10100110 (
b10100110 .
b10100110 %
b10100110 -
b10100110 ,
0&
#8425
1&
#8450
b10100111 (
b10100111 .
b10100111 %
b10100111 -
b10100111 ,
0&
#8475
1&
#8500
b10101000 (
b10101000 .
b10101000 %
b10101000 -
b10101000 ,
0&
#8525
1&
#8550
b10101001 (
b10101001 .
b10101001 %
b10101001 -
b10101001 ,
0&
#8575
1&
#8600
b10101010 (
b10101010 .
b10101010 %
b10101010 -
b10101010 ,
0&
#8625
1&
#8650
b10101011 (
b10101011 .
b10101011 %
b10101011 -
b10101011 ,
0&
#8675
1&
#8700
b10101100 (
b10101100 .
b10101100 %
b10101100 -
b10101100 ,
0&
#8725
1&
#8750
b10101101 (
b10101101 .
b10101101 %
b10101101 -
b10101101 ,
0&
#8775
1&
#8800
b10101110 (
b10101110 .
b10101110 %
b10101110 -
b10101110 ,
0&
#8825
1&
#8850
b10101111 (
b10101111 .
b10101111 %
b10101111 -
b10101111 ,
0&
#8875
1&
#8900
b10110000 (
b10110000 .
b10110000 %
b10110000 -
b10110000 ,
0&
#8925
1&
#8950
b10110001 (
b10110001 .
b10110001 %
b10110001 -
b10110001 ,
0&
#8975
1&
#9000
b10110010 (
b10110010 .
b10110010 %
b10110010 -
b10110010 ,
0&
#9025
1&
#9050
b10110011 (
b10110011 .
b10110011 %
b10110011 -
b10110011 ,
0&
#9075
1&
#9100
b10110100 (
b10110100 .
b10110100 %
b10110100 -
b10110100 ,
0&
#9125
1&
#9150
b10110101 (
b10110101 .
b10110101 %
b10110101 -
b10110101 ,
0&
#9175
1&
#9200
b10110110 (
b10110110 .
b10110110 %
b10110110 -
b10110110 ,
0&
#9225
1&
#9250
b10110111 (
b10110111 .
b10110111 %
b10110111 -
b10110111 ,
0&
#9275
1&
#9300
b10111000 (
b10111000 .
b10111000 %
b10111000 -
b10111000 ,
0&
#9325
1&
#9350
b10111001 (
b10111001 .
b10111001 %
b10111001 -
b10111001 ,
0&
#9375
1&
#9400
b10111010 (
b10111010 .
b10111010 %
b10111010 -
b10111010 ,
0&
#9425
1&
#9450
b10111011 (
b10111011 .
b10111011 %
b10111011 -
b10111011 ,
0&
#9475
1&
#9500
b10111100 (
b10111100 .
b10111100 %
b10111100 -
b10111100 ,
0&
#9525
1&
#9550
b10111101 (
b10111101 .
b10111101 %
b10111101 -
b10111101 ,
0&
#9575
1&
#9600
b10111110 (
b10111110 .
b10111110 %
b10111110 -
b10111110 ,
0&
#9625
1&
#9650
b10111111 (
b10111111 .
b10111111 %
b10111111 -
b10111111 ,
0&
#9675
1&
#9700
b11000000 (
b11000000 .
b11000000 %
b11000000 -
b11000000 ,
0&
#9725
1&
#9750
b11000001 (
b11000001 .
b11000001 %
b11000001 -
b11000001 ,
0&
#9775
1&
#9800
b11000010 (
b11000010 .
b11000010 %
b11000010 -
b11000010 ,
0&
#9825
1&
#9850
b11000011 (
b11000011 .
b11000011 %
b11000011 -
b11000011 ,
0&
#9875
1&
#9900
b11000100 (
b11000100 .
b11000100 %
b11000100 -
b11000100 ,
0&
#9925
1&
#9950
b11000101 (
b11000101 .
b11000101 %
b11000101 -
b11000101 ,
0&
#9975
1&
#10000
b11000110 (
b11000110 .
b11000110 %
b11000110 -
b11000110 ,
0&
#10025
1&
#10050
b11000111 (
b11000111 .
b11000111 %
b11000111 -
b11000111 ,
0&
#10075
1&
#10100
b11001000 (
b11001000 .
b11001000 %
b11001000 -
b11001000 ,
0&
#10125
1&
#10150
b11001001 (
b11001001 .
b11001001 %
b11001001 -
b11001001 ,
0&
#10175
1&
#10200
b11001010 (
b11001010 .
b11001010 %
b11001010 -
b11001010 ,
0&
#10225
1&
#10250
b11001011 (
b11001011 .
b11001011 %
b11001011 -
b11001011 ,
0&
#10275
1&
#10300
b11001100 (
b11001100 .
b11001100 %
b11001100 -
b11001100 ,
0&
#10325
1&
#10350
b11001101 (
b11001101 .
b11001101 %
b11001101 -
b11001101 ,
0&
#10375
1&
#10400
b11001110 (
b11001110 .
b11001110 %
b11001110 -
b11001110 ,
0&
#10425
1&
#10450
b11001111 (
b11001111 .
b11001111 %
b11001111 -
b11001111 ,
0&
#10475
1&
#10500
b11010000 (
b11010000 .
b11010000 %
b11010000 -
b11010000 ,
0&
#10525
1&
#10550
b11010001 (
b11010001 .
b11010001 %
b11010001 -
b11010001 ,
0&
#10575
1&
#10600
b11010010 (
b11010010 .
b11010010 %
b11010010 -
b11010010 ,
0&
#10625
1&
