ANIDS/anids_defines.vh
// ANIDS Defines
// Clock Period, this is 5ns period (200MHz clock)
`define CLK_PERIOD				16'd5


// APB can work with 8, 16, 32 bit data width
`define APB_DATA_WIDTH			8
`define APB_ADDR_WIDTH			16 							// 15 bits needed, but we use 16.


// DMA Data Width is input vector size, which is 128 bits
`define DMA_DATA_WIDTH			128

// Memory Fetch Unit widths
`define MFU_DATA_WIDTH			`DMA_DATA_WIDTH
`define MFU_FEATURE_WIDTH		`MFU_DATA_WIDTH				// stored feature vector width

// Pipeline Manager widths and history depth
`define PIPELINE_VECTOR_WIDTH	`MFU_FEATURE_WIDTH			// vector width propagated through pipeline manager
`define PIPELINE_COUNTER_WIDTH	7							// counter width for indices 0..127
`define PIPELINE_HISTORY_DEPTH	2							// number of coarse vector buffers before validation
`define PIPELINE_STAGE_CYCLES	64							// 128-bit vector processed over 64 cycles
`define PIPELINE_STAGE_COUNT_W	6							// counter width for 0..63 stage timing

// Input layer widths
`define INPUT_LAYER_FEATURE_WIDTH	`PIPELINE_VECTOR_WIDTH	// full feature vector width seen by input layer
`define INPUT_LAYER_PAIR_WIDTH		2						// number of feature bits processed per counter step

// Hidden layer unit widths
`define HL_FEATURE_PAIR_WIDTH		`INPUT_LAYER_PAIR_WIDTH	// number of feature bits consumed per cycle
`define HL_WEIGHT_WIDTH				8						// signed Q0.7 weight width
`define HL_BIAS_WIDTH				8						// signed Q0.7 bias width
`define HL_RESULT_WIDTH				8						// signed Q0.7 hidden neuron output width
`define HL_PAIR_SUM_WIDTH			9						// sum of two weighted feature contributions
`define HL_ACC_WIDTH				15						// accumulation register width before truncation

// Output layer unit widths
`define OL_INPUT_WIDTH				8						// signed Q0.7 hidden-layer input width
`define OL_WEIGHT_WIDTH				8						// signed Q0.7 output-layer weight width
`define OL_BIAS_WIDTH				8						// signed Q0.7 output-layer bias width
`define OL_RESULT_WIDTH				8						// signed Q0.7 output-layer result width
`define OL_PRODUCT_WIDTH			16						// full signed 8x8 multiply width
`define OL_TRUNC_PRODUCT_WIDTH		8						// product truncated back to Q0.7
`define OL_ACC_WIDTH				15						// accumulation width before final truncation

// Loss function widths
`define LF_FEATURE_PAIR_WIDTH		`INPUT_LAYER_PAIR_WIDTH	// number of original feature bits consumed per cycle
`define LF_RESULT_IN_WIDTH			8						// compared result width
`define LF_ABS_WIDTH				8						// absolute delta width
`define LF_PAIR_SUM_WIDTH			9						// sum of two absolute deltas
`define LF_ACC_WIDTH				15						// accumulation register width before truncation

// Sigmoid LUT address mapper widths
`define MMAP_IN_WIDTH				8						// signed Q0.7 value width before LUT lookup
`define MMAP_ADDR_WIDTH				`LUT_ADDR_WIDTH		// LUT address width after mapping

// LUT Address and Data Sizes
`define LUT_ADDR_WIDTH			8
`define LUT_DATA_WIDTH			8

`define RELU_WIDTH 				8
`define LF_OUT_WIDTH			8



// Weight & Bias Counts
`define HL_WEIGHT_COUNT   		64 * 128   	// 8192
`define HL_BIAS_COUNT      		64       	// 64
`define OL_WEIGHT_COUNT    		128 * 64   	// 8192
`define OL_BIAS_COUNT      		128      	// 128


// ANIDS Control Register Addresses
`define START_REG				0
`define N_REG					1
`define THRESHOLD_REG			2
`define RESULT_REG				3


// Indirect LUT Read/Write Registers
`define LUT_ADDR				4
`define LUT_DATA				5
`define LUT_CTRL				6
`define FREE_REG				7


// Hidden Layer Register Mapping
`define HL_WEIGHT_BASE			8 // we have 128 * 64 of these
`define HL_BIAS_BASE			`HL_WEIGHT_BASE + `HL_WEIGHT_COUNT // and 64 of these


// Output Layer Register Mapping
`define OL_WEIGHT_BASE			`HL_BIAS_BASE + `HL_BIAS_COUNT
`define OL_BIAS_BASE			`OL_WEIGHT_BASE + `OL_WEIGHT_COUNT


// ANIDS memory map borders
`define ANIDS_MAP_START   		`HL_WEIGHT_BASE
`define ANIDS_MAP_END     		`OL_BIAS_BASE + `OL_BIAS_COUNT
`define REG_COUNT				`ANIDS_MAP_END 	// (correct count due to 0-based indexing)


// Pipeline Stage Cycles
`define INPUT_LAYER_CYCLES 		1
`define HIDDEN_LAYER_CYCLES 	64
`define OUTPUT_LAYER_CYCLES 	64
`define LOOKUP_LAYER_CYCLES 	64
`define LOSS_FUNCTION_CYCLES 	64
`define OUTLIER_CYCLES 			1
`define RESULT_CYCLES 			1


// Pipeline Fill and Latency in cycles (pipefill = 259, latency = 130)
`define PIPE_FILL_CYCLES 		(`INPUT_LAYER_CYCLES + `HIDDEN_LAYER_CYCLES + `OUTPUT_LAYER_CYCLES + `LOOKUP_LAYER_CYCLES + `LOSS_FUNCTION_CYCLES + `OUTLIER_CYCLES + `RESULT_CYCLES)
`define LATENCY_IN_CYCLES 		(`LOOKUP_LAYER_CYCLES + `LOSS_FUNCTION_CYCLES + `OUTLIER_CYCLES + `RESULT_CYCLES )

ANIDS/src/core/memory_mapper.sv
// ANIDS Sigmoid LUT Memory Mapper
`include "anids_defines.vh"

module memory_mapper (
		in_value,
		lut_addr
	);

	parameter IN_WIDTH   = `MMAP_IN_WIDTH;
	parameter ADDR_WIDTH = `MMAP_ADDR_WIDTH;

	// ----------------------------------------------------------------------
	//                  		I/O Ports
	// ----------------------------------------------------------------------
	input  wire signed [IN_WIDTH-1:0]   in_value;
	output reg        [ADDR_WIDTH-1:0]  lut_addr;

	// ----------------------------------------------------------------------
	//                  		Address Mapping
	// ----------------------------------------------------------------------
	// Map signed Q0.7 values into an ascending LUT index:
	// most negative -> 0, zero -> middle, most positive -> last entry.
	// For a 256-entry LUT (8-bit address), this is a one-to-one mapping that
	// only flips the sign bit. For a 128-entry LUT, the LSB is dropped so that
	// adjacent signed codes share one LUT entry.
	always @(*) begin
		if (ADDR_WIDTH == IN_WIDTH) begin
			lut_addr = {~in_value[IN_WIDTH-1], in_value[IN_WIDTH-2:0]};
		end
		else begin
			lut_addr = {~in_value[IN_WIDTH-1], in_value[IN_WIDTH-2:1]};
		end
	end

endmodule

ANIDS/tb/unit/memory_mapper_tb.sv
// Purpose: verifies signed Q0.7 value to LUT-address mapping across the full 8-bit input range.
// ANIDS - Memory Mapper Testbench
`timescale 1ns/100ps
`include "anids_defines.vh"

module memory_mapper_tb;

	localparam IN_WIDTH   = `MMAP_IN_WIDTH;
	localparam ADDR_WIDTH = `MMAP_ADDR_WIDTH;

	reg  signed [IN_WIDTH-1:0] in_value;
	wire        [ADDR_WIDTH-1:0] lut_addr;

	memory_mapper #(
		.IN_WIDTH   (IN_WIDTH),
		.ADDR_WIDTH (ADDR_WIDTH)
	) dut (
		.in_value (in_value),
		.lut_addr (lut_addr)
	);

initial begin
		$dumpfile("memory_mapper_tb.vcd");
		$dumpvars(0, memory_mapper_tb);

		run_full_sweep;

		$display("MEMORY_MAPPER TB PASSED");
		$finish;
	end

	task run_full_sweep;
		integer raw_val;
		reg signed [IN_WIDTH-1:0] test_in;
		reg [ADDR_WIDTH-1:0] expected_addr;
	begin
		for (raw_val = -128; raw_val <= 127; raw_val = raw_val + 1) begin
			test_in = raw_val;
			if (ADDR_WIDTH == IN_WIDTH) begin
				expected_addr = {~test_in[IN_WIDTH-1], test_in[IN_WIDTH-2:0]};
			end
			else begin
				expected_addr = {~test_in[IN_WIDTH-1], test_in[IN_WIDTH-2:1]};
			end
			check_map(test_in, expected_addr, "full sweep");
		end
	end
	endtask

	task check_map(
		input signed [IN_WIDTH-1:0]      test_in,
		input        [ADDR_WIDTH-1:0]    expected_addr,
		input [255:0]                    test_name
	);
	begin
		in_value = test_in;
		#1;

		if (lut_addr !== expected_addr) begin
			$error("FAIL: %0s | in=%0d addr=%0d expected_addr=%0d",
				test_name, test_in, lut_addr, expected_addr);
			$finish;
		end
		else begin
			$display("PASS: %0s", test_name);
		end
	end
	endtask

endmodule

Outputs/vcd/memory_mapper_tb.vcd
$date
	Tue Jun 09 14:54:14 2026
$end
$version
	Icarus Verilog
$end
$timescale
	100ps
$end
$scope module memory_mapper_tb $end
$var wire 8 ! lut_addr [7:0] $end
$var parameter 32 " ADDR_WIDTH $end
$var parameter 32 # IN_WIDTH $end
$var reg 8 $ in_value [7:0] $end
$scope module dut $end
$var wire 8 % in_value [7:0] $end
$var parameter 32 & ADDR_WIDTH $end
$var parameter 32 ' IN_WIDTH $end
$var reg 8 ( lut_addr [7:0] $end
$upscope $end
$scope task check_map $end
$var reg 8 ) expected_addr [7:0] $end
$var reg 8 * test_in [7:0] $end
$var reg 256 + test_name [255:0] $end
$upscope $end
$scope task run_full_sweep $end
$var reg 8 , expected_addr [7:0] $end
$var reg 8 - test_in [7:0] $end
$var integer 32 . raw_val [31:0] $end
$upscope $end
$upscope $end
$enddefinitions $end
$comment Show the parameter values. $end
$dumpall
b1000 '
b1000 &
b1000 #
b1000 "
$end
#0
$dumpvars
b11111111111111111111111110000000 .
b10000000 -
b0 ,
b1100110011101010110110001101100001000000111001101110111011001010110010101110000 +
b10000000 *
b0 )
b0 (
b10000000 %
b10000000 $
b0 !
$end
#10
b1 !
b1 (
b10000001 $
b10000001 %
b1 )
b10000001 *
b1 ,
b10000001 -
b11111111111111111111111110000001 .
#20
b10 !
b10 (
b10000010 $
b10000010 %
b10 )
b10000010 *
b10 ,
b10000010 -
b11111111111111111111111110000010 .
#30
b11 !
b11 (
b10000011 $
b10000011 %
b11 )
b10000011 *
b11 ,
b10000011 -
b11111111111111111111111110000011 .
#40
b100 !
b100 (
b10000100 $
b10000100 %
b100 )
b10000100 *
b100 ,
b10000100 -
b11111111111111111111111110000100 .
#50
b101 !
b101 (
b10000101 $
b10000101 %
b101 )
b10000101 *
b101 ,
b10000101 -
b11111111111111111111111110000101 .
#60
b110 !
b110 (
b10000110 $
b10000110 %
b110 )
b10000110 *
b110 ,
b10000110 -
b11111111111111111111111110000110 .
#70
b111 !
b111 (
b10000111 $
b10000111 %
b111 )
b10000111 *
b111 ,
b10000111 -
b11111111111111111111111110000111 .
#80
b1000 !
b1000 (
b10001000 $
b10001000 %
b1000 )
b10001000 *
b1000 ,
b10001000 -
b11111111111111111111111110001000 .
#90
b1001 !
b1001 (
b10001001 $
b10001001 %
b1001 )
b10001001 *
b1001 ,
b10001001 -
b11111111111111111111111110001001 .
#100
b1010 !
b1010 (
b10001010 $
b10001010 %
b1010 )
b10001010 *
b1010 ,
b10001010 -
b11111111111111111111111110001010 .
#110
b1011 !
b1011 (
b10001011 $
b10001011 %
b1011 )
b10001011 *
b1011 ,
b10001011 -
b11111111111111111111111110001011 .
#120
b1100 !
b1100 (
b10001100 $
b10001100 %
b1100 )
b10001100 *
b1100 ,
b10001100 -
b11111111111111111111111110001100 .
#130
b1101 !
b1101 (
b10001101 $
b10001101 %
b1101 )
b10001101 *
b1101 ,
b10001101 -
b11111111111111111111111110001101 .
#140
b1110 !
b1110 (
b10001110 $
b10001110 %
b1110 )
b10001110 *
b1110 ,
b10001110 -
b11111111111111111111111110001110 .
#150
b1111 !
b1111 (
b10001111 $
b10001111 %
b1111 )
b10001111 *
b1111 ,
b10001111 -
b11111111111111111111111110001111 .
#160
b10000 !
b10000 (
b10010000 $
b10010000 %
b10000 )
b10010000 *
b10000 ,
b10010000 -
b11111111111111111111111110010000 .
#170
b10001 !
b10001 (
b10010001 $
b10010001 %
b10001 )
b10010001 *
b10001 ,
b10010001 -
b11111111111111111111111110010001 .
#180
b10010 !
b10010 (
b10010010 $
b10010010 %
b10010 )
b10010010 *
b10010 ,
b10010010 -
b11111111111111111111111110010010 .
#190
b10011 !
b10011 (
b10010011 $
b10010011 %
b10011 )
b10010011 *
b10011 ,
b10010011 -
b11111111111111111111111110010011 .
#200
b10100 !
b10100 (
b10010100 $
b10010100 %
b10100 )
b10010100 *
b10100 ,
b10010100 -
b11111111111111111111111110010100 .
#210
b10101 !
b10101 (
b10010101 $
b10010101 %
b10101 )
b10010101 *
b10101 ,
b10010101 -
b11111111111111111111111110010101 .
#220
b10110 !
b10110 (
b10010110 $
b10010110 %
b10110 )
b10010110 *
b10110 ,
b10010110 -
b11111111111111111111111110010110 .
#230
b10111 !
b10111 (
b10010111 $
b10010111 %
b10111 )
b10010111 *
b10111 ,
b10010111 -
b11111111111111111111111110010111 .
#240
b11000 !
b11000 (
b10011000 $
b10011000 %
b11000 )
b10011000 *
b11000 ,
b10011000 -
b11111111111111111111111110011000 .
#250
b11001 !
b11001 (
b10011001 $
b10011001 %
b11001 )
b10011001 *
b11001 ,
b10011001 -
b11111111111111111111111110011001 .
#260
b11010 !
b11010 (
b10011010 $
b10011010 %
b11010 )
b10011010 *
b11010 ,
b10011010 -
b11111111111111111111111110011010 .
#270
b11011 !
b11011 (
b10011011 $
b10011011 %
b11011 )
b10011011 *
b11011 ,
b10011011 -
b11111111111111111111111110011011 .
#280
b11100 !
b11100 (
b10011100 $
b10011100 %
b11100 )
b10011100 *
b11100 ,
b10011100 -
b11111111111111111111111110011100 .
#290
b11101 !
b11101 (
b10011101 $
b10011101 %
b11101 )
b10011101 *
b11101 ,
b10011101 -
b11111111111111111111111110011101 .
#300
b11110 !
b11110 (
b10011110 $
b10011110 %
b11110 )
b10011110 *
b11110 ,
b10011110 -
b11111111111111111111111110011110 .
#310
b11111 !
b11111 (
b10011111 $
b10011111 %
b11111 )
b10011111 *
b11111 ,
b10011111 -
b11111111111111111111111110011111 .
#320
b100000 !
b100000 (
b10100000 $
b10100000 %
b100000 )
b10100000 *
b100000 ,
b10100000 -
b11111111111111111111111110100000 .
#330
b100001 !
b100001 (
b10100001 $
b10100001 %
b100001 )
b10100001 *
b100001 ,
b10100001 -
b11111111111111111111111110100001 .
#340
b100010 !
b100010 (
b10100010 $
b10100010 %
b100010 )
b10100010 *
b100010 ,
b10100010 -
b11111111111111111111111110100010 .
#350
b100011 !
b100011 (
b10100011 $
b10100011 %
b100011 )
b10100011 *
b100011 ,
b10100011 -
b11111111111111111111111110100011 .
#360
b100100 !
b100100 (
b10100100 $
b10100100 %
b100100 )
b10100100 *
b100100 ,
b10100100 -
b11111111111111111111111110100100 .
#370
b100101 !
b100101 (
b10100101 $
b10100101 %
b100101 )
b10100101 *
b100101 ,
b10100101 -
b11111111111111111111111110100101 .
#380
b100110 !
b100110 (
b10100110 $
b10100110 %
b100110 )
b10100110 *
b100110 ,
b10100110 -
b11111111111111111111111110100110 .
#390
b100111 !
b100111 (
b10100111 $
b10100111 %
b100111 )
b10100111 *
b100111 ,
b10100111 -
b11111111111111111111111110100111 .
#400
b101000 !
b101000 (
b10101000 $
b10101000 %
b101000 )
b10101000 *
b101000 ,
b10101000 -
b11111111111111111111111110101000 .
#410
b101001 !
b101001 (
b10101001 $
b10101001 %
b101001 )
b10101001 *
b101001 ,
b10101001 -
b11111111111111111111111110101001 .
#420
b101010 !
b101010 (
b10101010 $
b10101010 %
b101010 )
b10101010 *
b101010 ,
b10101010 -
b11111111111111111111111110101010 .
#430
b101011 !
b101011 (
b10101011 $
b10101011 %
b101011 )
b10101011 *
b101011 ,
b10101011 -
b11111111111111111111111110101011 .
#440
b101100 !
b101100 (
b10101100 $
b10101100 %
b101100 )
b10101100 *
b101100 ,
b10101100 -
b11111111111111111111111110101100 .
#450
b101101 !
b101101 (
b10101101 $
b10101101 %
b101101 )
b10101101 *
b101101 ,
b10101101 -
b11111111111111111111111110101101 .
#460
b101110 !
b101110 (
b10101110 $
b10101110 %
b101110 )
b10101110 *
b101110 ,
b10101110 -
b11111111111111111111111110101110 .
#470
b101111 !
b101111 (
b10101111 $
b10101111 %
b101111 )
b10101111 *
b101111 ,
b10101111 -
b11111111111111111111111110101111 .
#480
b110000 !
b110000 (
b10110000 $
b10110000 %
b110000 )
b10110000 *
b110000 ,
b10110000 -
b11111111111111111111111110110000 .
#490
b110001 !
b110001 (
b10110001 $
b10110001 %
b110001 )
b10110001 *
b110001 ,
b10110001 -
b11111111111111111111111110110001 .
#500
b110010 !
b110010 (
b10110010 $
b10110010 %
b110010 )
b10110010 *
b110010 ,
b10110010 -
b11111111111111111111111110110010 .
#510
b110011 !
b110011 (
b10110011 $
b10110011 %
b110011 )
b10110011 *
b110011 ,
b10110011 -
b11111111111111111111111110110011 .
#520
b110100 !
b110100 (
b10110100 $
b10110100 %
b110100 )
b10110100 *
b110100 ,
b10110100 -
b11111111111111111111111110110100 .
#530
b110101 !
b110101 (
b10110101 $
b10110101 %
b110101 )
b10110101 *
b110101 ,
b10110101 -
b11111111111111111111111110110101 .
#540
b110110 !
b110110 (
b10110110 $
b10110110 %
b110110 )
b10110110 *
b110110 ,
b10110110 -
b11111111111111111111111110110110 .
#550
b110111 !
b110111 (
b10110111 $
b10110111 %
b110111 )
b10110111 *
b110111 ,
b10110111 -
b11111111111111111111111110110111 .
#560
b111000 !
b111000 (
b10111000 $
b10111000 %
b111000 )
b10111000 *
b111000 ,
b10111000 -
b11111111111111111111111110111000 .
#570
b111001 !
b111001 (
b10111001 $
b10111001 %
b111001 )
b10111001 *
b111001 ,
b10111001 -
b11111111111111111111111110111001 .
#580
b111010 !
b111010 (
b10111010 $
b10111010 %
b111010 )
b10111010 *
b111010 ,
b10111010 -
b11111111111111111111111110111010 .
#590
b111011 !
b111011 (
b10111011 $
b10111011 %
b111011 )
b10111011 *
b111011 ,
b10111011 -
b11111111111111111111111110111011 .
#600
b111100 !
b111100 (
b10111100 $
b10111100 %
b111100 )
b10111100 *
b111100 ,
b10111100 -
b11111111111111111111111110111100 .
#610
b111101 !
b111101 (
b10111101 $
b10111101 %
b111101 )
b10111101 *
b111101 ,
b10111101 -
b11111111111111111111111110111101 .
#620
b111110 !
b111110 (
b10111110 $
b10111110 %
b111110 )
b10111110 *
b111110 ,
b10111110 -
b11111111111111111111111110111110 .
#630
b111111 !
b111111 (
b10111111 $
b10111111 %
b111111 )
b10111111 *
b111111 ,
b10111111 -
b11111111111111111111111110111111 .
#640
b1000000 !
b1000000 (
b11000000 $
b11000000 %
b1000000 )
b11000000 *
b1000000 ,
b11000000 -
b11111111111111111111111111000000 .
#650
b1000001 !
b1000001 (
b11000001 $
b11000001 %
b1000001 )
b11000001 *
b1000001 ,
b11000001 -
b11111111111111111111111111000001 .
#660
b1000010 !
b1000010 (
b11000010 $
b11000010 %
b1000010 )
b11000010 *
b1000010 ,
b11000010 -
b11111111111111111111111111000010 .
#670
b1000011 !
b1000011 (
b11000011 $
b11000011 %
b1000011 )
b11000011 *
b1000011 ,
b11000011 -
b11111111111111111111111111000011 .
#680
b1000100 !
b1000100 (
b11000100 $
b11000100 %
b1000100 )
b11000100 *
b1000100 ,
b11000100 -
b11111111111111111111111111000100 .
#690
b1000101 !
b1000101 (
b11000101 $
b11000101 %
b1000101 )
b11000101 *
b1000101 ,
b11000101 -
b11111111111111111111111111000101 .
#700
b1000110 !
b1000110 (
b11000110 $
b11000110 %
b1000110 )
b11000110 *
b1000110 ,
b11000110 -
b11111111111111111111111111000110 .
#710
b1000111 !
b1000111 (
b11000111 $
b11000111 %
b1000111 )
b11000111 *
b1000111 ,
b11000111 -
b11111111111111111111111111000111 .
#720
b1001000 !
b1001000 (
b11001000 $
b11001000 %
b1001000 )
b11001000 *
b1001000 ,
b11001000 -
b11111111111111111111111111001000 .
#730
b1001001 !
b1001001 (
b11001001 $
b11001001 %
b1001001 )
b11001001 *
b1001001 ,
b11001001 -
b11111111111111111111111111001001 .
#740
b1001010 !
b1001010 (
b11001010 $
b11001010 %
b1001010 )
b11001010 *
b1001010 ,
b11001010 -
b11111111111111111111111111001010 .
#750
b1001011 !
b1001011 (
b11001011 $
b11001011 %
b1001011 )
b11001011 *
b1001011 ,
b11001011 -
b11111111111111111111111111001011 .
#760
b1001100 !
b1001100 (
b11001100 $
b11001100 %
b1001100 )
b11001100 *
b1001100 ,
b11001100 -
b11111111111111111111111111001100 .
#770
b1001101 !
b1001101 (
b11001101 $
b11001101 %
b1001101 )
b11001101 *
b1001101 ,
b11001101 -
b11111111111111111111111111001101 .
#780
b1001110 !
b1001110 (
b11001110 $
b11001110 %
b1001110 )
b11001110 *
b1001110 ,
b11001110 -
b11111111111111111111111111001110 .
#790
b1001111 !
b1001111 (
b11001111 $
b11001111 %
b1001111 )
b11001111 *
b1001111 ,
b11001111 -
b11111111111111111111111111001111 .
#800
b1010000 !
b1010000 (
b11010000 $
b11010000 %
b1010000 )
b11010000 *
b1010000 ,
b11010000 -
b11111111111111111111111111010000 .
#810
b1010001 !
b1010001 (
b11010001 $
b11010001 %
b1010001 )
b11010001 *
b1010001 ,
b11010001 -
b11111111111111111111111111010001 .
#820
b1010010 !
b1010010 (
b11010010 $
b11010010 %
b1010010 )
b11010010 *
b1010010 ,
b11010010 -
b11111111111111111111111111010010 .
#830
b1010011 !
b1010011 (
b11010011 $
b11010011 %
b1010011 )
b11010011 *
b1010011 ,
b11010011 -
b11111111111111111111111111010011 .
#840
b1010100 !
b1010100 (
b11010100 $
b11010100 %
b1010100 )
b11010100 *
b1010100 ,
b11010100 -
b11111111111111111111111111010100 .
#850
b1010101 !
b1010101 (
b11010101 $
b11010101 %
b1010101 )
b11010101 *
b1010101 ,
b11010101 -
b11111111111111111111111111010101 .
#860
b1010110 !
b1010110 (
b11010110 $
b11010110 %
b1010110 )
b11010110 *
b1010110 ,
b11010110 -
b11111111111111111111111111010110 .
#870
b1010111 !
b1010111 (
b11010111 $
b11010111 %
b1010111 )
b11010111 *
b1010111 ,
b11010111 -
b11111111111111111111111111010111 .
#880
b1011000 !
b1011000 (
b11011000 $
b11011000 %
b1011000 )
b11011000 *
b1011000 ,
b11011000 -
b11111111111111111111111111011000 .
#890
b1011001 !
b1011001 (
b11011001 $
b11011001 %
b1011001 )
b11011001 *
b1011001 ,
b11011001 -
b11111111111111111111111111011001 .
#900
b1011010 !
b1011010 (
b11011010 $
b11011010 %
b1011010 )
b11011010 *
b1011010 ,
b11011010 -
b11111111111111111111111111011010 .
#910
b1011011 !
b1011011 (
b11011011 $
b11011011 %
b1011011 )
b11011011 *
b1011011 ,
b11011011 -
b11111111111111111111111111011011 .
#920
b1011100 !
b1011100 (
b11011100 $
b11011100 %
b1011100 )
b11011100 *
b1011100 ,
b11011100 -
b11111111111111111111111111011100 .
#930
b1011101 !
b1011101 (
b11011101 $
b11011101 %
b1011101 )
b11011101 *
b1011101 ,
b11011101 -
b11111111111111111111111111011101 .
#940
b1011110 !
b1011110 (
b11011110 $
b11011110 %
b1011110 )
b11011110 *
b1011110 ,
b11011110 -
b11111111111111111111111111011110 .
#950
b1011111 !
b1011111 (
b11011111 $
b11011111 %
b1011111 )
b11011111 *
b1011111 ,
b11011111 -
b11111111111111111111111111011111 .
#960
b1100000 !
b1100000 (
b11100000 $
b11100000 %
b1100000 )
b11100000 *
b1100000 ,
b11100000 -
b11111111111111111111111111100000 .
#970
b1100001 !
b1100001 (
b11100001 $
b11100001 %
b1100001 )
b11100001 *
b1100001 ,
b11100001 -
b11111111111111111111111111100001 .
#980
b1100010 !
b1100010 (
b11100010 $
b11100010 %
b1100010 )
b11100010 *
b1100010 ,
b11100010 -
b11111111111111111111111111100010 .
#990
b1100011 !
b1100011 (
b11100011 $
b11100011 %
b1100011 )
b11100011 *
b1100011 ,
b11100011 -
b11111111111111111111111111100011 .
#1000
b1100100 !
b1100100 (
b11100100 $
b11100100 %
b1100100 )
b11100100 *
b1100100 ,
b11100100 -
b11111111111111111111111111100100 .
#1010
b1100101 !
b1100101 (
b11100101 $
b11100101 %
b1100101 )
b11100101 *
b1100101 ,
b11100101 -
b11111111111111111111111111100101 .
#1020
b1100110 !
b1100110 (
b11100110 $
b11100110 %
b1100110 )
b11100110 *
b1100110 ,
b11100110 -
b11111111111111111111111111100110 .
#1030
b1100111 !
b1100111 (
b11100111 $
b11100111 %
b1100111 )
b11100111 *
b1100111 ,
b11100111 -
b11111111111111111111111111100111 .
#1040
b1101000 !
b1101000 (
b11101000 $
b11101000 %
b1101000 )
b11101000 *
b1101000 ,
b11101000 -
b11111111111111111111111111101000 .
#1050
b1101001 !
b1101001 (
b11101001 $
b11101001 %
b1101001 )
b11101001 *
b1101001 ,
b11101001 -
b11111111111111111111111111101001 .
#1060
b1101010 !
b1101010 (
b11101010 $
b11101010 %
b1101010 )
b11101010 *
b1101010 ,
b11101010 -
b11111111111111111111111111101010 .
#1070
b1101011 !
b1101011 (
b11101011 $
b11101011 %
b1101011 )
b11101011 *
b1101011 ,
b11101011 -
b11111111111111111111111111101011 .
#1080
b1101100 !
b1101100 (
b11101100 $
b11101100 %
b1101100 )
b11101100 *
b1101100 ,
b11101100 -
b11111111111111111111111111101100 .
#1090
b1101101 !
b1101101 (
b11101101 $
b11101101 %
b1101101 )
b11101101 *
b1101101 ,
b11101101 -
b11111111111111111111111111101101 .
#1100
b1101110 !
b1101110 (
b11101110 $
b11101110 %
b1101110 )
b11101110 *
b1101110 ,
b11101110 -
b11111111111111111111111111101110 .
#1110
b1101111 !
b1101111 (
b11101111 $
b11101111 %
b1101111 )
b11101111 *
b1101111 ,
b11101111 -
b11111111111111111111111111101111 .
#1120
b1110000 !
b1110000 (
b11110000 $
b11110000 %
b1110000 )
b11110000 *
b1110000 ,
b11110000 -
b11111111111111111111111111110000 .
#1130
b1110001 !
b1110001 (
b11110001 $
b11110001 %
b1110001 )
b11110001 *
b1110001 ,
b11110001 -
b11111111111111111111111111110001 .
#1140
b1110010 !
b1110010 (
b11110010 $
b11110010 %
b1110010 )
b11110010 *
b1110010 ,
b11110010 -
b11111111111111111111111111110010 .
#1150
b1110011 !
b1110011 (
b11110011 $
b11110011 %
b1110011 )
b11110011 *
b1110011 ,
b11110011 -
b11111111111111111111111111110011 .
#1160
b1110100 !
b1110100 (
b11110100 $
b11110100 %
b1110100 )
b11110100 *
b1110100 ,
b11110100 -
b11111111111111111111111111110100 .
#1170
b1110101 !
b1110101 (
b11110101 $
b11110101 %
b1110101 )
b11110101 *
b1110101 ,
b11110101 -
b11111111111111111111111111110101 .
#1180
b1110110 !
b1110110 (
b11110110 $
b11110110 %
b1110110 )
b11110110 *
b1110110 ,
b11110110 -
b11111111111111111111111111110110 .
#1190
b1110111 !
b1110111 (
b11110111 $
b11110111 %
b1110111 )
b11110111 *
b1110111 ,
b11110111 -
b11111111111111111111111111110111 .
#1200
b1111000 !
b1111000 (
b11111000 $
b11111000 %
b1111000 )
b11111000 *
b1111000 ,
b11111000 -
b11111111111111111111111111111000 .
#1210
b1111001 !
b1111001 (
b11111001 $
b11111001 %
b1111001 )
b11111001 *
b1111001 ,
b11111001 -
b11111111111111111111111111111001 .
#1220
b1111010 !
b1111010 (
b11111010 $
b11111010 %
b1111010 )
b11111010 *
b1111010 ,
b11111010 -
b11111111111111111111111111111010 .
#1230
b1111011 !
b1111011 (
b11111011 $
b11111011 %
b1111011 )
b11111011 *
b1111011 ,
b11111011 -
b11111111111111111111111111111011 .
#1240
b1111100 !
b1111100 (
b11111100 $
b11111100 %
b1111100 )
b11111100 *
b1111100 ,
b11111100 -
b11111111111111111111111111111100 .
#1250
b1111101 !
b1111101 (
b11111101 $
b11111101 %
b1111101 )
b11111101 *
b1111101 ,
b11111101 -
b11111111111111111111111111111101 .
#1260
b1111110 !
b1111110 (
b11111110 $
b11111110 %
b1111110 )
b11111110 *
b1111110 ,
b11111110 -
b11111111111111111111111111111110 .
#1270
b1111111 !
b1111111 (
b11111111 $
b11111111 %
b1111111 )
b11111111 *
b1111111 ,
b11111111 -
b11111111111111111111111111111111 .
#1280
b10000000 !
b10000000 (
b0 $
b0 %
b10000000 )
b0 *
b10000000 ,
b0 -
b0 .
#1290
b10000001 !
b10000001 (
b1 $
b1 %
b10000001 )
b1 *
b10000001 ,
b1 -
b1 .
#1300
b10000010 !
b10000010 (
b10 $
b10 %
b10000010 )
b10 *
b10000010 ,
b10 -
b10 .
#1310
b10000011 !
b10000011 (
b11 $
b11 %
b10000011 )
b11 *
b10000011 ,
b11 -
b11 .
#1320
b10000100 !
b10000100 (
b100 $
b100 %
b10000100 )
b100 *
b10000100 ,
b100 -
b100 .
#1330
b10000101 !
b10000101 (
b101 $
b101 %
b10000101 )
b101 *
b10000101 ,
b101 -
b101 .
#1340
b10000110 !
b10000110 (
b110 $
b110 %
b10000110 )
b110 *
b10000110 ,
b110 -
b110 .
#1350
b10000111 !
b10000111 (
b111 $
b111 %
b10000111 )
b111 *
b10000111 ,
b111 -
b111 .
#1360
b10001000 !
b10001000 (
b1000 $
b1000 %
b10001000 )
b1000 *
b10001000 ,
b1000 -
b1000 .
#1370
b10001001 !
b10001001 (
b1001 $
b1001 %
b10001001 )
b1001 *
b10001001 ,
b1001 -
b1001 .
#1380
b10001010 !
b10001010 (
b1010 $
b1010 %
b10001010 )
b1010 *
b10001010 ,
b1010 -
b1010 .
#1390
b10001011 !
b10001011 (
b1011 $
b1011 %
b10001011 )
b1011 *
b10001011 ,
b1011 -
b1011 .
#1400
b10001100 !
b10001100 (
b1100 $
b1100 %
b10001100 )
b1100 *
b10001100 ,
b1100 -
b1100 .
#1410
b10001101 !
b10001101 (
b1101 $
b1101 %
b10001101 )
b1101 *
b10001101 ,
b1101 -
b1101 .
#1420
b10001110 !
b10001110 (
b1110 $
b1110 %
b10001110 )
b1110 *
b10001110 ,
b1110 -
b1110 .
#1430
b10001111 !
b10001111 (
b1111 $
b1111 %
b10001111 )
b1111 *
b10001111 ,
b1111 -
b1111 .
#1440
b10010000 !
b10010000 (
b10000 $
b10000 %
b10010000 )
b10000 *
b10010000 ,
b10000 -
b10000 .
#1450
b10010001 !
b10010001 (
b10001 $
b10001 %
b10010001 )
b10001 *
b10010001 ,
b10001 -
b10001 .
#1460
b10010010 !
b10010010 (
b10010 $
b10010 %
b10010010 )
b10010 *
b10010010 ,
b10010 -
b10010 .
