ANIDS/anids_defines.vh
// ANIDS Defines
// Clock Period, this is 5ns period (200MHz clock)
`define CLK_PERIOD				16'd5


// APB can work with 8, 16, 32 bit data width
`define APB_DATA_WIDTH			8
`define APB_ADDR_WIDTH			16 							// 15 bits needed, but we use 16.


// DMA Data Width is input vector size, which is 128 bits
`define DMA_DATA_WIDTH			128

// Memory Fetch Unit widths
`define MFU_DATA_WIDTH			`DMA_DATA_WIDTH
`define MFU_FEATURE_WIDTH		`MFU_DATA_WIDTH				// stored feature vector width

// Pipeline Manager widths and history depth
`define PIPELINE_VECTOR_WIDTH	`MFU_FEATURE_WIDTH			// vector width propagated through pipeline manager
`define PIPELINE_COUNTER_WIDTH	7							// counter width for indices 0..127
`define PIPELINE_HISTORY_DEPTH	2							// number of coarse vector buffers before validation
`define PIPELINE_STAGE_CYCLES	64							// 128-bit vector processed over 64 cycles
`define PIPELINE_STAGE_COUNT_W	6							// counter width for 0..63 stage timing

// Input layer widths
`define INPUT_LAYER_FEATURE_WIDTH	`PIPELINE_VECTOR_WIDTH	// full feature vector width seen by input layer
`define INPUT_LAYER_PAIR_WIDTH		2						// number of feature bits processed per counter step

// Hidden layer unit widths
`define HL_FEATURE_PAIR_WIDTH		`INPUT_LAYER_PAIR_WIDTH	// number of feature bits consumed per cycle
`define HL_WEIGHT_WIDTH				8						// signed Q0.7 weight width
`define HL_BIAS_WIDTH				8						// signed Q0.7 bias width
`define HL_RESULT_WIDTH				8						// signed Q0.7 hidden neuron output width
`define HL_PAIR_SUM_WIDTH			9						// sum of two weighted feature contributions
`define HL_ACC_WIDTH				15						// accumulation register width before truncation

// Output layer unit widths
`define OL_INPUT_WIDTH				8						// signed Q0.7 hidden-layer input width
`define OL_WEIGHT_WIDTH				8						// signed Q0.7 output-layer weight width
`define OL_BIAS_WIDTH				8						// signed Q0.7 output-layer bias width
`define OL_RESULT_WIDTH				8						// signed Q0.7 output-layer result width
`define OL_PRODUCT_WIDTH			16						// full signed 8x8 multiply width
`define OL_TRUNC_PRODUCT_WIDTH		8						// product truncated back to Q0.7
`define OL_ACC_WIDTH				15						// accumulation width before final truncation

// Loss function widths
`define LF_FEATURE_PAIR_WIDTH		`INPUT_LAYER_PAIR_WIDTH	// number of original feature bits consumed per cycle
`define LF_RESULT_IN_WIDTH			8						// compared result width
`define LF_ABS_WIDTH				8						// absolute delta width
`define LF_PAIR_SUM_WIDTH			9						// sum of two absolute deltas
`define LF_ACC_WIDTH				15						// accumulation register width before truncation

// Sigmoid LUT address mapper widths
`define MMAP_IN_WIDTH				8						// signed Q0.7 value width before LUT lookup
`define MMAP_ADDR_WIDTH				`LUT_ADDR_WIDTH		// LUT address width after mapping

// LUT Address and Data Sizes
`define LUT_ADDR_WIDTH			8
`define LUT_DATA_WIDTH			8

`define RELU_WIDTH 				8
`define LF_OUT_WIDTH			8



// Weight & Bias Counts
`define HL_WEIGHT_COUNT   		64 * 128   	// 8192
`define HL_BIAS_COUNT      		64       	// 64
`define OL_WEIGHT_COUNT    		128 * 64   	// 8192
`define OL_BIAS_COUNT      		128      	// 128


// ANIDS Control Register Addresses
`define START_REG				0
`define N_REG					1
`define THRESHOLD_REG			2
`define RESULT_REG				3


// Indirect LUT Read/Write Registers
`define LUT_ADDR				4
`define LUT_DATA				5
`define LUT_CTRL				6
`define FREE_REG				7


// Hidden Layer Register Mapping
`define HL_WEIGHT_BASE			8 // we have 128 * 64 of these
`define HL_BIAS_BASE			`HL_WEIGHT_BASE + `HL_WEIGHT_COUNT // and 64 of these


// Output Layer Register Mapping
`define OL_WEIGHT_BASE			`HL_BIAS_BASE + `HL_BIAS_COUNT
`define OL_BIAS_BASE			`OL_WEIGHT_BASE + `OL_WEIGHT_COUNT


// ANIDS memory map borders
`define ANIDS_MAP_START   		`HL_WEIGHT_BASE
`define ANIDS_MAP_END     		`OL_BIAS_BASE + `OL_BIAS_COUNT
`define REG_COUNT				`ANIDS_MAP_END 	// (correct count due to 0-based indexing)


// Pipeline Stage Cycles
`define INPUT_LAYER_CYCLES 		1
`define HIDDEN_LAYER_CYCLES 	64
`define OUTPUT_LAYER_CYCLES 	64
`define LOOKUP_LAYER_CYCLES 	64
`define LOSS_FUNCTION_CYCLES 	64
`define OUTLIER_CYCLES 			1
`define RESULT_CYCLES 			1


// Pipeline Fill and Latency in cycles (pipefill = 259, latency = 130)
`define PIPE_FILL_CYCLES 		(`INPUT_LAYER_CYCLES + `HIDDEN_LAYER_CYCLES + `OUTPUT_LAYER_CYCLES + `LOOKUP_LAYER_CYCLES + `LOSS_FUNCTION_CYCLES + `OUTLIER_CYCLES + `RESULT_CYCLES)
`define LATENCY_IN_CYCLES 		(`LOOKUP_LAYER_CYCLES + `LOSS_FUNCTION_CYCLES + `OUTLIER_CYCLES + `RESULT_CYCLES )

ANIDS/src/core/output_layer_processing_unit.sv
// ANIDS Output Layer Processing Unit
`include "anids_defines.vh"

module output_layer_processing_unit (
		clk,
		resetN,
		enable,
		N,
		counter,
		hidden_in,
		weight,
		bias,
		result,
		ready
	);

	parameter INPUT_WIDTH         = `OL_INPUT_WIDTH;
	parameter WEIGHT_WIDTH        = `OL_WEIGHT_WIDTH;
	parameter BIAS_WIDTH          = `OL_BIAS_WIDTH;
	parameter RESULT_WIDTH        = `OL_RESULT_WIDTH;
	parameter COUNTER_WIDTH       = `PIPELINE_COUNTER_WIDTH;
	parameter PRODUCT_WIDTH       = `OL_PRODUCT_WIDTH;
	parameter TRUNC_PRODUCT_WIDTH = `OL_TRUNC_PRODUCT_WIDTH;
	parameter ACC_WIDTH           = `OL_ACC_WIDTH;

	// ----------------------------------------------------------------------
	//                  		I/O Ports
	// ----------------------------------------------------------------------
	input  wire                                 clk;
	input  wire                                 resetN;
	input  wire                                 enable;
	input  wire [`APB_DATA_WIDTH-1:0]           N;
	input  wire [COUNTER_WIDTH-1:0]             counter;
	input  wire signed [INPUT_WIDTH-1:0]        hidden_in;
	input  wire signed [WEIGHT_WIDTH-1:0]       weight;
	input  wire signed [BIAS_WIDTH-1:0]         bias;
	output reg  signed [RESULT_WIDTH-1:0]       result;
	output reg                                  ready;

	// ----------------------------------------------------------------------
	//                  		Datapath
	// ----------------------------------------------------------------------
	reg signed [ACC_WIDTH-1:0] acc;

	// Last active pair-step index for one full hidden-layer sweep.
	wire [COUNTER_WIDTH-1:0] last_step_index =
		((N >> 1) - 1'b1);

	// Full signed Q0.7 x Q0.7 multiply result before truncation.
	wire signed [PRODUCT_WIDTH-1:0] product_full = hidden_in * weight;

	// Product converted back to signed Q0.7 by dropping 7 LSB fractional bits.
	wire signed [TRUNC_PRODUCT_WIDTH-1:0] product_q07 =
		product_full[PRODUCT_WIDTH-2 -: TRUNC_PRODUCT_WIDTH];

	// Next accumulator value after adding the current MAC contribution.
	wire signed [ACC_WIDTH-1:0] acc_next =
		acc + $signed({{(ACC_WIDTH-TRUNC_PRODUCT_WIDTH){product_q07[TRUNC_PRODUCT_WIDTH-1]}}, product_q07});

	// TRUN8 keeps the sign bit and top 7 remaining bits of the accumulated sum.
	wire signed [RESULT_WIDTH-1:0] trunc8 = acc_next[ACC_WIDTH-1 -: RESULT_WIDTH];

	// Signed bias add uses one extra bit to detect overflow before saturation.
	wire signed [RESULT_WIDTH:0] biased_sum =
		$signed({trunc8[RESULT_WIDTH-1], trunc8}) +
		$signed({bias[BIAS_WIDTH-1], bias});

	reg signed [RESULT_WIDTH-1:0] sat_result;
	always @(*) begin
		if (biased_sum > $signed({1'b0, {RESULT_WIDTH-1{1'b1}}})) begin
			sat_result = {1'b0, {RESULT_WIDTH-1{1'b1}}};
		end
		else if (biased_sum < $signed({1'b1, {RESULT_WIDTH-1{1'b0}}})) begin
			sat_result = {1'b1, {RESULT_WIDTH-1{1'b0}}};
		end
		else begin
			sat_result = biased_sum[RESULT_WIDTH-1:0];
		end
	end

	// ----------------------------------------------------------------------
	//                  		Sequential Logic
	// ----------------------------------------------------------------------
	always @(posedge clk or negedge resetN) begin
		if (!resetN) begin
			acc    <= #1 {ACC_WIDTH{1'b0}};
			result <= #1 {RESULT_WIDTH{1'b0}};
			ready  <= #1 1'b0;
		end
		else if (!enable) begin
			acc   <= #1 {ACC_WIDTH{1'b0}};
			ready <= #1 1'b0;
		end
		else begin
			ready <= #1 1'b0;

			if (counter == last_step_index) begin
				acc    <= #1 {ACC_WIDTH{1'b0}};
				result <= #1 sat_result;
				ready  <= #1 1'b1;
			end
			else begin
				acc <= #1 acc_next;
			end
		end
	end

endmodule

ANIDS/tb/unit/output_layer_processing_unit_tb.sv
// Purpose: verifies one output-layer neuron MAC path, bias handling, ready timing, and saturation.
// ANIDS - Output Layer Processing Unit Testbench
`timescale 1ns/100ps
`include "anids_defines.vh"

module output_layer_processing_unit_tb;

	localparam INPUT_WIDTH    = `OL_INPUT_WIDTH;
	localparam WEIGHT_WIDTH   = `OL_WEIGHT_WIDTH;
	localparam BIAS_WIDTH     = `OL_BIAS_WIDTH;
	localparam RESULT_WIDTH   = `OL_RESULT_WIDTH;
	localparam COUNTER_WIDTH  = `PIPELINE_COUNTER_WIDTH;
	localparam ACC_WIDTH      = `OL_ACC_WIDTH;

	reg                               clk;
	reg                               resetN;
	reg                               enable;
	reg  [`APB_DATA_WIDTH-1:0]        N;
	reg  [COUNTER_WIDTH-1:0]          counter;
	reg  signed [INPUT_WIDTH-1:0]     hidden_in;
	reg  signed [WEIGHT_WIDTH-1:0]    weight;
	reg  signed [BIAS_WIDTH-1:0]      bias;
	wire signed [RESULT_WIDTH-1:0]    result;
	wire                              ready;

	output_layer_processing_unit dut (
		.clk       (clk),
		.resetN    (resetN),
		.enable    (enable),
		.N         (N),
		.counter   (counter),
		.hidden_in (hidden_in),
		.weight    (weight),
		.bias      (bias),
		.result    (result),
		.ready     (ready)
	);

	always #2.5 clk = ~clk;

	initial begin
		$dumpfile("output_layer_processing_unit_tb.vcd");
		$dumpvars(0, output_layer_processing_unit_tb);

		clk      = 1'b0;
		resetN   = 1'b0;
		enable   = 1'b0;
		N        = 8'd4;
		counter  = {COUNTER_WIDTH{1'b0}};
		hidden_in = '0;
		weight   = '0;
		bias     = '0;

		#2;
		check_outputs(1'b0, 8'sd0, "reset clears outputs");
		check_acc(15'sd0, "reset clears accumulator");

		resetN = 1'b1;
		@(posedge clk);
		#2;
		check_outputs(1'b0, 8'sd0, "idle after reset");

		run_basic_math_test;
		run_one_cycle_step_test;
		run_disable_reset_test;
		run_positive_saturation_test;
		run_negative_saturation_test;

		$display("OUTPUT_LAYER_PROCESSING_UNIT TB PASSED");
		$finish;
	end

	task run_basic_math_test;
	begin
		$display("SECTION: basic math");
		enable    = 1'b1;
		N         = 8'd4; // two cycles, last index = 1
		bias      = 8'sd1;
		counter   = 7'd0;
		hidden_in = 8'sd64;
		weight    = 8'sd64; // 0.5 * 0.5 -> 0.25 -> 32
		@(posedge clk);
		#2;
		check_acc(15'sd32, "first MAC contribution is accumulated in one cycle");
		check_outputs(1'b0, 8'sd0, "result stays unchanged before final cycle");

		counter   = 7'd1;
		hidden_in = 8'sd64;
		weight    = 8'sd64;
		@(posedge clk);
		#2;
		check_outputs(1'b1, 8'sd1, "two MAC steps produce expected biased result");
		check_acc(15'sd0, "accumulator clears after final cycle");
	end
	endtask

	task run_one_cycle_step_test;
	begin
		$display("SECTION: one-cycle completion");
		enable    = 1'b0;
		counter   = 7'd0;
		@(posedge clk);
		#2;

		enable    = 1'b1;
		N         = 8'd2; // one cycle, last index = 0
		counter   = 7'd0;
		bias      = 8'sd0;
		hidden_in = 8'sd127;
		weight    = 8'sd64; // ~0.992 * 0.5 -> truncated to 63
		@(posedge clk);
		#2;
		check_outputs(1'b1, 8'sd0, "single accumulation step finishes in one cycle");
		check_acc(15'sd0, "single-cycle completion clears accumulator");
	end
	endtask

	task run_disable_reset_test;
	begin
		$display("SECTION: disable behavior");
		enable    = 1'b0;
		counter   = 7'd0;
		hidden_in = 8'sd64;
		weight    = 8'sd64;
		@(posedge clk);
		#2;
		check_outputs(1'b0, 8'sd0, "ready drops after completion");
		check_outputs(1'b0, 8'sd0, "result holds when enable goes low");

		enable    = 1'b1;
		N         = 8'd4;
		bias      = 8'sd0;
		counter   = 7'd0;
		hidden_in = 8'sd64;
		weight    = 8'sd64;
		@(posedge clk);
		#2;
		check_acc(15'sd32, "accumulator restarts cleanly after re-enable");

		enable    = 1'b0;
		@(posedge clk);
		#2;
		check_acc(15'sd0, "disable clears in-progress accumulation");
	end
	endtask

	task run_positive_saturation_test;
		integer i;
	begin
		$display("SECTION: positive saturation");
		enable    = 1'b0;
		@(posedge clk);
		#2;

		enable    = 1'b1;
		N         = 8'd128; // 64 cycles
		bias      = 8'sd127;
		hidden_in = 8'sd127;
		weight    = 8'sd127;
		counter   = 7'd0;

		for (i = 0; i < 63; i = i + 1) begin
			@(posedge clk);
			#2;
			check_outputs(1'b0, result, "positive saturation stays busy before final cycle");
			counter = counter + 1'b1;
		end

		@(posedge clk);
		#2;
		check_outputs(1'b1, 8'sd127, "positive overflow saturates at +127");
		check_acc(15'sd0, "accumulator clears after positive saturation");
	end
	endtask

	task run_negative_saturation_test;
		integer i;
	begin
		$display("SECTION: negative saturation");
		enable    = 1'b0;
		@(posedge clk);
		#2;

		enable    = 1'b1;
		N         = 8'd128; // 64 cycles
		bias      = -8'sd127;
		hidden_in = -8'sd128;
		weight    = 8'sd127;
		counter   = 7'd0;

		for (i = 0; i < 63; i = i + 1) begin
			@(posedge clk);
			#2;
			counter = counter + 1'b1;
		end

		@(posedge clk);
		#2;
		check_outputs(1'b1, -8'sd128, "negative overflow saturates at -128");
		check_acc(15'sd0, "accumulator clears after negative saturation");
	end
	endtask

	task check_outputs(
		input                             expected_ready,
		input signed [RESULT_WIDTH-1:0]   expected_result,
		input [255:0]                     test_name
	);
	begin
		if (ready !== expected_ready || result !== expected_result) begin
			$error("FAIL: %0s | ready=%0b expected_ready=%0b result=%0d expected_result=%0d",
				test_name, ready, expected_ready, result, expected_result);
			$finish;
		end
		else begin
			$display("PASS: %0s", test_name);
		end
	end
	endtask

	task check_acc(
		input signed [ACC_WIDTH-1:0]      expected_acc,
		input [255:0]                     test_name
	);
	begin
		if (dut.acc !== expected_acc) begin
			$error("FAIL: %0s | acc=%0d expected_acc=%0d", test_name, dut.acc, expected_acc);
			$finish;
		end
		else begin
			$display("PASS: %0s", test_name);
		end
	end
	endtask

endmodule

Outputs/vcd/output_layer_processing_unit_tb.vcd
$date
	Tue Jun 09 14:54:15 2026
$end
$version
	Icarus Verilog
$end
$timescale
	100ps
$end
$scope module output_layer_processing_unit_tb $end
$var wire 8 ! result [7:0] $end
$var wire 1 " ready $end
$var parameter 32 # ACC_WIDTH $end
$var parameter 32 $ BIAS_WIDTH $end
$var parameter 32 % COUNTER_WIDTH $end
$var parameter 32 & INPUT_WIDTH $end
$var parameter 32 ' RESULT_WIDTH $end
$var parameter 32 ( WEIGHT_WIDTH $end
$var reg 8 ) N [7:0] $end
$var reg 8 * bias [7:0] $end
$var reg 1 + clk $end
$var reg 7 , counter [6:0] $end
$var reg 1 - enable $end
$var reg 8 . hidden_in [7:0] $end
$var reg 1 / resetN $end
$var reg 8 0 weight [7:0] $end
$scope module dut $end
$var wire 8 1 N [7:0] $end
$var wire 8 2 bias [7:0] $end
$var wire 1 + clk $end
$var wire 7 3 counter [6:0] $end
$var wire 1 - enable $end
$var wire 8 4 hidden_in [7:0] $end
$var wire 1 / resetN $end
$var wire 8 5 weight [7:0] $end
$var wire 8 6 trunc8 [7:0] $end
$var wire 8 7 product_q07 [7:0] $end
$var wire 16 8 product_full [15:0] $end
$var wire 7 9 last_step_index [6:0] $end
$var wire 9 : biased_sum [8:0] $end
$var wire 15 ; acc_next [14:0] $end
$var parameter 32 < ACC_WIDTH $end
$var parameter 32 = BIAS_WIDTH $end
$var parameter 32 > COUNTER_WIDTH $end
$var parameter 32 ? INPUT_WIDTH $end
$var parameter 32 @ PRODUCT_WIDTH $end
$var parameter 32 A RESULT_WIDTH $end
$var parameter 32 B TRUNC_PRODUCT_WIDTH $end
$var parameter 32 C WEIGHT_WIDTH $end
$var reg 15 D acc [14:0] $end
$var reg 1 " ready $end
$var reg 8 E result [7:0] $end
$var reg 8 F sat_result [7:0] $end
$upscope $end
$scope task check_acc $end
$var reg 15 G expected_acc [14:0] $end
$var reg 256 H test_name [255:0] $end
$upscope $end
$scope task check_outputs $end
$var reg 1 I expected_ready $end
$var reg 8 J expected_result [7:0] $end
$var reg 256 K test_name [255:0] $end
$upscope $end
$scope task run_basic_math_test $end
$upscope $end
$scope task run_disable_reset_test $end
$upscope $end
$scope task run_negative_saturation_test $end
$var integer 32 L i [31:0] $end
$upscope $end
$scope task run_one_cycle_step_test $end
$upscope $end
$scope task run_positive_saturation_test $end
$var integer 32 M i [31:0] $end
$upscope $end
$upscope $end
$enddefinitions $end
$comment Show the parameter values. $end
$dumpall
b1000 C
b1000 B
b1000 A
b10000 @
b1000 ?
b111 >
b1000 =
b1111 <
b1000 (
b1000 '
b1000 &
b111 %
b1000 $
b1111 #
$end
#0
$dumpvars
bx M
bx L
bx K
bx J
xI
bx H
bx G
bx F
bx E
bx D
bx ;
bx :
b1 9
b0 8
b0 7
bx 6
b0 5
b0 4
b0 3
b0 2
b100 1
b0 0
0/
b0 .
0-
b0 ,
0+
b0 *
b100 )
x"
bx !
$end
#10
b0 F
b0 :
b0 6
0"
b0 !
b0 E
b0 ;
b0 D
#20
1/
b11100100110010101110011011001010111010000100000011000110110110001100101011000010111001001110011001000000110000101100011011000110111010101101101011101010110110001100001011101000110111101110010 H
b0 G
b111001001100101011100110110010101110100001000000110001101101100011001010110000101110010011100110010000001101111011101010111010001110000011101010111010001110011 K
b0 J
0I
#25
1+
#45
b100000 ;
b100000 7
b1 F
b1000000000000 8
b1000000 0
b1000000 5
b1000000 .
b1000000 4
b1 :
b1 *
b1 2
1-
b1101001011001000110110001100101001000000110000101100110011101000110010101110010001000000111001001100101011100110110010101110100 K
#50
0+
#75
1+
#85
b1000000 ;
b100000 D
#95
b1 ,
b1 3
b110000101111001011100110010000001110101011011100110001101101000011000010110111001100111011001010110010000100000011000100110010101100110011011110111001001100101001000000110011001101001011011100110000101101100001000000110001101111001011000110110110001100101 K
b111010001101001011011110110111000100000011010010111001100100000011000010110001101100011011101010110110101110101011011000110000101110100011001010110010000100000011010010110111000100000011011110110111001100101001000000110001101111001011000110110110001100101 H
b100000 G
#100
0+
#125
1+
#135
1"
b1 !
b1 E
b100000 ;
b0 D
#145
b0 ,
b0 3
0-
b110110101110101011011000110000101110100011011110111001000100000011000110110110001100101011000010111001001110011001000000110000101100110011101000110010101110010001000000110011001101001011011100110000101101100001000000110001101111001011000110110110001100101 H
b0 G
b111001100100000011100000111001001101111011001000111010101100011011001010010000001100101011110000111000001100101011000110111010001100101011001000010000001100010011010010110000101110011011001010110010000100000011100100110010101110011011101010110110001110100 K
b1 J
1I
#150
0+
#175
1+
#185
0"
#195
b0 9
b111111 ;
b111111 7
b0 F
b1111111000000 8
b1111111 .
b1111111 4
b0 :
b0 *
b0 2
b10 )
b10 1
1-
#200
0+
#225
1+
#235
1"
b0 !
b0 E
#245
b100000 ;
b100000 7
b1000000000000 8
b1000000 .
b1000000 4
0-
b110110001100101001000000110001101101111011011010111000001101100011001010111010001101001011011110110111000100000011000110110110001100101011000010111001001110011001000000110000101100011011000110111010101101101011101010110110001100001011101000110111101110010 H
b110000101110100011010010110111101101110001000000111001101110100011001010111000000100000011001100110100101101110011010010111001101101000011001010111001100100000011010010110111000100000011011110110111001100101001000000110001101111001011000110110110001100101 K
b0 J
#250
0+
#275
1+
#285
0"
#295
b1 9
b100 )
b100 1
1-
b110010101110011011101010110110001110100001000000110100001101111011011000110010001110011001000000111011101101000011001010110111000100000011001010110111001100001011000100110110001100101001000000110011101101111011001010111001100100000011011000110111101110111 K
0I
#300
0+
#325
1+
#335
b1000000 ;
b100000 D
#345
0-
b111001001100101011100110111010001100001011100100111010001110011001000000110001101101100011001010110000101101110011011000111100100100000011000010110011001110100011001010111001000100000011100100110010100101101011001010110111001100001011000100110110001100101 H
b100000 G
#350
0+
#375
1+
#385
b100000 ;
b0 D
#395
b10000001100011011011000110010101100001011100100111001100100000011010010110111000101101011100000111001001101111011001110111001001100101011100110111001100100000011000010110001101100011011101010110110101110101011011000110000101110100011010010110111101101110 H
b0 G
#400
0+
#425
1+
#445
b111111 9
b1111110 ;
b1111110 7
b1111111 F
b0 M
b1111111 0
b1111111 5
b11111100000001 8
b1111111 .
b1111111 4
b1111111 :
b1111111 *
b1111111 2
b10000000 )
b10000000 1
1-
#450
0+
#475
1+
#485
b10000000 :
b1 6
b11111100 ;
b1111110 D
#495
b1 M
b1 ,
b1 3
b110111101101110001000000111001101110100011000010111100101110011001000000110001001110101011100110111100100100000011000100110010101100110011011110111001001100101001000000110011001101001011011100110000101101100001000000110001101111001011000110110110001100101 K
#500
0+
#525
1+
#535
b10000001 :
b10 6
b101111010 ;
b11111100 D
#545
b10 M
b10 ,
b10 3
#550
0+
#575
1+
#585
b10000010 :
b11 6
b111111000 ;
b101111010 D
#595
b11 M
b11 ,
b11 3
#600
0+
#625
1+
#635
b10000011 :
b100 6
b1001110110 ;
b111111000 D
#645
b100 M
b100 ,
b100 3
#650
0+
#675
1+
#685
b10000100 :
b101 6
b1011110100 ;
b1001110110 D
#695
b101 M
b101 ,
b101 3
#700
0+
#725
1+
#735
b10000101 :
b110 6
b1101110010 ;
b1011110100 D
#745
b110 M
b110 ,
b110 3
#750
0+
#775
1+
#785
b10000110 :
b111 6
b1111110000 ;
b1101110010 D
#795
b111 M
b111 ,
b111 3
#800
0+
#825
1+
#835
b10000111 :
b1000 6
b10001101110 ;
b1111110000 D
#845
b1000 M
b1000 ,
b1000 3
#850
0+
#875
1+
#885
b10001000 :
b1001 6
b10011101100 ;
b10001101110 D
#895
b1001 M
b1001 ,
b1001 3
#900
0+
#925
1+
#935
b10001001 :
b1010 6
b10101101010 ;
b10011101100 D
#945
b1010 M
b1010 ,
b1010 3
#950
0+
#975
1+
#985
b10001010 :
b1011 6
b10111101000 ;
b10101101010 D
#995
b1011 M
b1011 ,
b1011 3
#1000
0+
#1025
1+
#1035
b10001011 :
b1100 6
b11001100110 ;
b10111101000 D
#1045
b1100 M
b1100 ,
b1100 3
#1050
0+
#1075
1+
#1085
b10001100 :
b1101 6
b11011100100 ;
b11001100110 D
#1095
b1101 M
b1101 ,
b1101 3
#1100
0+
#1125
1+
#1135
b10001101 :
b1110 6
b11101100010 ;
b11011100100 D
#1145
b1110 M
b1110 ,
b1110 3
#1150
0+
#1175
1+
#1185
b10001110 :
b1111 6
b11111100000 ;
b11101100010 D
#1195
b1111 M
b1111 ,
b1111 3
#1200
0+
#1225
1+
#1235
b10001111 :
b10000 6
b100001011110 ;
b11111100000 D
#1245
b10000 M
b10000 ,
b10000 3
#1250
0+
#1275
1+
#1285
b10010000 :
b10001 6
b100011011100 ;
b100001011110 D
#1295
b10001 M
b10001 ,
b10001 3
#1300
0+
#1325
1+
#1335
b10010001 :
b10010 6
b100101011010 ;
b100011011100 D
#1345
b10010 M
b10010 ,
b10010 3
#1350
0+
#1375
1+
#1385
b10010010 :
b10011 6
b100111011000 ;
b100101011010 D
#1395
b10011 M
b10011 ,
b10011 3
#1400
0+
#1425
1+
#1435
b10010011 :
b10100 6
b101001010110 ;
b100111011000 D
#1445
b10100 M
b10100 ,
b10100 3
#1450
0+
#1475
1+
#1485
b10010100 :
b10101 6
b101011010100 ;
b101001010110 D
#1495
b10101 M
b10101 ,
b10101 3
#1500
0+
#1525
1+
#1535
b10010101 :
b10110 6
b101101010010 ;
b101011010100 D
#1545
b10110 M
b10110 ,
b10110 3
#1550
0+
#1575
1+
#1585
b10010110 :
b10111 6
b101111010000 ;
b101101010010 D
#1595
b10111 M
b10111 ,
b10111 3
#1600
0+
#1625
1+
#1635
b10010111 :
b11000 6
b110001001110 ;
b101111010000 D
#1645
b11000 M
b11000 ,
b11000 3
#1650
0+
#1675
1+
#1685
b10011000 :
b11001 6
b110011001100 ;
b110001001110 D
#1695
b11001 M
b11001 ,
b11001 3
#1700
0+
#1725
1+
#1735
b10011001 :
b11010 6
b110101001010 ;
b110011001100 D
#1745
b11010 M
b11010 ,
b11010 3
#1750
0+
#1775
1+
#1785
b10011010 :
b11011 6
b110111001000 ;
b110101001010 D
#1795
b11011 M
b11011 ,
b11011 3
#1800
0+
#1825
1+
#1835
b10011011 :
b11100 6
b111001000110 ;
b110111001000 D
#1845
b11100 M
b11100 ,
b11100 3
#1850
0+
#1875
1+
#1885
b10011100 :
b11101 6
b111011000100 ;
b111001000110 D
#1895
b11101 M
b11101 ,
b11101 3
#1900
0+
#1925
1+
#1935
b10011101 :
b11110 6
b111101000010 ;
b111011000100 D
#1945
b11110 M
b11110 ,
b11110 3
#1950
0+
#1975
1+
#1985
b10011110 :
b11111 6
b111111000000 ;
b111101000010 D
#1995
b11111 M
b11111 ,
b11111 3
#2000
0+
#2025
1+
#2035
b10011111 :
b100000 6
b1000000111110 ;
b111111000000 D
#2045
b100000 M
b100000 ,
b100000 3
#2050
0+
#2075
1+
#2085
b10100000 :
b100001 6
b1000010111100 ;
b1000000111110 D
#2095
b100001 M
b100001 ,
b100001 3
#2100
0+
#2125
1+
#2135
b10100001 :
b100010 6
b1000100111010 ;
b1000010111100 D
#2145
b100010 M
b100010 ,
b100010 3
#2150
0+
#2175
1+
#2185
b10100010 :
b100011 6
b1000110111000 ;
b1000100111010 D
#2195
b100011 M
b100011 ,
b100011 3
#2200
0+
#2225
1+
#2235
b10100011 :
b100100 6
b1001000110110 ;
b1000110111000 D
#2245
b100100 M
b100100 ,
b100100 3
#2250
0+
#2275
1+
#2285
b10100100 :
b100101 6
b1001010110100 ;
b1001000110110 D
#2295
b100101 M
b100101 ,
b100101 3
#2300
0+
#2325
1+
#2335
b10100101 :
b100110 6
b1001100110010 ;
b1001010110100 D
#2345
b100110 M
b100110 ,
b100110 3
#2350
0+
#2375
1+
#2385
b10100110 :
b100111 6
b1001110110000 ;
b1001100110010 D
#2395
b100111 M
b100111 ,
b100111 3
#2400
0+
#2425
1+
#2435
b10100111 :
b101000 6
b1010000101110 ;
b1001110110000 D
#2445
b101000 M
b101000 ,
b101000 3
#2450
0+
#2475
1+
#2485
b10101000 :
b101001 6
b1010010101100 ;
b1010000101110 D
#2495
b101001 M
b101001 ,
b101001 3
#2500
0+
#2525
1+
#2535
b10101001 :
b101010 6
b1010100101010 ;
b1010010101100 D
#2545
b101010 M
b101010 ,
b101010 3
#2550
0+
#2575
1+
#2585
b10101010 :
b101011 6
b1010110101000 ;
b1010100101010 D
#2595
b101011 M
b101011 ,
b101011 3
#2600
0+
#2625
1+
#2635
b10101011 :
b101100 6
b1011000100110 ;
b1010110101000 D
#2645
b101100 M
b101100 ,
b101100 3
#2650
0+
#2675
1+
#2685
b10101100 :
b101101 6
b1011010100100 ;
b1011000100110 D
#2695
b101101 M
b101101 ,
b101101 3
#2700
0+
#2725
1+
#2735
b10101101 :
b101110 6
b1011100100010 ;
b1011010100100 D
#2745
b101110 M
b101110 ,
b101110 3
#2750
0+
#2775
1+
#2785
b10101110 :
b101111 6
b1011110100000 ;
b1011100100010 D
#2795
b101111 M
b101111 ,
b101111 3
#2800
0+
#2825
1+
#2835
b10101111 :
b110000 6
b1100000011110 ;
b1011110100000 D
#2845
b110000 M
b110000 ,
b110000 3
#2850
0+
#2875
1+
#2885
b10110000 :
b110001 6
b1100010011100 ;
b1100000011110 D
#2895
b110001 M
b110001 ,
b110001 3
#2900
0+
#2925
1+
#2935
b10110001 :
b110010 6
b1100100011010 ;
b1100010011100 D
#2945
b110010 M
b110010 ,
b110010 3
#2950
0+
#2975
1+
#2985
b10110010 :
b110011 6
b1100110011000 ;
b1100100011010 D
#2995
b110011 M
b110011 ,
b110011 3
#3000
0+
#3025
1+
#3035
b10110011 :
b110100 6
b1101000010110 ;
b1100110011000 D
#3045
b110100 M
b110100 ,
b110100 3
#3050
0+
#3075
1+
#3085
b10110100 :
b110101 6
b1101010010100 ;
b1101000010110 D
#3095
b110101 M
b110101 ,
b110101 3
#3100
0+
#3125
1+
#3135
b10110101 :
b110110 6
b1101100010010 ;
b1101010010100 D
#3145
b110110 M
b110110 ,
b110110 3
#3150
0+
#3175
1+
#3185
b10110110 :
b110111 6
b1101110010000 ;
b1101100010010 D
#3195
b110111 M
b110111 ,
b110111 3
#3200
0+
#3225
1+
#3235
b10110111 :
b111000 6
b1110000001110 ;
b1101110010000 D
#3245
b111000 M
b111000 ,
b111000 3
#3250
0+
#3275
1+
#3285
b10111000 :
b111001 6
b1110010001100 ;
b1110000001110 D
#3295
b111001 M
b111001 ,
b111001 3
#3300
0+
#3325
1+
#3335
b10111001 :
b111010 6
b1110100001010 ;
b1110010001100 D
#3345
b111010 M
b111010 ,
b111010 3
#3350
0+
#3375
1+
#3385
b10111010 :
b111011 6
b1110110001000 ;
b1110100001010 D
#3395
b111011 M
b111011 ,
b111011 3
#3400
0+
#3425
1+
#3435
b10111011 :
b111100 6
b1111000000110 ;
b1110110001000 D
#3445
b111100 M
b111100 ,
b111100 3
#3450
0+
#3475
1+
#3485
b10111100 :
b111101 6
b1111010000100 ;
b1111000000110 D
#3495
b111101 M
b111101 ,
b111101 3
#3500
0+
#3525
1+
#3535
b10111101 :
b111110 6
b1111100000010 ;
b1111010000100 D
#3545
b111110 M
b111110 ,
b111110 3
#3550
0+
#3575
1+
#3585
b10111110 :
b111111 6
b1111110000000 ;
b1111100000010 D
#3595
b111111 M
b111111 ,
b111111 3
#3600
0+
#3625
1+
