ANIDS/anids_defines.vh
// ANIDS Defines
// Clock Period, this is 5ns period (200MHz clock)
`define CLK_PERIOD				16'd5


// APB can work with 8, 16, 32 bit data width
`define APB_DATA_WIDTH			8
`define APB_ADDR_WIDTH			16 							// 15 bits needed, but we use 16.


// DMA Data Width is input vector size, which is 128 bits
`define DMA_DATA_WIDTH			128

// Memory Fetch Unit widths
`define MFU_DATA_WIDTH			`DMA_DATA_WIDTH
`define MFU_FEATURE_WIDTH		`MFU_DATA_WIDTH				// stored feature vector width

// Pipeline Manager widths and history depth
`define PIPELINE_VECTOR_WIDTH	`MFU_FEATURE_WIDTH			// vector width propagated through pipeline manager
`define PIPELINE_COUNTER_WIDTH	7							// counter width for indices 0..127
`define PIPELINE_HISTORY_DEPTH	2							// number of coarse vector buffers before validation
`define PIPELINE_STAGE_CYCLES	64							// 128-bit vector processed over 64 cycles
`define PIPELINE_STAGE_COUNT_W	6							// counter width for 0..63 stage timing

// Input layer widths
`define INPUT_LAYER_FEATURE_WIDTH	`PIPELINE_VECTOR_WIDTH	// full feature vector width seen by input layer
`define INPUT_LAYER_PAIR_WIDTH		2						// number of feature bits processed per counter step

// Hidden layer unit widths
`define HL_FEATURE_PAIR_WIDTH		`INPUT_LAYER_PAIR_WIDTH	// number of feature bits consumed per cycle
`define HL_WEIGHT_WIDTH				8						// signed Q0.7 weight width
`define HL_BIAS_WIDTH				8						// signed Q0.7 bias width
`define HL_RESULT_WIDTH				8						// signed Q0.7 hidden neuron output width
`define HL_PAIR_SUM_WIDTH			9						// sum of two weighted feature contributions
`define HL_ACC_WIDTH				15						// accumulation register width before truncation

// Output layer unit widths
`define OL_INPUT_WIDTH				8						// signed Q0.7 hidden-layer input width
`define OL_WEIGHT_WIDTH				8						// signed Q0.7 output-layer weight width
`define OL_BIAS_WIDTH				8						// signed Q0.7 output-layer bias width
`define OL_RESULT_WIDTH				8						// signed Q0.7 output-layer result width
`define OL_PRODUCT_WIDTH			16						// full signed 8x8 multiply width
`define OL_TRUNC_PRODUCT_WIDTH		8						// product truncated back to Q0.7
`define OL_ACC_WIDTH				15						// accumulation width before final truncation

// Loss function widths
`define LF_FEATURE_PAIR_WIDTH		`INPUT_LAYER_PAIR_WIDTH	// number of original feature bits consumed per cycle
`define LF_RESULT_IN_WIDTH			8						// compared result width
`define LF_ABS_WIDTH				8						// absolute delta width
`define LF_PAIR_SUM_WIDTH			9						// sum of two absolute deltas
`define LF_ACC_WIDTH				15						// accumulation register width before truncation

// Sigmoid LUT address mapper widths
`define MMAP_IN_WIDTH				8						// signed Q0.7 value width before LUT lookup
`define MMAP_ADDR_WIDTH				`LUT_ADDR_WIDTH		// LUT address width after mapping

// LUT Address and Data Sizes
`define LUT_ADDR_WIDTH			8
`define LUT_DATA_WIDTH			8

`define RELU_WIDTH 				8
`define LF_OUT_WIDTH			8



// Weight & Bias Counts
`define HL_WEIGHT_COUNT   		64 * 128   	// 8192
`define HL_BIAS_COUNT      		64       	// 64
`define OL_WEIGHT_COUNT    		128 * 64   	// 8192
`define OL_BIAS_COUNT      		128      	// 128


// ANIDS Control Register Addresses
`define START_REG				0
`define N_REG					1
`define THRESHOLD_REG			2
`define RESULT_REG				3


// Indirect LUT Read/Write Registers
`define LUT_ADDR				4
`define LUT_DATA				5
`define LUT_CTRL				6
`define FREE_REG				7


// Hidden Layer Register Mapping
`define HL_WEIGHT_BASE			8 // we have 128 * 64 of these
`define HL_BIAS_BASE			`HL_WEIGHT_BASE + `HL_WEIGHT_COUNT // and 64 of these


// Output Layer Register Mapping
`define OL_WEIGHT_BASE			`HL_BIAS_BASE + `HL_BIAS_COUNT
`define OL_BIAS_BASE			`OL_WEIGHT_BASE + `OL_WEIGHT_COUNT


// ANIDS memory map borders
`define ANIDS_MAP_START   		`HL_WEIGHT_BASE
`define ANIDS_MAP_END     		`OL_BIAS_BASE + `OL_BIAS_COUNT
`define REG_COUNT				`ANIDS_MAP_END 	// (correct count due to 0-based indexing)


// Pipeline Stage Cycles
`define INPUT_LAYER_CYCLES 		1
`define HIDDEN_LAYER_CYCLES 	64
`define OUTPUT_LAYER_CYCLES 	64
`define LOOKUP_LAYER_CYCLES 	64
`define LOSS_FUNCTION_CYCLES 	64
`define OUTLIER_CYCLES 			1
`define RESULT_CYCLES 			1


// Pipeline Fill and Latency in cycles (pipefill = 259, latency = 130)
`define PIPE_FILL_CYCLES 		(`INPUT_LAYER_CYCLES + `HIDDEN_LAYER_CYCLES + `OUTPUT_LAYER_CYCLES + `LOOKUP_LAYER_CYCLES + `LOSS_FUNCTION_CYCLES + `OUTLIER_CYCLES + `RESULT_CYCLES)
`define LATENCY_IN_CYCLES 		(`LOOKUP_LAYER_CYCLES + `LOSS_FUNCTION_CYCLES + `OUTLIER_CYCLES + `RESULT_CYCLES )

ANIDS/src/result_status_encoder.sv
// ANIDS Result Status Encoder
`include "anids_defines.vh"

module result_status_encoder (
		clk,
		resetN,
		start,
		done,
		outlier_pulse,
		result_wr_en,
		result_wr_data
	);

	parameter STATUS_WIDTH = `APB_DATA_WIDTH;
	parameter RESULT_HOLD_CYCLES = 8;
	parameter HOLD_COUNT_WIDTH   = 4;
	localparam [STATUS_WIDTH-1:0] STATUS_NOT_ANOMALY = 8'd0;
	localparam [STATUS_WIDTH-1:0] STATUS_ANOMALY     = 8'd1;
	localparam [STATUS_WIDTH-1:0] STATUS_WAITING     = 8'd2;
	localparam [STATUS_WIDTH-1:0] STATUS_IDLE        = 8'd3;

	// ----------------------------------------------------------------------
	//                  		I/O Ports
	// ----------------------------------------------------------------------
	input  wire                         clk;
	input  wire                         resetN;
	input  wire                         start;
	input  wire                         done;
	input  wire                         outlier_pulse;
	output reg                          result_wr_en;
	output reg  [STATUS_WIDTH-1:0]      result_wr_data;

	// ----------------------------------------------------------------------
	//                  		Status Encoding
	// ----------------------------------------------------------------------
	reg                                initialized;
	reg [STATUS_WIDTH-1:0]             current_status;
	reg [STATUS_WIDTH-1:0]             next_status;
	reg [HOLD_COUNT_WIDTH-1:0]         hold_count;
	wire                               holding_result = (hold_count != {HOLD_COUNT_WIDTH{1'b0}});

	always @(*) begin
		if (!start) begin
			next_status = STATUS_IDLE;
		end
		else if (holding_result) begin
			next_status = current_status;
		end
		else if (done) begin
			next_status = outlier_pulse ? STATUS_ANOMALY
			                            : STATUS_NOT_ANOMALY;
		end
		else begin
			next_status = STATUS_WAITING;
		end
	end

	always @(posedge clk or negedge resetN) begin
		if (!resetN) begin
			initialized    <= #1 1'b0;
			current_status <= #1 STATUS_IDLE;
			result_wr_en   <= #1 1'b0;
			result_wr_data <= #1 STATUS_IDLE;
			hold_count     <= #1 {HOLD_COUNT_WIDTH{1'b0}};
		end
		else begin
			result_wr_en <= #1 1'b0;

			if (!start) begin
				hold_count <= #1 {HOLD_COUNT_WIDTH{1'b0}};
			end
			else if (holding_result) begin
				hold_count <= #1 hold_count - 1'b1;
			end

			if (!initialized || (next_status != current_status)) begin
				initialized    <= #1 1'b1;
				current_status <= #1 next_status;
				result_wr_en   <= #1 1'b1;
				result_wr_data <= #1 next_status;

				if (done) begin
					hold_count <= #1 RESULT_HOLD_CYCLES - 1'b1;
				end
				else begin
					hold_count <= #1 {HOLD_COUNT_WIDTH{1'b0}};
				end
			end
		end
	end

endmodule

ANIDS/tb/unit/result_status_encoder_tb.sv
// Purpose: verifies RESULT_REG status encoding, write pulses, result hold time, and idle/waiting transitions.
// ANIDS - Result Status Encoder Testbench
`timescale 1ns/100ps
`include "anids_defines.vh"

module result_status_encoder_tb;

	localparam [7:0] STATUS_NOT_ANOMALY = 8'd0;
	localparam [7:0] STATUS_ANOMALY     = 8'd1;
	localparam [7:0] STATUS_WAITING     = 8'd2;
	localparam [7:0] STATUS_IDLE        = 8'd3;
	localparam integer RESULT_HOLD_CYCLES = 8;

	reg                         clk;
	reg                         resetN;
	reg                         start;
	reg                         done;
	reg                         outlier_pulse;
	wire                        result_wr_en;
	wire [`APB_DATA_WIDTH-1:0]  result_wr_data;

	result_status_encoder dut (
		.clk           (clk),
		.resetN        (resetN),
		.start         (start),
		.done          (done),
		.outlier_pulse (outlier_pulse),
		.result_wr_en  (result_wr_en),
		.result_wr_data(result_wr_data)
	);

	always #2.5 clk = ~clk;

	initial begin
		$dumpfile("result_status_encoder_tb.vcd");
		$dumpvars(0, result_status_encoder_tb);

		clk           = 1'b0;
		resetN        = 1'b0;
		start         = 1'b0;
		done          = 1'b0;
		outlier_pulse = 1'b0;

		@(posedge clk);
		#2;
		check_outputs(1'b0, STATUS_IDLE, "reset keeps write disabled");

		resetN = 1'b1;
		@(posedge clk);
		#2;
		check_outputs(1'b1, STATUS_IDLE, "first active cycle writes idle status");

		@(posedge clk);
		#2;
		check_outputs(1'b0, STATUS_IDLE, "idle status write is a one-cycle pulse");

		start = 1'b1;
		@(posedge clk);
		#2;
		check_outputs(1'b1, STATUS_WAITING, "start drives status to waiting");

		@(posedge clk);
		#2;
		check_outputs(1'b0, STATUS_WAITING, "waiting write is a one-cycle pulse");

		done          = 1'b1;
		outlier_pulse = 1'b1;
		@(posedge clk);
		#2;
		check_outputs(1'b1, STATUS_ANOMALY, "anomaly result is encoded on done");

		done          = 1'b0;
		outlier_pulse = 1'b0;
		repeat (RESULT_HOLD_CYCLES - 1) begin
			@(posedge clk);
			#2;
			check_outputs(1'b0, STATUS_ANOMALY, "anomaly status is held for polling");
		end
		@(posedge clk);
		#2;
		check_outputs(1'b1, STATUS_WAITING, "status returns to waiting after anomaly hold");

		done = 1'b1;
		@(posedge clk);
		#2;
		check_outputs(1'b1, STATUS_NOT_ANOMALY, "non-anomaly result is encoded on done");

		done = 1'b0;
		repeat (RESULT_HOLD_CYCLES - 1) begin
			@(posedge clk);
			#2;
			check_outputs(1'b0, STATUS_NOT_ANOMALY, "non-anomaly status is held for polling");
		end
		@(posedge clk);
		#2;
		check_outputs(1'b1, STATUS_WAITING, "status returns to waiting after non-anomaly hold");

		start = 1'b0;
		@(posedge clk);
		#2;
		check_outputs(1'b1, STATUS_IDLE, "dropping start returns to idle");

		@(posedge clk);
		#2;
		check_outputs(1'b0, STATUS_IDLE, "idle transition is a one-cycle pulse");

		$display("RESULT_STATUS_ENCODER TB PASSED");
		$finish;
	end

	task check_outputs(
		input                          expected_wr_en,
		input [`APB_DATA_WIDTH-1:0]    expected_wr_data,
		input [255:0]                  test_name
	);
	begin
		if (result_wr_en !== expected_wr_en || result_wr_data !== expected_wr_data) begin
			$error("FAIL: %0s | wr_en=%0b expected_wr_en=%0b wr_data=%0d expected_wr_data=%0d",
				test_name, result_wr_en, expected_wr_en, result_wr_data, expected_wr_data);
			$finish;
		end
		else begin
			$display("PASS: %0s", test_name);
		end
	end
	endtask

endmodule

Outputs/vcd/result_status_encoder_tb.vcd
$date
	Tue Jun 09 14:54:15 2026
$end
$version
	Icarus Verilog
$end
$timescale
	100ps
$end
$scope module result_status_encoder_tb $end
$var wire 1 ! result_wr_en $end
$var wire 8 " result_wr_data [7:0] $end
$var parameter 32 # RESULT_HOLD_CYCLES $end
$var parameter 8 $ STATUS_ANOMALY $end
$var parameter 8 % STATUS_IDLE $end
$var parameter 8 & STATUS_NOT_ANOMALY $end
$var parameter 8 ' STATUS_WAITING $end
$var reg 1 ( clk $end
$var reg 1 ) done $end
$var reg 1 * outlier_pulse $end
$var reg 1 + resetN $end
$var reg 1 , start $end
$scope module dut $end
$var wire 1 ( clk $end
$var wire 1 ) done $end
$var wire 1 * outlier_pulse $end
$var wire 1 + resetN $end
$var wire 1 , start $end
$var wire 1 - holding_result $end
$var parameter 32 . HOLD_COUNT_WIDTH $end
$var parameter 32 / RESULT_HOLD_CYCLES $end
$var parameter 8 0 STATUS_ANOMALY $end
$var parameter 8 1 STATUS_IDLE $end
$var parameter 8 2 STATUS_NOT_ANOMALY $end
$var parameter 8 3 STATUS_WAITING $end
$var parameter 32 4 STATUS_WIDTH $end
$var reg 8 5 current_status [7:0] $end
$var reg 4 6 hold_count [3:0] $end
$var reg 1 7 initialized $end
$var reg 8 8 next_status [7:0] $end
$var reg 8 9 result_wr_data [7:0] $end
$var reg 1 ! result_wr_en $end
$upscope $end
$scope task check_outputs $end
$var reg 8 : expected_wr_data [7:0] $end
$var reg 1 ; expected_wr_en $end
$var reg 256 < test_name [255:0] $end
$upscope $end
$upscope $end
$enddefinitions $end
$comment Show the parameter values. $end
$dumpall
b1000 4
b10 3
b0 2
b11 1
b1 0
b1000 /
b100 .
b10 '
b0 &
b11 %
b1 $
b1000 #
$end
#0
$dumpvars
bx <
x;
bx :
bx 9
b11 8
x7
bx 6
bx 5
x-
0,
0+
0*
0)
0(
bx "
x!
$end
#10
0-
b0 6
b11 "
b11 9
0!
b11 5
07
#25
1(
#45
1+
b111001001100101011100110110010101110100001000000110101101100101011001010111000001110011001000000111011101110010011010010111010001100101001000000110010001101001011100110110000101100010011011000110010101100100 <
b11 :
0;
#50
0(
#75
1(
#85
1!
17
#95
b10000001100001011000110111010001101001011101100110010100100000011000110111100101100011011011000110010100100000011101110111001001101001011101000110010101110011001000000110100101100100011011000110010100100000011100110111010001100001011101000111010101110011 <
1;
#100
0(
#125
1(
#135
0!
#145
b10 8
1,
b111010001100001011101000111010101110011001000000111011101110010011010010111010001100101001000000110100101110011001000000110000100100000011011110110111001100101001011010110001101111001011000110110110001100101001000000111000001110101011011000111001101100101 <
0;
#150
0(
#175
1(
#185
b10 "
b10 9
1!
b10 5
#195
b11100110111010001100001011100100111010000100000011001000111001001101001011101100110010101110011001000000111001101110100011000010111010001110101011100110010000001110100011011110010000001110111011000010110100101110100011010010110111001100111 <
b10 :
1;
#200
0(
#225
1(
#235
0!
#245
b1 8
1*
1)
b110100101110100011010010110111001100111001000000111011101110010011010010111010001100101001000000110100101110011001000000110000100100000011011110110111001100101001011010110001101111001011000110110110001100101001000000111000001110101011011000111001101100101 <
0;
#250
0(
#275
1(
#285
1-
b111 6
b1 "
b1 9
1!
b1 5
#295
0*
0)
b110111001101111011011010110000101101100011110010010000001110010011001010111001101110101011011000111010000100000011010010111001100100000011001010110111001100011011011110110010001100101011001000010000001101111011011100010000001100100011011110110111001100101 <
b1 :
1;
#300
0(
#325
1(
#335
b110 6
0!
#345
b110111101101101011000010110110001111001001000000111001101110100011000010111010001110101011100110010000001101001011100110010000001101000011001010110110001100100001000000110011001101111011100100010000001110000011011110110110001101100011010010110111001100111 <
0;
#350
0(
#375
1(
#385
b101 6
#400
0(
#425
1(
#435
b100 6
#450
0(
#475
1(
#485
b11 6
#500
0(
#525
1(
#535
b10 6
#550
0(
#575
1(
#585
b1 6
#600
0(
#625
1(
#635
b10 8
0-
b0 6
#650
0(
#675
1(
#685
b10 "
b10 9
1!
b10 5
#695
b0 8
1)
b110111001110011001000000111010001101111001000000111011101100001011010010111010001101001011011100110011100100000011000010110011001110100011001010111001000100000011000010110111001101111011011010110000101101100011110010010000001101000011011110110110001100100 <
b10 :
1;
#700
0(
#725
1(
#735
1-
b111 6
b0 "
b0 9
b0 5
1!
#745
0)
b110111001101111011011010110000101101100011110010010000001110010011001010111001101110101011011000111010000100000011010010111001100100000011001010110111001100011011011110110010001100101011001000010000001101111011011100010000001100100011011110110111001100101 <
b0 :
#750
0(
#775
1(
#785
b110 6
0!
#795
b110111101101101011000010110110001111001001000000111001101110100011000010111010001110101011100110010000001101001011100110010000001101000011001010110110001100100001000000110011001101111011100100010000001110000011011110110110001101100011010010110111001100111 <
0;
#800
0(
#825
1(
#835
b101 6
#850
0(
#875
1(
#885
b100 6
#900
0(
#925
1(
#935
b11 6
#950
0(
#975
1(
#985
b10 6
#1000
0(
#1025
1(
#1035
b1 6
#1050
0(
#1075
1(
#1085
b10 8
0-
b0 6
#1100
0(
#1125
1(
#1135
b10 "
b10 9
1!
b10 5
#1145
b11 8
0,
b110111100100000011101110110000101101001011101000110100101101110011001110010000001100001011001100111010001100101011100100010000001101110011011110110111000101101011000010110111001101111011011010110000101101100011110010010000001101000011011110110110001100100 <
b10 :
1;
#1150
0(
#1175
1(
#1185
b11 "
b11 9
b11 5
1!
#1195
b11001000111001001101111011100000111000001101001011011100110011100100000011100110111010001100001011100100111010000100000011100100110010101110100011101010111001001101110011100110010000001110100011011110010000001101001011001000110110001100101 <
b11 :
#1200
0(
#1225
1(
#1235
0!
#1245
b10000001110100011100100110000101101110011100110110100101110100011010010110111101101110001000000110100101110011001000000110000100100000011011110110111001100101001011010110001101111001011000110110110001100101001000000111000001110101011011000111001101100101 <
0;
