ANIDS/anids_defines.vh
// ANIDS Defines
// Clock Period, this is 5ns period (200MHz clock)
`define CLK_PERIOD				16'd5


// APB can work with 8, 16, 32 bit data width
`define APB_DATA_WIDTH			8
`define APB_ADDR_WIDTH			16 							// 15 bits needed, but we use 16.


// DMA Data Width is input vector size, which is 128 bits
`define DMA_DATA_WIDTH			128

// Memory Fetch Unit widths
`define MFU_DATA_WIDTH			`DMA_DATA_WIDTH
`define MFU_FEATURE_WIDTH		`MFU_DATA_WIDTH				// stored feature vector width

// Pipeline Manager widths and history depth
`define PIPELINE_VECTOR_WIDTH	`MFU_FEATURE_WIDTH			// vector width propagated through pipeline manager
`define PIPELINE_COUNTER_WIDTH	7							// counter width for indices 0..127
`define PIPELINE_HISTORY_DEPTH	2							// number of coarse vector buffers before validation
`define PIPELINE_STAGE_CYCLES	64							// 128-bit vector processed over 64 cycles
`define PIPELINE_STAGE_COUNT_W	6							// counter width for 0..63 stage timing

// Input layer widths
`define INPUT_LAYER_FEATURE_WIDTH	`PIPELINE_VECTOR_WIDTH	// full feature vector width seen by input layer
`define INPUT_LAYER_PAIR_WIDTH		2						// number of feature bits processed per counter step

// Hidden layer unit widths
`define HL_FEATURE_PAIR_WIDTH		`INPUT_LAYER_PAIR_WIDTH	// number of feature bits consumed per cycle
`define HL_WEIGHT_WIDTH				8						// signed Q0.7 weight width
`define HL_BIAS_WIDTH				8						// signed Q0.7 bias width
`define HL_RESULT_WIDTH				8						// signed Q0.7 hidden neuron output width
`define HL_PAIR_SUM_WIDTH			9						// sum of two weighted feature contributions
`define HL_ACC_WIDTH				15						// accumulation register width before truncation

// Output layer unit widths
`define OL_INPUT_WIDTH				8						// signed Q0.7 hidden-layer input width
`define OL_WEIGHT_WIDTH				8						// signed Q0.7 output-layer weight width
`define OL_BIAS_WIDTH				8						// signed Q0.7 output-layer bias width
`define OL_RESULT_WIDTH				8						// signed Q0.7 output-layer result width
`define OL_PRODUCT_WIDTH			16						// full signed 8x8 multiply width
`define OL_TRUNC_PRODUCT_WIDTH		8						// product truncated back to Q0.7
`define OL_ACC_WIDTH				15						// accumulation width before final truncation

// Loss function widths
`define LF_FEATURE_PAIR_WIDTH		`INPUT_LAYER_PAIR_WIDTH	// number of original feature bits consumed per cycle
`define LF_RESULT_IN_WIDTH			8						// compared result width
`define LF_ABS_WIDTH				8						// absolute delta width
`define LF_PAIR_SUM_WIDTH			9						// sum of two absolute deltas
`define LF_ACC_WIDTH				15						// accumulation register width before truncation

// Sigmoid LUT address mapper widths
`define MMAP_IN_WIDTH				8						// signed Q0.7 value width before LUT lookup
`define MMAP_ADDR_WIDTH				`LUT_ADDR_WIDTH		// LUT address width after mapping

// LUT Address and Data Sizes
`define LUT_ADDR_WIDTH			8
`define LUT_DATA_WIDTH			8

`define RELU_WIDTH 				8
`define LF_OUT_WIDTH			8



// Weight & Bias Counts
`define HL_WEIGHT_COUNT   		64 * 128   	// 8192
`define HL_BIAS_COUNT      		64       	// 64
`define OL_WEIGHT_COUNT    		128 * 64   	// 8192
`define OL_BIAS_COUNT      		128      	// 128


// ANIDS Control Register Addresses
`define START_REG				0
`define N_REG					1
`define THRESHOLD_REG			2
`define RESULT_REG				3


// Indirect LUT Read/Write Registers
`define LUT_ADDR				4
`define LUT_DATA				5
`define LUT_CTRL				6
`define FREE_REG				7


// Hidden Layer Register Mapping
`define HL_WEIGHT_BASE			8 // we have 128 * 64 of these
`define HL_BIAS_BASE			`HL_WEIGHT_BASE + `HL_WEIGHT_COUNT // and 64 of these


// Output Layer Register Mapping
`define OL_WEIGHT_BASE			`HL_BIAS_BASE + `HL_BIAS_COUNT
`define OL_BIAS_BASE			`OL_WEIGHT_BASE + `OL_WEIGHT_COUNT


// ANIDS memory map borders
`define ANIDS_MAP_START   		`HL_WEIGHT_BASE
`define ANIDS_MAP_END     		`OL_BIAS_BASE + `OL_BIAS_COUNT
`define REG_COUNT				`ANIDS_MAP_END 	// (correct count due to 0-based indexing)


// Pipeline Stage Cycles
`define INPUT_LAYER_CYCLES 		1
`define HIDDEN_LAYER_CYCLES 	64
`define OUTPUT_LAYER_CYCLES 	64
`define LOOKUP_LAYER_CYCLES 	64
`define LOSS_FUNCTION_CYCLES 	64
`define OUTLIER_CYCLES 			1
`define RESULT_CYCLES 			1


// Pipeline Fill and Latency in cycles (pipefill = 259, latency = 130)
`define PIPE_FILL_CYCLES 		(`INPUT_LAYER_CYCLES + `HIDDEN_LAYER_CYCLES + `OUTPUT_LAYER_CYCLES + `LOOKUP_LAYER_CYCLES + `LOSS_FUNCTION_CYCLES + `OUTLIER_CYCLES + `RESULT_CYCLES)
`define LATENCY_IN_CYCLES 		(`LOOKUP_LAYER_CYCLES + `LOSS_FUNCTION_CYCLES + `OUTLIER_CYCLES + `RESULT_CYCLES )

ANIDS/src/lut_mem.v
// ANIDS LUT Module
`include "anids_defines.vh"

module lut_mem (
		clk,
		resetN,
		rd_addr,
		wr_addr,
		wr_en,
		wr_data,
		rd_data
	);

	//			=== Parameters ===
	parameter DATA_WIDTH = `LUT_DATA_WIDTH;
	parameter ADDR_WIDTH = `LUT_ADDR_WIDTH;
	parameter RAM_DEPTH  = 1 << ADDR_WIDTH; // this is = 2 ^ ADDR_WIDTH


	//			=== System Signals ===
	input                  			clk;
	input				   			resetN;


	//			=== Read Signals ===
	input 		[ADDR_WIDTH-1:0] 	rd_addr;
	output reg 	[DATA_WIDTH-1:0] 	rd_data;


	//			=== Write Signals ===
	input 		[ADDR_WIDTH-1:0] 	wr_addr;
	input 		[DATA_WIDTH-1:0] 	wr_data;
	input                  			wr_en;


	//			=== Memory ===
	reg [DATA_WIDTH-1:0] memory [0:RAM_DEPTH-1];


	//			=== Read/Write logic ===
	always @(posedge clk or negedge resetN) begin
		if (!resetN) begin
			rd_data <= #1 {DATA_WIDTH{1'b0}};
		end else begin
			if (wr_en) memory[wr_addr] <= #1 wr_data;
			rd_data <= #1 memory[rd_addr];
		end
	end



	//*** ask shahar about this:
	//	DO I DO AS I KEPT ABOVE, OR WHAT I HAVE IN THE COMMENT BELOW?
	//  	WHAT SYNTHESIZES INTO RAM BETTER?

	// // === Write Logic ===
	// genvar i;
	// generate
	// 	for (i = 0; i < RAM_DEPTH; i++) begin
	// 		always @(posedge clk or negedge resetN) begin
	// 			if (!resetN) begin
	// 				memory[i] <= #1 {DATA_WIDTH{1'b0}};
	// 			end
	// 			else if (wr_en && wr_addr == i) begin
	// 				memory[i] <= #1 wr_data;
	// 			end
	// 		end
	// 	end
	// endgenerate


	// //			=== Read Logic ===
	// always @(posedge clk or negedge resetN) begin
	// 	if (!resetN) begin
	// 		rd_data <= #1 {DATA_WIDTH{1'b0}};
	// 	end
	// 	else if (rd_addr < RAM_DEPTH) begin // safety condition, prob not necessary
	// 		rd_data <= #1 memory[rd_addr];
	// 	end
	// end

endmodule

ANIDS/tb/lut_rw_tb.v
// ANIDS - LUT Memory Read/Write Testbench
`timescale 1ns/100ps
`include "anids_defines.vh"

module lut_rw_tb;

  localparam DATA_WIDTH = `LUT_DATA_WIDTH;
  localparam ADDR_WIDTH = `LUT_ADDR_WIDTH;
  localparam RAM_DEPTH  = 1 << ADDR_WIDTH;

  // DUT signals
  reg                       clk;
  reg                       resetN;
  reg  [ADDR_WIDTH-1:0]     rd_addr;
  reg  [ADDR_WIDTH-1:0]     wr_addr;
  reg  [DATA_WIDTH-1:0]     wr_data;
  reg                       wr_en;
  wire [DATA_WIDTH-1:0]     rd_data;

  // Clock generation: 200 MHz (period 5ns)
  always #2.5 clk = ~clk;

  // DUT
  lut_mem dut (
    .clk     (clk),
    .resetN  (resetN),
    .rd_addr (rd_addr),
    .wr_addr (wr_addr),
    .wr_en   (wr_en),
    .wr_data (wr_data),
    .rd_data (rd_data)
  );

  integer idx;
  integer errors;

  initial begin
    $dumpfile("lut_rw_tb.vcd");
    $dumpvars(0, lut_rw_tb);

    // Reset and defaults
    clk     = 1'b0;
    resetN  = 1'b0;
    rd_addr = {ADDR_WIDTH{1'b0}};
    wr_addr = {ADDR_WIDTH{1'b0}};
    wr_data = {DATA_WIDTH{1'b0}};
    wr_en   = 1'b0;
    errors  = 0;

    // Release reset
    repeat (2) @(posedge clk);
    resetN = 1'b1;

    // Write phase: write each location with its address value
    for (idx = 0; idx < RAM_DEPTH; idx = idx + 1) begin
      wr_en   <= 1'b1;
      wr_addr <= idx[ADDR_WIDTH-1:0];
      wr_data <= idx[DATA_WIDTH-1:0];
      @(posedge clk);
      wr_en   <= 1'b0;
    end

    // Allow last write to settle
    @(posedge clk);

    // Read/verify phase (synchronous read requires one-cycle latency)
    // Prime first read
    rd_addr <= {ADDR_WIDTH{1'b0}};
    @(posedge clk);
    #1;
    if (rd_data !== {DATA_WIDTH{1'b0}}) begin
      $error("Mismatch at addr 0: got %0h expected %0h", rd_data, {DATA_WIDTH{1'b0}});
      errors = errors + 1;
    end else begin
      $display("PASS addr 0 data %0h", rd_data);
    end

    // Subsequent reads: rd_data corresponds to rd_addr from previous cycle
    for (idx = 1; idx < RAM_DEPTH; idx = idx + 1) begin
      rd_addr <= idx[ADDR_WIDTH-1:0];
      @(posedge clk);
      #1;
      if (rd_data !== (idx-1)) begin
        $error("Mismatch at addr %0d: got %0h expected %0h",
               idx-1, rd_data, (idx-1));
        errors = errors + 1;
      end else begin
        $display("PASS addr %0d data %0h", idx-1, rd_data);
      end
    end

    // Capture last address (RAM_DEPTH-1)
    @(posedge clk);
    #1;
    if (rd_data !== (RAM_DEPTH-1)) begin
      $error("Mismatch at addr %0d: got %0h expected %0h",
             RAM_DEPTH-1, rd_data, (RAM_DEPTH-1));
      errors = errors + 1;
    end else begin
      $display("PASS addr %0d data %0h", RAM_DEPTH-1, rd_data);
    end

    if (errors == 0)
      $display("LUT_MEM TB PASSED (%0d entries)", RAM_DEPTH);
    else
      $display("LUT_MEM TB FAILED with %0d errors", errors);

    $finish;
  end
endmodule

outputs/lut_rw_tb.vcd
$date
	Wed Feb 11 17:57:12 2026
$end
$version
	Icarus Verilog
$end
$timescale
	100ps
$end
$scope module lut_rw_tb $end
$var wire 8 ! rd_data [7:0] $end
$var parameter 32 " ADDR_WIDTH $end
$var parameter 32 # DATA_WIDTH $end
$var parameter 39 $ RAM_DEPTH $end
$var reg 1 % clk $end
$var reg 7 & rd_addr [6:0] $end
$var reg 1 ' resetN $end
$var reg 7 ( wr_addr [6:0] $end
$var reg 8 ) wr_data [7:0] $end
$var reg 1 * wr_en $end
$var integer 32 + errors [31:0] $end
$var integer 32 , idx [31:0] $end
$scope module dut $end
$var wire 1 % clk $end
$var wire 7 - rd_addr [6:0] $end
$var wire 1 ' resetN $end
$var wire 7 . wr_addr [6:0] $end
$var wire 8 / wr_data [7:0] $end
$var wire 1 * wr_en $end
$var parameter 32 0 ADDR_WIDTH $end
$var parameter 32 1 DATA_WIDTH $end
$var parameter 39 2 RAM_DEPTH $end
$var reg 8 3 rd_data [7:0] $end
$upscope $end
$upscope $end
$enddefinitions $end
$comment Show the parameter values. $end
$dumpall
b10000000 2
b1000 1
b111 0
b10000000 $
b1000 #
b111 "
$end
#0
$dumpvars
bx 3
b0 /
b0 .
b0 -
bx ,
b0 +
0*
b0 )
b0 (
0'
b0 &
0%
bx !
$end
#10
b0 !
b0 3
#25
1%
#50
0%
#75
1*
b0 ,
1'
1%
#85
bx !
bx 3
#100
0%
#125
b1 )
b1 /
b1 (
b1 .
1*
b1 ,
1%
#150
0%
#175
b10 )
b10 /
b10 (
b10 .
1*
b10 ,
1%
#185
b0 !
b0 3
#200
0%
#225
b11 )
b11 /
b11 (
b11 .
1*
b11 ,
1%
#250
0%
#275
b100 )
b100 /
b100 (
b100 .
1*
b100 ,
1%
#300
0%
#325
b101 )
b101 /
b101 (
b101 .
1*
b101 ,
1%
#350
0%
#375
b110 )
b110 /
b110 (
b110 .
1*
b110 ,
1%
#400
0%
#425
b111 )
b111 /
b111 (
b111 .
1*
b111 ,
1%
#450
0%
#475
b1000 )
b1000 /
b1000 (
b1000 .
1*
b1000 ,
1%
#500
0%
#525
b1001 )
b1001 /
b1001 (
b1001 .
1*
b1001 ,
1%
#550
0%
#575
b1010 )
b1010 /
b1010 (
b1010 .
1*
b1010 ,
1%
#600
0%
#625
b1011 )
b1011 /
b1011 (
b1011 .
1*
b1011 ,
1%
#650
0%
#675
b1100 )
b1100 /
b1100 (
b1100 .
1*
b1100 ,
1%
#700
0%
#725
b1101 )
b1101 /
b1101 (
b1101 .
1*
b1101 ,
1%
#750
0%
#775
b1110 )
b1110 /
b1110 (
b1110 .
1*
b1110 ,
1%
#800
0%
#825
b1111 )
b1111 /
b1111 (
b1111 .
1*
b1111 ,
1%
#850
0%
#875
b10000 )
b10000 /
b10000 (
b10000 .
1*
b10000 ,
1%
#900
0%
#925
b10001 )
b10001 /
b10001 (
b10001 .
1*
b10001 ,
1%
#950
0%
#975
b10010 )
b10010 /
b10010 (
b10010 .
1*
b10010 ,
1%
#1000
0%
#1025
b10011 )
b10011 /
b10011 (
b10011 .
1*
b10011 ,
1%
#1050
0%
#1075
b10100 )
b10100 /
b10100 (
b10100 .
1*
b10100 ,
1%
#1100
0%
#1125
b10101 )
b10101 /
b10101 (
b10101 .
1*
b10101 ,
1%
#1150
0%
#1175
b10110 )
b10110 /
b10110 (
b10110 .
1*
b10110 ,
1%
#1200
0%
#1225
b10111 )
b10111 /
b10111 (
b10111 .
1*
b10111 ,
1%
#1250
0%
#1275
b11000 )
b11000 /
b11000 (
b11000 .
1*
b11000 ,
1%
#1300
0%
#1325
b11001 )
b11001 /
b11001 (
b11001 .
1*
b11001 ,
1%
#1350
0%
#1375
b11010 )
b11010 /
b11010 (
b11010 .
1*
b11010 ,
1%
#1400
0%
#1425
b11011 )
b11011 /
b11011 (
b11011 .
1*
b11011 ,
1%
#1450
0%
#1475
b11100 )
b11100 /
b11100 (
b11100 .
1*
b11100 ,
1%
#1500
0%
#1525
b11101 )
b11101 /
b11101 (
b11101 .
1*
b11101 ,
1%
#1550
0%
#1575
b11110 )
b11110 /
b11110 (
b11110 .
1*
b11110 ,
1%
#1600
0%
#1625
b11111 )
b11111 /
b11111 (
b11111 .
1*
b11111 ,
1%
#1650
0%
#1675
b100000 )
b100000 /
b100000 (
b100000 .
1*
b100000 ,
1%
#1700
0%
#1725
b100001 )
b100001 /
b100001 (
b100001 .
1*
b100001 ,
1%
#1750
0%
#1775
b100010 )
b100010 /
b100010 (
b100010 .
1*
b100010 ,
1%
#1800
0%
#1825
b100011 )
b100011 /
b100011 (
b100011 .
1*
b100011 ,
1%
#1850
0%
#1875
b100100 )
b100100 /
b100100 (
b100100 .
1*
b100100 ,
1%
#1900
0%
#1925
b100101 )
b100101 /
b100101 (
b100101 .
1*
b100101 ,
1%
#1950
0%
#1975
b100110 )
b100110 /
b100110 (
b100110 .
1*
b100110 ,
1%
#2000
0%
#2025
b100111 )
b100111 /
b100111 (
b100111 .
1*
b100111 ,
1%
#2050
0%
#2075
b101000 )
b101000 /
b101000 (
b101000 .
1*
b101000 ,
1%
#2100
0%
#2125
b101001 )
b101001 /
b101001 (
b101001 .
1*
b101001 ,
1%
#2150
0%
#2175
b101010 )
b101010 /
b101010 (
b101010 .
1*
b101010 ,
1%
#2200
0%
#2225
b101011 )
b101011 /
b101011 (
b101011 .
1*
b101011 ,
1%
#2250
0%
#2275
b101100 )
b101100 /
b101100 (
b101100 .
1*
b101100 ,
1%
#2300
0%
#2325
b101101 )
b101101 /
b101101 (
b101101 .
1*
b101101 ,
1%
#2350
0%
#2375
b101110 )
b101110 /
b101110 (
b101110 .
1*
b101110 ,
1%
#2400
0%
#2425
b101111 )
b101111 /
b101111 (
b101111 .
1*
b101111 ,
1%
#2450
0%
#2475
b110000 )
b110000 /
b110000 (
b110000 .
1*
b110000 ,
1%
#2500
0%
#2525
b110001 )
b110001 /
b110001 (
b110001 .
1*
b110001 ,
1%
#2550
0%
#2575
b110010 )
b110010 /
b110010 (
b110010 .
1*
b110010 ,
1%
#2600
0%
#2625
b110011 )
b110011 /
b110011 (
b110011 .
1*
b110011 ,
1%
#2650
0%
#2675
b110100 )
b110100 /
b110100 (
b110100 .
1*
b110100 ,
1%
#2700
0%
#2725
b110101 )
b110101 /
b110101 (
b110101 .
1*
b110101 ,
1%
#2750
0%
#2775
b110110 )
b110110 /
b110110 (
b110110 .
1*
b110110 ,
1%
#2800
0%
#2825
b110111 )
b110111 /
b110111 (
b110111 .
1*
b110111 ,
1%
#2850
0%
#2875
b111000 )
b111000 /
b111000 (
b111000 .
1*
b111000 ,
1%
#2900
0%
#2925
b111001 )
b111001 /
b111001 (
b111001 .
1*
b111001 ,
1%
#2950
0%
#2975
b111010 )
b111010 /
b111010 (
b111010 .
1*
b111010 ,
1%
#3000
0%
#3025
b111011 )
b111011 /
b111011 (
b111011 .
1*
b111011 ,
1%
#3050
0%
#3075
b111100 )
b111100 /
b111100 (
b111100 .
1*
b111100 ,
1%
#3100
0%
#3125
b111101 )
b111101 /
b111101 (
b111101 .
1*
b111101 ,
1%
#3150
0%
#3175
b111110 )
b111110 /
b111110 (
b111110 .
1*
b111110 ,
1%
#3200
0%
#3225
b111111 )
b111111 /
b111111 (
b111111 .
1*
b111111 ,
1%
#3250
0%
#3275
b1000000 )
b1000000 /
b1000000 (
b1000000 .
1*
b1000000 ,
1%
#3300
0%
#3325
b1000001 )
b1000001 /
b1000001 (
b1000001 .
1*
b1000001 ,
1%
#3350
0%
#3375
b1000010 )
b1000010 /
b1000010 (
b1000010 .
1*
b1000010 ,
1%
#3400
0%
#3425
b1000011 )
b1000011 /
b1000011 (
b1000011 .
1*
b1000011 ,
1%
#3450
0%
#3475
b1000100 )
b1000100 /
b1000100 (
b1000100 .
1*
b1000100 ,
1%
#3500
0%
#3525
b1000101 )
b1000101 /
b1000101 (
b1000101 .
1*
b1000101 ,
1%
#3550
0%
#3575
b1000110 )
b1000110 /
b1000110 (
b1000110 .
1*
b1000110 ,
1%
#3600
0%
#3625
b1000111 )
b1000111 /
b1000111 (
b1000111 .
1*
b1000111 ,
1%
#3650
0%
#3675
b1001000 )
b1001000 /
b1001000 (
b1001000 .
1*
b1001000 ,
1%
#3700
0%
#3725
b1001001 )
b1001001 /
b1001001 (
b1001001 .
1*
b1001001 ,
1%
#3750
0%
#3775
b1001010 )
b1001010 /
b1001010 (
b1001010 .
1*
b1001010 ,
1%
#3800
0%
#3825
b1001011 )
b1001011 /
b1001011 (
b1001011 .
1*
b1001011 ,
1%
#3850
0%
#3875
b1001100 )
b1001100 /
b1001100 (
b1001100 .
1*
b1001100 ,
1%
#3900
0%
#3925
b1001101 )
b1001101 /
b1001101 (
b1001101 .
1*
b1001101 ,
1%
#3950
0%
#3975
b1001110 )
b1001110 /
b1001110 (
b1001110 .
1*
b1001110 ,
1%
#4000
0%
#4025
b1001111 )
b1001111 /
b1001111 (
b1001111 .
1*
b1001111 ,
1%
#4050
0%
#4075
b1010000 )
b1010000 /
b1010000 (
b1010000 .
1*
b1010000 ,
1%
#4100
0%
#4125
b1010001 )
b1010001 /
b1010001 (
b1010001 .
1*
b1010001 ,
1%
#4150
0%
#4175
b1010010 )
b1010010 /
b1010010 (
b1010010 .
1*
b1010010 ,
1%
#4200
0%
#4225
b1010011 )
b1010011 /
b1010011 (
b1010011 .
1*
b1010011 ,
1%
#4250
0%
#4275
b1010100 )
b1010100 /
b1010100 (
b1010100 .
1*
b1010100 ,
1%
#4300
0%
#4325
b1010101 )
b1010101 /
b1010101 (
b1010101 .
1*
b1010101 ,
1%
#4350
0%
#4375
b1010110 )
b1010110 /
b1010110 (
b1010110 .
1*
b1010110 ,
1%
#4400
0%
#4425
b1010111 )
b1010111 /
b1010111 (
b1010111 .
1*
b1010111 ,
1%
#4450
0%
#4475
b1011000 )
b1011000 /
b1011000 (
b1011000 .
1*
b1011000 ,
1%
#4500
0%
#4525
b1011001 )
b1011001 /
b1011001 (
b1011001 .
1*
b1011001 ,
1%
#4550
0%
#4575
b1011010 )
b1011010 /
b1011010 (
b1011010 .
1*
b1011010 ,
1%
#4600
0%
#4625
b1011011 )
b1011011 /
b1011011 (
b1011011 .
1*
b1011011 ,
1%
#4650
0%
#4675
b1011100 )
b1011100 /
b1011100 (
b1011100 .
1*
b1011100 ,
1%
#4700
0%
#4725
b1011101 )
b1011101 /
b1011101 (
b1011101 .
1*
b1011101 ,
1%
#4750
0%
#4775
b1011110 )
b1011110 /
b1011110 (
b1011110 .
1*
b1011110 ,
1%
#4800
0%
#4825
b1011111 )
b1011111 /
b1011111 (
b1011111 .
1*
b1011111 ,
1%
#4850
0%
#4875
b1100000 )
b1100000 /
b1100000 (
b1100000 .
1*
b1100000 ,
1%
#4900
0%
#4925
b1100001 )
b1100001 /
b1100001 (
b1100001 .
1*
b1100001 ,
1%
#4950
0%
#4975
b1100010 )
b1100010 /
b1100010 (
b1100010 .
1*
b1100010 ,
1%
#5000
0%
#5025
b1100011 )
b1100011 /
b1100011 (
b1100011 .
1*
b1100011 ,
1%
#5050
0%
#5075
b1100100 )
b1100100 /
b1100100 (
b1100100 .
1*
b1100100 ,
1%
#5100
0%
#5125
b1100101 )
b1100101 /
b1100101 (
b1100101 .
1*
b1100101 ,
1%
#5150
0%
#5175
b1100110 )
b1100110 /
b1100110 (
b1100110 .
1*
b1100110 ,
1%
#5200
0%
#5225
b1100111 )
b1100111 /
b1100111 (
b1100111 .
1*
b1100111 ,
1%
#5250
0%
#5275
b1101000 )
b1101000 /
b1101000 (
b1101000 .
1*
b1101000 ,
1%
#5300
0%
#5325
b1101001 )
b1101001 /
b1101001 (
b1101001 .
1*
b1101001 ,
1%
#5350
0%
#5375
b1101010 )
b1101010 /
b1101010 (
b1101010 .
1*
b1101010 ,
1%
#5400
0%
#5425
b1101011 )
b1101011 /
b1101011 (
b1101011 .
1*
b1101011 ,
1%
#5450
0%
#5475
b1101100 )
b1101100 /
b1101100 (
b1101100 .
1*
b1101100 ,
1%
#5500
0%
#5525
b1101101 )
b1101101 /
b1101101 (
b1101101 .
1*
b1101101 ,
1%
#5550
0%
#5575
b1101110 )
b1101110 /
b1101110 (
b1101110 .
1*
b1101110 ,
1%
#5600
0%
#5625
b1101111 )
b1101111 /
b1101111 (
b1101111 .
1*
b1101111 ,
1%
#5650
0%
#5675
b1110000 )
b1110000 /
b1110000 (
b1110000 .
1*
b1110000 ,
1%
#5700
0%
#5725
b1110001 )
b1110001 /
b1110001 (
b1110001 .
1*
b1110001 ,
1%
#5750
0%
#5775
b1110010 )
b1110010 /
b1110010 (
b1110010 .
1*
b1110010 ,
1%
#5800
0%
#5825
b1110011 )
b1110011 /
b1110011 (
b1110011 .
1*
b1110011 ,
1%
#5850
0%
#5875
b1110100 )
b1110100 /
b1110100 (
b1110100 .
1*
b1110100 ,
1%
#5900
0%
#5925
b1110101 )
b1110101 /
b1110101 (
b1110101 .
1*
b1110101 ,
1%
#5950
0%
#5975
b1110110 )
b1110110 /
b1110110 (
b1110110 .
1*
b1110110 ,
1%
#6000
0%
#6025
b1110111 )
b1110111 /
b1110111 (
b1110111 .
1*
b1110111 ,
1%
#6050
0%
#6075
b1111000 )
b1111000 /
b1111000 (
b1111000 .
1*
b1111000 ,
1%
#6100
0%
#6125
b1111001 )
b1111001 /
b1111001 (
b1111001 .
1*
b1111001 ,
1%
#6150
0%
#6175
b1111010 )
b1111010 /
b1111010 (
b1111010 .
1*
b1111010 ,
1%
#6200
0%
#6225
b1111011 )
b1111011 /
b1111011 (
b1111011 .
1*
b1111011 ,
1%
#6250
0%
#6275
b1111100 )
b1111100 /
b1111100 (
b1111100 .
1*
b1111100 ,
1%
#6300
0%
#6325
b1111101 )
b1111101 /
b1111101 (
b1111101 .
1*
b1111101 ,
1%
#6350
0%
#6375
b1111110 )
b1111110 /
b1111110 (
b1111110 .
1*
b1111110 ,
1%
#6400
0%
#6425
b1111111 )
b1111111 /
b1111111 (
b1111111 .
1*
b1111111 ,
1%
#6450
0%
#6475
0*
b10000000 ,
1%
#6500
0%
#6525
1%
#6550
0%
#6575
1%
#6585
b1 &
b1 -
b1 ,
#6600
0%
#6625
1%
#6635
b10 &
b10 -
b1 !
b1 3
b10 ,
#6650
0%
#6675
1%
#6685
b11 &
b11 -
b10 !
b10 3
b11 ,
#6700
0%
#6725
1%
#6735
b100 &
b100 -
b11 !
b11 3
b100 ,
#6750
0%
#6775
1%
#6785
b101 &
b101 -
b100 !
b100 3
b101 ,
#6800
0%
#6825
1%
#6835
b110 &
b110 -
b101 !
b101 3
b110 ,
#6850
0%
#6875
1%
#6885
b111 &
b111 -
b110 !
b110 3
b111 ,
#6900
0%
#6925
1%
#6935
b1000 &
b1000 -
b111 !
b111 3
b1000 ,
#6950
0%
#6975
1%
#6985
b1001 &
b1001 -
b1000 !
b1000 3
b1001 ,
#7000
0%
#7025
1%
#7035
b1010 &
b1010 -
b1001 !
b1001 3
b1010 ,
#7050
0%
#7075
1%
#7085
b1011 &
b1011 -
b1010 !
b1010 3
b1011 ,
#7100
0%
#7125
1%
#7135
b1100 &
b1100 -
b1011 !
b1011 3
b1100 ,
#7150
0%
#7175
1%
#7185
b1101 &
b1101 -
b1100 !
b1100 3
b1101 ,
#7200
0%
#7225
1%
#7235
b1110 &
b1110 -
b1101 !
b1101 3
b1110 ,
#7250
0%
#7275
1%
#7285
b1111 &
b1111 -
b1110 !
b1110 3
b1111 ,
#7300
0%
#7325
1%
#7335
b10000 &
b10000 -
b1111 !
b1111 3
b10000 ,
#7350
0%
#7375
1%
#7385
b10001 &
b10001 -
b10000 !
b10000 3
b10001 ,
#7400
0%
#7425
1%
#7435
b10010 &
b10010 -
b10001 !
b10001 3
b10010 ,
#7450
0%
#7475
1%
#7485
b10011 &
b10011 -
b10010 !
b10010 3
b10011 ,
#7500
0%
#7525
1%
#7535
b10100 &
b10100 -
b10011 !
b10011 3
b10100 ,
#7550
0%
#7575
1%
#7585
b10101 &
b10101 -
b10100 !
b10100 3
b10101 ,
#7600
0%
#7625
1%
#7635
b10110 &
b10110 -
b10101 !
b10101 3
b10110 ,
#7650
0%
#7675
1%
#7685
b10111 &
b10111 -
b10110 !
b10110 3
b10111 ,
#7700
0%
#7725
1%
#7735
b11000 &
b11000 -
b10111 !
b10111 3
b11000 ,
#7750
0%
#7775
1%
#7785
b11001 &
b11001 -
b11000 !
b11000 3
b11001 ,
#7800
0%
#7825
1%
#7835
b11010 &
b11010 -
b11001 !
b11001 3
b11010 ,
#7850
0%
#7875
1%
#7885
b11011 &
b11011 -
b11010 !
b11010 3
b11011 ,
#7900
0%
#7925
1%
#7935
b11100 &
b11100 -
b11011 !
b11011 3
b11100 ,
#7950
0%
#7975
1%
#7985
b11101 &
b11101 -
b11100 !
b11100 3
b11101 ,
#8000
0%
#8025
1%
#8035
b11110 &
b11110 -
b11101 !
b11101 3
b11110 ,
#8050
0%
#8075
1%
#8085
b11111 &
b11111 -
b11110 !
b11110 3
b11111 ,
#8100
0%
#8125
1%
#8135
b100000 &
b100000 -
b11111 !
b11111 3
b100000 ,
#8150
0%
#8175
1%
#8185
b100001 &
b100001 -
b100000 !
b100000 3
b100001 ,
#8200
0%
#8225
1%
#8235
b100010 &
b100010 -
b100001 !
b100001 3
b100010 ,
#8250
0%
#8275
1%
#8285
b100011 &
b100011 -
b100010 !
b100010 3
b100011 ,
#8300
0%
#8325
1%
#8335
b100100 &
b100100 -
b100011 !
b100011 3
b100100 ,
#8350
0%
#8375
1%
#8385
b100101 &
b100101 -
b100100 !
b100100 3
b100101 ,
#8400
0%
#8425
1%
#8435
b100110 &
b100110 -
b100101 !
b100101 3
b100110 ,
#8450
0%
#8475
1%
#8485
b100111 &
b100111 -
b100110 !
b100110 3
b100111 ,
#8500
0%
#8525
1%
#8535
b101000 &
b101000 -
b100111 !
b100111 3
b101000 ,
#8550
0%
#8575
1%
#8585
b101001 &
b101001 -
b101000 !
b101000 3
b101001 ,
#8600
0%
#8625
1%
#8635
b101010 &
b101010 -
b101001 !
b101001 3
b101010 ,
#8650
0%
#8675
1%
#8685
b101011 &
b101011 -
b101010 !
b101010 3
b101011 ,
#8700
0%
#8725
1%
#8735
b101100 &
b101100 -
b101011 !
b101011 3
b101100 ,
#8750
0%
#8775
1%
#8785
b101101 &
b101101 -
b101100 !
b101100 3
b101101 ,
#8800
0%
#8825
1%
#8835
b101110 &
b101110 -
b101101 !
b101101 3
b101110 ,
#8850
0%
#8875
1%
#8885
b101111 &
b101111 -
b101110 !
b101110 3
b101111 ,
#8900
0%
#8925
1%
#8935
b110000 &
b110000 -
b101111 !
b101111 3
b110000 ,
#8950
0%
#8975
1%
#8985
b110001 &
b110001 -
b110000 !
b110000 3
b110001 ,
#9000
0%
#9025
1%
#9035
b110010 &
b110010 -
b110001 !
b110001 3
b110010 ,
#9050
0%
#9075
1%
#9085
b110011 &
b110011 -
b110010 !
b110010 3
b110011 ,
#9100
0%
#9125
1%
#9135
b110100 &
b110100 -
b110011 !
b110011 3
b110100 ,
#9150
0%
#9175
1%
#9185
b110101 &
b110101 -
b110100 !
b110100 3
b110101 ,
#9200
0%
#9225
1%
#9235
b110110 &
b110110 -
b110101 !
b110101 3
b110110 ,
#9250
0%
#9275
1%
#9285
b110111 &
b110111 -
b110110 !
b110110 3
b110111 ,
#9300
0%
#9325
1%
#9335
b111000 &
b111000 -
b110111 !
b110111 3
b111000 ,
#9350
0%
#9375
1%
#9385
b111001 &
b111001 -
b111000 !
b111000 3
b111001 ,
#9400
0%
#9425
1%
#9435
b111010 &
b111010 -
b111001 !
b111001 3
b111010 ,
#9450
0%
#9475
1%
#9485
b111011 &
b111011 -
b111010 !
b111010 3
b111011 ,
#9500
0%
#9525
1%
