ANIDS/anids_defines.vh
// ANIDS Defines
// Clock Period, this is 5ns period (200MHz clock)
`define CLK_PERIOD				16'd5


// APB can work with 8, 16, 32 bit data width
`define APB_DATA_WIDTH			8
`define APB_ADDR_WIDTH			16 							// 15 bits needed, but we use 16.


// DMA Data Width is input vector size, which is 128 bits
`define DMA_DATA_WIDTH			128

// Memory Fetch Unit widths
`define MFU_DATA_WIDTH			`DMA_DATA_WIDTH
`define MFU_FEATURE_WIDTH		`MFU_DATA_WIDTH				// stored feature vector width

// Pipeline Manager widths and history depth
`define PIPELINE_VECTOR_WIDTH	`MFU_FEATURE_WIDTH			// vector width propagated through pipeline manager
`define PIPELINE_COUNTER_WIDTH	7							// counter width for indices 0..127
`define PIPELINE_HISTORY_DEPTH	2							// number of coarse vector buffers before validation
`define PIPELINE_STAGE_CYCLES	64							// 128-bit vector processed over 64 cycles
`define PIPELINE_STAGE_COUNT_W	6							// counter width for 0..63 stage timing

// Input layer widths
`define INPUT_LAYER_FEATURE_WIDTH	`PIPELINE_VECTOR_WIDTH	// full feature vector width seen by input layer
`define INPUT_LAYER_PAIR_WIDTH		2						// number of feature bits processed per counter step

// Hidden layer unit widths
`define HL_FEATURE_PAIR_WIDTH		`INPUT_LAYER_PAIR_WIDTH	// number of feature bits consumed per cycle
`define HL_WEIGHT_WIDTH				8						// signed Q0.7 weight width
`define HL_BIAS_WIDTH				8						// signed Q0.7 bias width
`define HL_RESULT_WIDTH				8						// signed Q0.7 hidden neuron output width
`define HL_PAIR_SUM_WIDTH			9						// sum of two weighted feature contributions
`define HL_ACC_WIDTH				15						// accumulation register width before truncation

// Output layer unit widths
`define OL_INPUT_WIDTH				8						// signed Q0.7 hidden-layer input width
`define OL_WEIGHT_WIDTH				8						// signed Q0.7 output-layer weight width
`define OL_BIAS_WIDTH				8						// signed Q0.7 output-layer bias width
`define OL_RESULT_WIDTH				8						// signed Q0.7 output-layer result width
`define OL_PRODUCT_WIDTH			16						// full signed 8x8 multiply width
`define OL_TRUNC_PRODUCT_WIDTH		8						// product truncated back to Q0.7
`define OL_ACC_WIDTH				15						// accumulation width before final truncation

// Loss function widths
`define LF_FEATURE_PAIR_WIDTH		`INPUT_LAYER_PAIR_WIDTH	// number of original feature bits consumed per cycle
`define LF_RESULT_IN_WIDTH			8						// compared result width
`define LF_ABS_WIDTH				8						// absolute delta width
`define LF_PAIR_SUM_WIDTH			9						// sum of two absolute deltas
`define LF_ACC_WIDTH				15						// accumulation register width before truncation

// Sigmoid LUT address mapper widths
`define MMAP_IN_WIDTH				8						// signed Q0.7 value width before LUT lookup
`define MMAP_ADDR_WIDTH				`LUT_ADDR_WIDTH		// LUT address width after mapping

// LUT Address and Data Sizes
`define LUT_ADDR_WIDTH			8
`define LUT_DATA_WIDTH			8

`define RELU_WIDTH 				8
`define LF_OUT_WIDTH			8



// Weight & Bias Counts
`define HL_WEIGHT_COUNT   		64 * 128   	// 8192
`define HL_BIAS_COUNT      		64       	// 64
`define OL_WEIGHT_COUNT    		128 * 64   	// 8192
`define OL_BIAS_COUNT      		128      	// 128


// ANIDS Control Register Addresses
`define START_REG				0
`define N_REG					1
`define THRESHOLD_REG			2
`define RESULT_REG				3


// Indirect LUT Read/Write Registers
`define LUT_ADDR				4
`define LUT_DATA				5
`define LUT_CTRL				6
`define FREE_REG				7


// Hidden Layer Register Mapping
`define HL_WEIGHT_BASE			8 // we have 128 * 64 of these
`define HL_BIAS_BASE			`HL_WEIGHT_BASE + `HL_WEIGHT_COUNT // and 64 of these


// Output Layer Register Mapping
`define OL_WEIGHT_BASE			`HL_BIAS_BASE + `HL_BIAS_COUNT
`define OL_BIAS_BASE			`OL_WEIGHT_BASE + `OL_WEIGHT_COUNT


// ANIDS memory map borders
`define ANIDS_MAP_START   		`HL_WEIGHT_BASE
`define ANIDS_MAP_END     		`OL_BIAS_BASE + `OL_BIAS_COUNT
`define REG_COUNT				`ANIDS_MAP_END 	// (correct count due to 0-based indexing)


// Pipeline Stage Cycles
`define INPUT_LAYER_CYCLES 		1
`define HIDDEN_LAYER_CYCLES 	64
`define OUTPUT_LAYER_CYCLES 	64
`define LOOKUP_LAYER_CYCLES 	64
`define LOSS_FUNCTION_CYCLES 	64
`define OUTLIER_CYCLES 			1
`define RESULT_CYCLES 			1


// Pipeline Fill and Latency in cycles (pipefill = 259, latency = 130)
`define PIPE_FILL_CYCLES 		(`INPUT_LAYER_CYCLES + `HIDDEN_LAYER_CYCLES + `OUTPUT_LAYER_CYCLES + `LOOKUP_LAYER_CYCLES + `LOSS_FUNCTION_CYCLES + `OUTLIER_CYCLES + `RESULT_CYCLES)
`define LATENCY_IN_CYCLES 		(`LOOKUP_LAYER_CYCLES + `LOSS_FUNCTION_CYCLES + `OUTLIER_CYCLES + `RESULT_CYCLES )

ANIDS/src/mem_fetch_unit.sv
// ANIDS Memory Fetch Unit
`include "anids_defines.vh"

module mem_fetch_unit (
		clk,
		resetN,
		fetch,
		valid,
		mem_data,
		ready,
		features_out,
		updated
	);

	parameter DATA_WIDTH    = `MFU_DATA_WIDTH;
	parameter FEATURE_WIDTH = `MFU_FEATURE_WIDTH;

	// ----------------------------------------------------------------------
	//                  		I/O Ports
	// ----------------------------------------------------------------------
	input  wire							clk;
	input  wire							resetN;
	input  wire							fetch;
	input  wire							valid;
	input  wire [DATA_WIDTH-1:0] 		mem_data;
	output reg 							ready;
	output reg  [FEATURE_WIDTH-1:0] 	features_out;
	output reg 							updated;

	// ----------------------------------------------------------------------
	//                  		State Machine
	// ----------------------------------------------------------------------
	localparam STATE_IDLE    = 1'b0;
	localparam STATE_PENDING = 1'b1;

	reg state;

	always @(posedge clk or negedge resetN) begin
		if (!resetN) begin
			state        <= #1 STATE_IDLE;
			ready        <= #1 1'b0;
			features_out <= #1 {FEATURE_WIDTH{1'b0}};
			updated      <= #1 1'b0;
		end
		else begin
			case (state)
				STATE_IDLE: begin
					ready   <= #1 1'b0;
					updated <= #1 1'b0;

					if (fetch) begin
						state <= #1 STATE_PENDING;
						ready <= #1 1'b1;
					end
				end

				STATE_PENDING: begin
					ready   <= #1 1'b1;
					updated <= #1 1'b0;

					if (valid) begin
						features_out <= #1 mem_data[FEATURE_WIDTH-1:0];
						state        <= #1 STATE_IDLE;
						ready        <= #1 1'b0;
						updated      <= #1 1'b1;
					end
				end

				// *** remove later? this is redundant for safety
				default: begin
					state   <= #1 STATE_IDLE;
					ready   <= #1 1'b0;
					updated <= #1 1'b0;
				end
			endcase
		end
	end

endmodule

ANIDS/tb/mem_fetch_unit_tb.v
// ANIDS - Memory Fetch Unit Testbench
`timescale 1ns/100ps
`include "anids_defines.vh"

module mem_fetch_unit_tb;

	localparam DATA_WIDTH    = `MFU_DATA_WIDTH;
	localparam FEATURE_WIDTH = `MFU_FEATURE_WIDTH;

	reg                     clk;
	reg                     resetN;
	reg                     fetch;
	reg                     valid;
	reg  [DATA_WIDTH-1:0]   mem_data;
	wire                    ready;
	wire                    updated;
	wire [FEATURE_WIDTH-1:0] features_out;

	always #2.5 clk = ~clk;

	mem_fetch_unit #(
		.DATA_WIDTH(DATA_WIDTH),
		.FEATURE_WIDTH(FEATURE_WIDTH)
	) dut (
		.clk          (clk),
		.resetN       (resetN),
		.fetch        (fetch),
		.valid        (valid),
		.mem_data     (mem_data),
		.ready        (ready),
		.features_out (features_out),
		.updated      (updated)
	);

	initial begin
		$dumpfile("mem_fetch_unit_tb.vcd");
		$dumpvars(0, mem_fetch_unit_tb);

		clk      = 1'b0;
		resetN   = 1'b0;
		fetch    = 1'b0;
		valid    = 1'b0;
		mem_data = {DATA_WIDTH{1'b0}};

		check_cycle(1'b0, 1'b0, 1'b0, 128'h00000000000000000000000000000000,
			1'b0, 1'b0, 128'h00000000000000000000000000000000, "reset clears state");

		check_cycle(1'b1, 1'b0, 1'b0, 128'h11112222333344445555666677778888,
			1'b0, 1'b0, 128'h00000000000000000000000000000000, "idle ignores valid without fetch");

		check_cycle(1'b1, 1'b1, 1'b0, 128'h11112222333344445555666677778888,
			1'b1, 1'b0, 128'h00000000000000000000000000000000, "fetch moves unit to pending");

		check_cycle(1'b1, 1'b0, 1'b0, 128'h9999AAAABBBBCCCCDDDDEEEEFFFF0000,
			1'b1, 1'b0, 128'h00000000000000000000000000000000, "pending waits for valid and holds features");

		check_cycle(1'b1, 1'b0, 1'b1, 128'h0123456789ABCDEFFEDCBA9876543210,
			1'b0, 1'b1, 128'h0123456789ABCDEFFEDCBA9876543210, "valid latches feature vector and returns idle");

		check_cycle(1'b1, 1'b0, 1'b1, 128'hAAAAAAAAAAAAAAAAAAAAAAAAAAAAAAAA,
			1'b0, 1'b0, 128'h0123456789ABCDEFFEDCBA9876543210, "idle holds previous features without fetch");

		check_cycle(1'b1, 1'b1, 1'b0, 128'h13579BDF2468ACE013579BDF2468ACE0,
			1'b1, 1'b0, 128'h0123456789ABCDEFFEDCBA9876543210, "second fetch starts new pending transaction");

		check_cycle(1'b1, 1'b0, 1'b1, 128'h13579BDF2468ACE013579BDF2468ACE0,
			1'b0, 1'b1, 128'h13579BDF2468ACE013579BDF2468ACE0, "next valid updates features on next fetch");

		$display("MEM_FETCH_UNIT TB PASSED");
		$finish;
	end

	task check_cycle(
		input                      test_resetN,
		input                      test_fetch,
		input                      test_valid,
		input [DATA_WIDTH-1:0]     test_mem_data,
		input                      expected_ready,
		input                      expected_updated,
		input [FEATURE_WIDTH-1:0]  expected_features,
		input [255:0]              test_name
	);
	begin
		resetN   <= test_resetN;
		fetch    <= test_fetch;
		valid    <= test_valid;
		mem_data <= test_mem_data;

		@(posedge clk);
		#2;

		if (ready !== expected_ready || updated !== expected_updated || features_out !== expected_features) begin
			$error("FAIL: %0s | resetN=%0b fetch=%0b valid=%0b ready=%0b expected_ready=%0b updated=%0b expected_updated=%0b features=%032h expected_features=%032h",
				test_name, test_resetN, test_fetch, test_valid,
				ready, expected_ready, updated, expected_updated, features_out, expected_features);
			$finish;
		end
		else begin
			$display("PASS: %0s", test_name);
		end
	end
	endtask

endmodule

outputs/mem_fetch_unit_tb.vcd
$date
	Sat Mar 07 14:24:14 2026
$end
$version
	Icarus Verilog
$end
$timescale
	100ps
$end
$scope module mem_fetch_unit_tb $end
$var wire 1 ! updated $end
$var wire 1 " ready $end
$var wire 128 # features_out [127:0] $end
$var parameter 32 $ DATA_WIDTH $end
$var parameter 32 % FEATURE_WIDTH $end
$var reg 1 & clk $end
$var reg 1 ' fetch $end
$var reg 128 ( mem_data [127:0] $end
$var reg 1 ) resetN $end
$var reg 1 * valid $end
$scope module dut $end
$var wire 1 & clk $end
$var wire 1 ' fetch $end
$var wire 128 + mem_data [127:0] $end
$var wire 1 ) resetN $end
$var wire 1 * valid $end
$var parameter 32 , DATA_WIDTH $end
$var parameter 32 - FEATURE_WIDTH $end
$var parameter 1 . STATE_IDLE $end
$var parameter 1 / STATE_PENDING $end
$var reg 128 0 features_out [127:0] $end
$var reg 1 " ready $end
$var reg 1 1 state $end
$var reg 1 ! updated $end
$upscope $end
$scope task check_cycle $end
$var reg 128 2 expected_features [127:0] $end
$var reg 1 3 expected_ready $end
$var reg 1 4 expected_updated $end
$var reg 1 5 test_fetch $end
$var reg 128 6 test_mem_data [127:0] $end
$var reg 256 7 test_name [255:0] $end
$var reg 1 8 test_resetN $end
$var reg 1 9 test_valid $end
$upscope $end
$upscope $end
$enddefinitions $end
$comment Show the parameter values. $end
$dumpall
1/
0.
b10000000 -
b10000000 ,
b10000000 %
b10000000 $
$end
#0
$dumpvars
09
08
b11100100110010101110011011001010111010000100000011000110110110001100101011000010111001001110011001000000111001101110100011000010111010001100101 7
b0 6
05
04
03
b0 2
x1
bx 0
b0 +
0*
0)
b0 (
0'
0&
bx #
x"
x!
$end
#10
0!
b0 #
b0 0
0"
01
#25
1&
#45
b10001000100010010001000100010001100110011001101000100010001000101010101010101011001100110011001110111011101111000100010001000 (
b10001000100010010001000100010001100110011001101000100010001000101010101010101011001100110011001110111011101111000100010001000 +
1)
b110100101100100011011000110010100100000011010010110011101101110011011110111001001100101011100110010000001110110011000010110110001101001011001000010000001110111011010010111010001101000011011110111010101110100001000000110011001100101011101000110001101101000 7
b10001000100010010001000100010001100110011001101000100010001000101010101010101011001100110011001110111011101111000100010001000 6
18
#50
0&
#75
1&
#95
1'
b11001100110010101110100011000110110100000100000011011010110111101110110011001010111001100100000011101010110111001101001011101000010000001110100011011110010000001110000011001010110111001100100011010010110111001100111 7
13
15
#100
0&
#125
1&
#135
1"
11
#145
b10011001100110011010101010101010101110111011101111001100110011001101110111011101111011101110111011111111111111110000000000000000 (
b10011001100110011010101010101010101110111011101111001100110011001101110111011101111011101110111011111111111111110000000000000000 +
0'
b110100101110100011100110010000001100110011011110111001000100000011101100110000101101100011010010110010000100000011000010110111001100100001000000110100001101111011011000110010001110011001000000110011001100101011000010111010001110101011100100110010101110011 7
b10011001100110011010101010101010101110111011101111001100110011001101110111011101111011101110111011111111111111110000000000000000 6
05
#150
0&
#175
1&
#195
b1001000110100010101100111100010011010101111001101111011111111111011011100101110101001100001110110010101000011001000010000 (
b1001000110100010101100111100010011010101111001101111011111111111011011100101110101001100001110110010101000011001000010000 +
1*
b10000001100110011001010110000101110100011101010111001001100101001000000111011001100101011000110111010001101111011100100010000001100001011011100110010000100000011100100110010101110100011101010111001001101110011100110010000001101001011001000110110001100101 7
b1001000110100010101100111100010011010101111001101111011111111111011011100101110101001100001110110010101000011001000010000 2
14
03
b1001000110100010101100111100010011010101111001101111011111111111011011100101110101001100001110110010101000011001000010000 6
19
#200
0&
#225
1&
#235
1!
0"
01
b1001000110100010101100111100010011010101111001101111011111111111011011100101110101001100001110110010101000011001000010000 #
b1001000110100010101100111100010011010101111001101111011111111111011011100101110101001100001110110010101000011001000010000 0
#245
b10101010101010101010101010101010101010101010101010101010101010101010101010101010101010101010101010101010101010101010101010101010 (
b10101010101010101010101010101010101010101010101010101010101010101010101010101010101010101010101010101010101010101010101010101010 +
b10000001110000011100100110010101110110011010010110111101110101011100110010000001100110011001010110000101110100011101010111001001100101011100110010000001110111011010010111010001101000011011110111010101110100001000000110011001100101011101000110001101101000 7
04
b10101010101010101010101010101010101010101010101010101010101010101010101010101010101010101010101010101010101010101010101010101010 6
#250
0&
#275
1&
#285
0!
#295
b10011010101111001101111011111001001000110100010101100111000000001001101010111100110111101111100100100011010001010110011100000 (
b10011010101111001101111011111001001000110100010101100111000000001001101010111100110111101111100100100011010001010110011100000 +
0*
1'
b110100000100000011100110111010001100001011100100111010001110011001000000110111001100101011101110010000001110000011001010110111001100100011010010110111001100111001000000111010001110010011000010110111001110011011000010110001101110100011010010110111101101110 7
13
b10011010101111001101111011111001001000110100010101100111000000001001101010111100110111101111100100100011010001010110011100000 6
09
15
#300
0&
#325
1&
#335
1"
11
#345
1*
0'
b110010000100000011101010111000001100100011000010111010001100101011100110010000001100110011001010110000101110100011101010111001001100101011100110010000001101111011011100010000001101110011001010111100001110100001000000110011001100101011101000110001101101000 7
b10011010101111001101111011111001001000110100010101100111000000001001101010111100110111101111100100100011010001010110011100000 2
14
03
19
05
#350
0&
#375
1&
#385
1!
0"
01
b10011010101111001101111011111001001000110100010101100111000000001001101010111100110111101111100100100011010001010110011100000 #
b10011010101111001101111011111001001000110100010101100111000000001001101010111100110111101111100100100011010001010110011100000 0
