ANIDS/anids_defines.vh
// ANIDS Defines
// Clock Period, this is 5ns period (200MHz clock)
`define CLK_PERIOD				16'd5


// APB can work with 8, 16, 32 bit data width
`define APB_DATA_WIDTH			8
`define APB_ADDR_WIDTH			16 							// 15 bits needed, but we use 16.


// DMA Data Width is input vector size, which is 128 bits
`define DMA_DATA_WIDTH			128

// Memory Fetch Unit widths
`define MFU_DATA_WIDTH			`DMA_DATA_WIDTH
`define MFU_FEATURE_WIDTH		`MFU_DATA_WIDTH				// stored feature vector width

// Pipeline Manager widths and history depth
`define PIPELINE_VECTOR_WIDTH	`MFU_FEATURE_WIDTH			// vector width propagated through pipeline manager
`define PIPELINE_COUNTER_WIDTH	7							// counter width for indices 0..127
`define PIPELINE_HISTORY_DEPTH	2							// number of coarse vector buffers before validation
`define PIPELINE_STAGE_CYCLES	64							// 128-bit vector processed over 64 cycles
`define PIPELINE_STAGE_COUNT_W	6							// counter width for 0..63 stage timing

// Input layer widths
`define INPUT_LAYER_FEATURE_WIDTH	`PIPELINE_VECTOR_WIDTH	// full feature vector width seen by input layer
`define INPUT_LAYER_PAIR_WIDTH		2						// number of feature bits processed per counter step

// Hidden layer unit widths
`define HL_FEATURE_PAIR_WIDTH		`INPUT_LAYER_PAIR_WIDTH	// number of feature bits consumed per cycle
`define HL_WEIGHT_WIDTH				8						// signed Q0.7 weight width
`define HL_BIAS_WIDTH				8						// signed Q0.7 bias width
`define HL_RESULT_WIDTH				8						// signed Q0.7 hidden neuron output width
`define HL_PAIR_SUM_WIDTH			9						// sum of two weighted feature contributions
`define HL_ACC_WIDTH				15						// accumulation register width before truncation

// Output layer unit widths
`define OL_INPUT_WIDTH				8						// signed Q0.7 hidden-layer input width
`define OL_WEIGHT_WIDTH				8						// signed Q0.7 output-layer weight width
`define OL_BIAS_WIDTH				8						// signed Q0.7 output-layer bias width
`define OL_RESULT_WIDTH				8						// signed Q0.7 output-layer result width
`define OL_PRODUCT_WIDTH			16						// full signed 8x8 multiply width
`define OL_TRUNC_PRODUCT_WIDTH		8						// product truncated back to Q0.7
`define OL_ACC_WIDTH				15						// accumulation width before final truncation

// Loss function widths
`define LF_FEATURE_PAIR_WIDTH		`INPUT_LAYER_PAIR_WIDTH	// number of original feature bits consumed per cycle
`define LF_RESULT_IN_WIDTH			8						// compared result width
`define LF_ABS_WIDTH				8						// absolute delta width
`define LF_PAIR_SUM_WIDTH			9						// sum of two absolute deltas
`define LF_ACC_WIDTH				15						// accumulation register width before truncation

// Sigmoid LUT address mapper widths
`define MMAP_IN_WIDTH				8						// signed Q0.7 value width before LUT lookup
`define MMAP_ADDR_WIDTH				`LUT_ADDR_WIDTH		// LUT address width after mapping

// LUT Address and Data Sizes
`define LUT_ADDR_WIDTH			8
`define LUT_DATA_WIDTH			8

`define RELU_WIDTH 				8
`define LF_OUT_WIDTH			8



// Weight & Bias Counts
`define HL_WEIGHT_COUNT   		64 * 128   	// 8192
`define HL_BIAS_COUNT      		64       	// 64
`define OL_WEIGHT_COUNT    		128 * 64   	// 8192
`define OL_BIAS_COUNT      		128      	// 128


// ANIDS Control Register Addresses
`define START_REG				0
`define N_REG					1
`define THRESHOLD_REG			2
`define RESULT_REG				3


// Indirect LUT Read/Write Registers
`define LUT_ADDR				4
`define LUT_DATA				5
`define LUT_CTRL				6
`define FREE_REG				7


// Hidden Layer Register Mapping
`define HL_WEIGHT_BASE			8 // we have 128 * 64 of these
`define HL_BIAS_BASE			`HL_WEIGHT_BASE + `HL_WEIGHT_COUNT // and 64 of these


// Output Layer Register Mapping
`define OL_WEIGHT_BASE			`HL_BIAS_BASE + `HL_BIAS_COUNT
`define OL_BIAS_BASE			`OL_WEIGHT_BASE + `OL_WEIGHT_COUNT


// ANIDS memory map borders
`define ANIDS_MAP_START   		`HL_WEIGHT_BASE
`define ANIDS_MAP_END     		`OL_BIAS_BASE + `OL_BIAS_COUNT
`define REG_COUNT				`ANIDS_MAP_END 	// (correct count due to 0-based indexing)


// Pipeline Stage Cycles
`define INPUT_LAYER_CYCLES 		1
`define HIDDEN_LAYER_CYCLES 	64
`define OUTPUT_LAYER_CYCLES 	64
`define LOOKUP_LAYER_CYCLES 	64
`define LOSS_FUNCTION_CYCLES 	64
`define OUTLIER_CYCLES 			1
`define RESULT_CYCLES 			1


// Pipeline Fill and Latency in cycles (pipefill = 259, latency = 130)
`define PIPE_FILL_CYCLES 		(`INPUT_LAYER_CYCLES + `HIDDEN_LAYER_CYCLES + `OUTPUT_LAYER_CYCLES + `LOOKUP_LAYER_CYCLES + `LOSS_FUNCTION_CYCLES + `OUTLIER_CYCLES + `RESULT_CYCLES)
`define LATENCY_IN_CYCLES 		(`LOOKUP_LAYER_CYCLES + `LOSS_FUNCTION_CYCLES + `OUTLIER_CYCLES + `RESULT_CYCLES )

ANIDS/src/mem_fetch_unit.sv
// ANIDS Memory Fetch Unit
`include "anids_defines.vh"

module mem_fetch_unit (
		clk,
		resetN,
		fetch,
		valid,
		mem_data,
		ready,
		features_out,
		updated
	);

	parameter DATA_WIDTH    = `MFU_DATA_WIDTH;
	parameter FEATURE_WIDTH = `MFU_FEATURE_WIDTH;

	// ----------------------------------------------------------------------
	//                  		I/O Ports
	// ----------------------------------------------------------------------
	input  wire							clk;
	input  wire							resetN;
	input  wire							fetch;
	input  wire							valid;
	input  wire [DATA_WIDTH-1:0] 		mem_data;
	output reg 							ready;
	output reg  [FEATURE_WIDTH-1:0] 	features_out;
	output reg 							updated;

	// ----------------------------------------------------------------------
	//                  		State Machine
	// ----------------------------------------------------------------------
	localparam STATE_IDLE    = 1'b0;
	localparam STATE_PENDING = 1'b1;

	reg state;

	always @(posedge clk or negedge resetN) begin
		if (!resetN) begin
			state        <= #1 STATE_IDLE;
			ready        <= #1 1'b0;
			features_out <= #1 {FEATURE_WIDTH{1'b0}};
			updated      <= #1 1'b0;
		end
		else begin
			case (state)
				STATE_IDLE: begin
					ready   <= #1 1'b0;
					updated <= #1 1'b0;

					if (fetch) begin
						state <= #1 STATE_PENDING;
						ready <= #1 1'b1;
					end
				end

				STATE_PENDING: begin
					ready   <= #1 1'b1;
					updated <= #1 1'b0;

					if (valid) begin
						features_out <= #1 mem_data[FEATURE_WIDTH-1:0];
						state        <= #1 STATE_IDLE;
						ready        <= #1 1'b0;
						updated      <= #1 1'b1;
					end
				end

				// *** remove later? this is redundant for safety
				default: begin
					state   <= #1 STATE_IDLE;
					ready   <= #1 1'b0;
					updated <= #1 1'b0;
				end
			endcase
		end
	end

endmodule

ANIDS/src/pipeline_manager.v
// ANIDS Pipeline Manager
`include "anids_defines.vh"

module pipeline_manager (
		clk,
		resetN,
		start,
		N,
		mfu_features,
		mfu_updated,
		fetch,
		enable,
		next_vector,
		validate_vector,
		counter
	);


	parameter VECTOR_WIDTH   = `PIPELINE_VECTOR_WIDTH;
	parameter COUNTER_WIDTH  = `PIPELINE_COUNTER_WIDTH;


	// ----------------------------------------------------------------------
	//                  		I/O Ports
	// ----------------------------------------------------------------------

	// system signals
	input  wire                         clk;
	input  wire                         resetN;
	input  wire                         start;
	input  wire [COUNTER_WIDTH-1:0]     N;					// 128 vector size

	// data vector signals
	input  wire [VECTOR_WIDTH-1:0]      mfu_features;		// new data vector
	input  wire                         mfu_updated;		// signals new vector arrival
	output reg                          fetch;				// fetch new vector signal

	// outputs to engine
	output reg                          enable;				// inference engine enable signal
	output reg  [VECTOR_WIDTH-1:0]      next_vector; 		// goes to input layer
	output reg  [VECTOR_WIDTH-1:0]      validate_vector;	// goes to loss function
	output reg  [COUNTER_WIDTH-1:0]     counter;			// current feature index


	// ----------------------------------------------------------------------
	//                  		Buffer Registers
	// ----------------------------------------------------------------------
	reg [VECTOR_WIDTH-1:0] history_1;
	reg [VECTOR_WIDTH-1:0] history_2;


	// ----------------------------------------------------------------------
	//                  		Manager States
	// ----------------------------------------------------------------------
	reg [1:0] state;
	localparam STATE_IDLE        = 2'd0;
	localparam STATE_WAIT_VECTOR = 2'd1;
	localparam STATE_RUN         = 2'd2;


	// ----------------------------------------------------------------------
	//                  		Manager Logic
	// ----------------------------------------------------------------------
	always @(posedge clk or negedge resetN) begin
		if (!resetN) begin
			fetch           <= #1 1'b0;
			enable          <= #1 1'b0;
			next_vector     <= #1 {VECTOR_WIDTH{1'b0}};
			validate_vector <= #1 {VECTOR_WIDTH{1'b0}};
			history_1       <= #1 {VECTOR_WIDTH{1'b0}};
			history_2       <= #1 {VECTOR_WIDTH{1'b0}};
			counter         <= #1 {COUNTER_WIDTH{1'b0}};
			state           <= #1 STATE_IDLE;
		end
		else begin
			fetch <= #1 1'b0;

			case (state)
				STATE_IDLE: begin
					enable  <= #1 1'b0;
					counter <= #1 {COUNTER_WIDTH{1'b0}};

					// waiting for start signal.
					// (start needs to be held on 1 to run engine)
					if (start) begin
						fetch <= #1 1'b1;
						state <= #1 STATE_WAIT_VECTOR;
					end
				end

				STATE_WAIT_VECTOR: begin
					enable <= #1 1'b0;

					if (!start) begin
						// engine stop routine
						next_vector     <= #1 {VECTOR_WIDTH{1'b0}};
						validate_vector <= #1 {VECTOR_WIDTH{1'b0}};
						history_1       <= #1 {VECTOR_WIDTH{1'b0}};
						history_2       <= #1 {VECTOR_WIDTH{1'b0}};
						counter         <= #1 {COUNTER_WIDTH{1'b0}};
						state           <= #1 STATE_IDLE;
					end
					else if (mfu_updated) begin
						// coarse shift vector forward
						next_vector     <= #1 mfu_features; // goes to input layer
						history_1       <= #1 next_vector;	// buffer 1
						history_2       <= #1 history_1;	// buffer 2
						validate_vector <= #1 history_2;	// goes to loss function

						// prepare for running
						counter         <= #1 {COUNTER_WIDTH{1'b0}};
						enable          <= #1 1'b1;
						state           <= #1 STATE_RUN;
					end
				end

				STATE_RUN: begin
					if (!start) begin
						// engine stop routine
						enable          <= #1 1'b0;
						next_vector     <= #1 {VECTOR_WIDTH{1'b0}};
						validate_vector <= #1 {VECTOR_WIDTH{1'b0}};
						history_1       <= #1 {VECTOR_WIDTH{1'b0}};
						history_2       <= #1 {VECTOR_WIDTH{1'b0}};
						counter         <= #1 {COUNTER_WIDTH{1'b0}};
						state           <= #1 STATE_IDLE;
					end
					else begin
						enable <= #1 1'b1;
						// increment counter until we need to fetch new vector
						if (counter == N) begin
							counter <= #1 {COUNTER_WIDTH{1'b0}};
							fetch   <= #1 1'b1;
							enable  <= #1 1'b0;
							state   <= #1 STATE_WAIT_VECTOR;
						end
						else begin
							counter <= #1 counter + 1'b1;
						end
					end
				end

				//*** this is redundant, remove later
				default: begin
					// by default return to idle.
					fetch   <= #1 1'b0;
					enable  <= #1 1'b0;
					counter <= #1 {COUNTER_WIDTH{1'b0}};
					state   <= #1 STATE_IDLE;
				end
			endcase
		end
	end
endmodule

ANIDS/tb/pipeline_manager_tb.v
// ANIDS - Pipeline Manager Testbench
`timescale 1ns/100ps
`include "anids_defines.vh"

module pipeline_manager_tb;

	localparam VECTOR_WIDTH  = `PIPELINE_VECTOR_WIDTH;
	localparam COUNTER_WIDTH = `PIPELINE_COUNTER_WIDTH;

	reg                         clk;
	reg                         resetN;
	reg                         start;
	reg  [COUNTER_WIDTH-1:0]    N;
	reg                         valid;
	reg  [VECTOR_WIDTH-1:0]     mem_data;
	wire                        fetch;
	wire                        enable;
	wire                        mfu_ready;
	wire [VECTOR_WIDTH-1:0]     mfu_features;
	wire                        mfu_updated;
	wire [VECTOR_WIDTH-1:0]     next_vector;
	wire [VECTOR_WIDTH-1:0]     validate_vector;
	wire [COUNTER_WIDTH-1:0]    counter;

	pipeline_manager #(
		.VECTOR_WIDTH  (VECTOR_WIDTH),
		.COUNTER_WIDTH (COUNTER_WIDTH)
	) dut (
		.clk            (clk),
		.resetN         (resetN),
		.start          (start),
		.N              (N),
		.mfu_features   (mfu_features),
		.mfu_updated    (mfu_updated),
		.fetch          (fetch),
		.enable         (enable),
		.next_vector    (next_vector),
		.validate_vector(validate_vector),
		.counter        (counter)
	);

	mem_fetch_unit #(
		.DATA_WIDTH    (VECTOR_WIDTH),
		.FEATURE_WIDTH (VECTOR_WIDTH)
	) mfu (
		.clk          (clk),
		.resetN       (resetN),
		.fetch        (fetch),
		.valid        (valid),
		.mem_data     (mem_data),
		.ready        (mfu_ready),
		.features_out (mfu_features),
		.updated      (mfu_updated)
	);

	always #2.5 clk = ~clk;

	initial begin
		$dumpfile("pipeline_manager_tb.vcd");
		$dumpvars(0, pipeline_manager_tb);

		clk          = 1'b0;
		resetN       = 1'b0;
		start        = 1'b0;
		N            = 7'd3;
		valid        = 1'b0;
		mem_data     = {VECTOR_WIDTH{1'b0}};
		#2;

		check_outputs(1'b0, 1'b0, 7'd0,
			128'h00000000000000000000000000000000,
			128'h00000000000000000000000000000000,
			"reset clears outputs");

		resetN <= 1'b1;
		@(posedge clk);
		#2;
		check_outputs(1'b0, 1'b0, 7'd0,
			128'h00000000000000000000000000000000,
			128'h00000000000000000000000000000000,
			"idle before start");

		start <= 1'b1;
		@(posedge clk);
		#2;
		check_outputs(1'b1, 1'b0, 7'd0,
			128'h00000000000000000000000000000000,
			128'h00000000000000000000000000000000,
			"start requests first vector");

		send_vector(128'h11112222333344445555666677778888);
		@(posedge clk);
		#2;
		check_outputs(1'b0, 1'b1, 7'd0,
			128'h11112222333344445555666677778888,
			128'h00000000000000000000000000000000,
			"first vector loads and run starts");

		@(posedge clk);
		#2;
		check_outputs(1'b0, 1'b1, 7'd1,
			128'h11112222333344445555666677778888,
			128'h00000000000000000000000000000000,
			"counter increments while running");

		@(posedge clk);
		#2;
		check_outputs(1'b0, 1'b1, 7'd2,
			128'h11112222333344445555666677778888,
			128'h00000000000000000000000000000000,
			"counter continues to increment");

		@(posedge clk);
		#2;
		check_outputs(1'b0, 1'b1, 7'd3,
			128'h11112222333344445555666677778888,
			128'h00000000000000000000000000000000,
			"counter reaches N");

		@(posedge clk);
		#2;
		check_outputs(1'b1, 1'b0, 7'd0,
			128'h11112222333344445555666677778888,
			128'h00000000000000000000000000000000,
			"vector done requests next fetch and stalls");

		send_vector(128'h9999AAAABBBBCCCCDDDDEEEEFFFF0000);
		@(posedge clk);
		#2;
		check_outputs(1'b0, 1'b1, 7'd0,
			128'h9999AAAABBBBCCCCDDDDEEEEFFFF0000,
			128'h00000000000000000000000000000000,
			"second vector loads and restarts counter");

		run_until_fetch;
		check_outputs(1'b1, 1'b0, 7'd0,
			128'h9999AAAABBBBCCCCDDDDEEEEFFFF0000,
			128'h00000000000000000000000000000000,
			"second vector completes and requests third vector");

		send_vector(128'h0123456789ABCDEFFEDCBA9876543210);
		@(posedge clk);
		#2;
		check_outputs(1'b0, 1'b1, 7'd0,
			128'h0123456789ABCDEFFEDCBA9876543210,
			128'h00000000000000000000000000000000,
			"third vector loads while validate buffer is still empty");

		run_until_fetch;
		check_outputs(1'b1, 1'b0, 7'd0,
			128'h0123456789ABCDEFFEDCBA9876543210,
			128'h00000000000000000000000000000000,
			"third vector completes and requests fourth vector");

		send_vector(128'h13579BDF2468ACE013579BDF2468ACE0);
		@(posedge clk);
		#2;
		check_outputs(1'b0, 1'b1, 7'd0,
			128'h13579BDF2468ACE013579BDF2468ACE0,
			128'h11112222333344445555666677778888,
			"fourth vector load updates validate vector from first input");

		start <= 1'b0;
		@(posedge clk);
		#2;
		check_outputs(1'b0, 1'b0, 7'd0,
			128'h00000000000000000000000000000000,
			128'h00000000000000000000000000000000,
			"start low returns module to idle");

		$display("PIPELINE_MANAGER TB PASSED");
		$finish;
	end

	task check_outputs(
		input                      expected_fetch,
		input                      expected_enable,
		input [COUNTER_WIDTH-1:0]  expected_counter,
		input [VECTOR_WIDTH-1:0]   expected_next_vector,
		input [VECTOR_WIDTH-1:0]   expected_validate_vector,
		input [255:0]              test_name
	);
	begin
		if (fetch !== expected_fetch ||
			enable !== expected_enable ||
			counter !== expected_counter ||
			next_vector !== expected_next_vector ||
			validate_vector !== expected_validate_vector) begin
			$error("FAIL: %0s | fetch=%0b expected_fetch=%0b enable=%0b expected_enable=%0b counter=%0d expected_counter=%0d next=%032h expected_next=%032h validate=%032h expected_validate=%032h",
				test_name, fetch, expected_fetch, enable, expected_enable,
				counter, expected_counter, next_vector, expected_next_vector,
				validate_vector, expected_validate_vector);
			$finish;
		end
		else begin
			$display("PASS: %0s", test_name);
		end
	end
	endtask

	task send_vector(
		input [VECTOR_WIDTH-1:0] vec
	);
	begin
		wait (mfu_ready === 1'b1);
		mem_data <= vec;
		valid    <= 1'b1;
		@(posedge clk);
		#2;
		valid    <= 1'b0;
		mem_data <= {VECTOR_WIDTH{1'b0}};
	end
	endtask

	task run_until_fetch;
	begin
		@(posedge clk);
		#2;
		while (fetch !== 1'b1) begin
			@(posedge clk);
			#2;
		end
	end
	endtask

endmodule

outputs/pipeline_manager_tb.vcd
$date
	Sat Mar 07 15:36:49 2026
$end
$version
	Icarus Verilog
$end
$timescale
	100ps
$end
$scope module pipeline_manager_tb $end
$var wire 128 ! validate_vector [127:0] $end
$var wire 128 " next_vector [127:0] $end
$var wire 1 # mfu_updated $end
$var wire 1 $ mfu_ready $end
$var wire 128 % mfu_features [127:0] $end
$var wire 1 & fetch $end
$var wire 1 ' enable $end
$var wire 7 ( counter [6:0] $end
$var parameter 32 ) COUNTER_WIDTH $end
$var parameter 32 * VECTOR_WIDTH $end
$var reg 7 + N [6:0] $end
$var reg 1 , clk $end
$var reg 128 - mem_data [127:0] $end
$var reg 1 . resetN $end
$var reg 1 / start $end
$var reg 1 0 valid $end
$scope module dut $end
$var wire 7 1 N [6:0] $end
$var wire 1 , clk $end
$var wire 1 . resetN $end
$var wire 1 / start $end
$var wire 1 # mfu_updated $end
$var wire 128 2 mfu_features [127:0] $end
$var parameter 32 3 COUNTER_WIDTH $end
$var parameter 2 4 STATE_IDLE $end
$var parameter 2 5 STATE_RUN $end
$var parameter 2 6 STATE_WAIT_VECTOR $end
$var parameter 32 7 VECTOR_WIDTH $end
$var reg 7 8 counter [6:0] $end
$var reg 1 ' enable $end
$var reg 1 & fetch $end
$var reg 128 9 history_1 [127:0] $end
$var reg 128 : history_2 [127:0] $end
$var reg 128 ; next_vector [127:0] $end
$var reg 2 < state [1:0] $end
$var reg 128 = validate_vector [127:0] $end
$upscope $end
$scope module mfu $end
$var wire 1 , clk $end
$var wire 1 & fetch $end
$var wire 128 > mem_data [127:0] $end
$var wire 1 . resetN $end
$var wire 1 0 valid $end
$var parameter 32 ? DATA_WIDTH $end
$var parameter 32 @ FEATURE_WIDTH $end
$var parameter 1 A STATE_IDLE $end
$var parameter 1 B STATE_PENDING $end
$var reg 128 C features_out [127:0] $end
$var reg 1 $ ready $end
$var reg 1 D state $end
$var reg 1 # updated $end
$upscope $end
$scope task check_outputs $end
$var reg 7 E expected_counter [6:0] $end
$var reg 1 F expected_enable $end
$var reg 1 G expected_fetch $end
$var reg 128 H expected_next_vector [127:0] $end
$var reg 128 I expected_validate_vector [127:0] $end
$var reg 256 J test_name [255:0] $end
$upscope $end
$scope task run_until_fetch $end
$upscope $end
$scope task send_vector $end
$var reg 128 K vec [127:0] $end
$upscope $end
$upscope $end
$enddefinitions $end
$comment Show the parameter values. $end
$dumpall
1B
0A
b10000000 @
b10000000 ?
b10000000 7
b1 6
b10 5
b0 4
b111 3
b10000000 *
b111 )
$end
#0
$dumpvars
bx K
bx J
bx I
bx H
xG
xF
bx E
xD
bx C
b0 >
bx =
bx <
bx ;
bx :
bx 9
bx 8
bx 2
b11 1
00
0/
0.
b0 -
0,
b11 +
bx (
x'
x&
bx %
x$
x#
bx "
bx !
$end
#10
b0 <
b0 (
b0 8
b0 :
b0 9
b0 !
b0 =
b0 "
b0 ;
0'
0&
0#
b0 %
b0 2
b0 C
0$
0D
#20
1.
b111001001100101011100110110010101110100001000000110001101101100011001010110000101110010011100110010000001101111011101010111010001110000011101010111010001110011 J
b0 I
b0 H
b0 E
0F
0G
#25
1,
#45
1/
b110100101100100011011000110010100100000011000100110010101100110011011110111001001100101001000000111001101110100011000010111001001110100 J
#50
0,
#75
1,
#85
b1 <
1&
#95
b10001000100010010001000100010001100110011001101000100010001000101010101010101011001100110011001110111011101111000100010001000 K
b11100110111010001100001011100100111010000100000011100100110010101110001011101010110010101110011011101000111001100100000011001100110100101110010011100110111010000100000011101100110010101100011011101000110111101110010 J
1G
#100
0,
#125
1,
#135
10
b10001000100010010001000100010001100110011001101000100010001000101010101010101011001100110011001110111011101111000100010001000 -
b10001000100010010001000100010001100110011001101000100010001000101010101010101011001100110011001110111011101111000100010001000 >
1$
1D
0&
#150
0,
#175
1,
#185
1#
0$
0D
b10001000100010010001000100010001100110011001101000100010001000101010101010101011001100110011001110111011101111000100010001000 %
b10001000100010010001000100010001100110011001101000100010001000101010101010101011001100110011001110111011101111000100010001000 2
b10001000100010010001000100010001100110011001101000100010001000101010101010101011001100110011001110111011101111000100010001000 C
#195
b0 -
b0 >
00
#200
0,
#225
1,
#235
0#
b10 <
1'
b10001000100010010001000100010001100110011001101000100010001000101010101010101011001100110011001110111011101111000100010001000 "
b10001000100010010001000100010001100110011001101000100010001000101010101010101011001100110011001110111011101111000100010001000 ;
#245
b110100101110010011100110111010000100000011101100110010101100011011101000110111101110010001000000110110001101111011000010110010001110011001000000110000101101110011001000010000001110010011101010110111000100000011100110111010001100001011100100111010001110011 J
b10001000100010010001000100010001100110011001101000100010001000101010101010101011001100110011001110111011101111000100010001000 H
1F
0G
#250
0,
#275
1,
#285
b1 (
b1 8
#295
b110001101101111011101010110111001110100011001010111001000100000011010010110111001100011011100100110010101101101011001010110111001110100011100110010000001110111011010000110100101101100011001010010000001110010011101010110111001101110011010010110111001100111 J
b1 E
#300
0,
#325
1,
#335
b10 (
b10 8
#345
b11000110110111101110101011011100111010001100101011100100010000001100011011011110110111001110100011010010110111001110101011001010111001100100000011101000110111100100000011010010110111001100011011100100110010101101101011001010110111001110100 J
b10 E
#350
0,
#375
1,
#385
b11 (
b11 8
#395
b110001101101111011101010110111001110100011001010111001000100000011100100110010101100001011000110110100001100101011100110010000001001110 J
b11 E
#400
0,
#425
1,
#435
b1 <
0'
1&
b0 (
b0 8
#445
b10011001100110011010101010101010101110111011101111001100110011001101110111011101111011101110111011111111111111110000000000000000 K
b110010100100000011100100110010101110001011101010110010101110011011101000111001100100000011011100110010101111000011101000010000001100110011001010111010001100011011010000010000001100001011011100110010000100000011100110111010001100001011011000110110001110011 J
b0 E
0F
1G
#450
0,
#475
1,
#485
10
b10011001100110011010101010101010101110111011101111001100110011001101110111011101111011101110111011111111111111110000000000000000 -
b10011001100110011010101010101010101110111011101111001100110011001101110111011101111011101110111011111111111111110000000000000000 >
0&
1$
1D
#500
0,
#525
1,
#535
1#
0$
0D
b10011001100110011010101010101010101110111011101111001100110011001101110111011101111011101110111011111111111111110000000000000000 %
b10011001100110011010101010101010101110111011101111001100110011001101110111011101111011101110111011111111111111110000000000000000 2
b10011001100110011010101010101010101110111011101111001100110011001101110111011101111011101110111011111111111111110000000000000000 C
#545
b0 -
b0 >
00
#550
0,
#575
1,
#585
b10 <
1'
b10001000100010010001000100010001100110011001101000100010001000101010101010101011001100110011001110111011101111000100010001000 9
b10011001100110011010101010101010101110111011101111001100110011001101110111011101111011101110111011111111111111110000000000000000 "
b10011001100110011010101010101010101110111011101111001100110011001101110111011101111011101110111011111111111111110000000000000000 ;
0#
#595
b110010101100011011101000110111101110010001000000110110001101111011000010110010001110011001000000110000101101110011001000010000001110010011001010111001101110100011000010111001001110100011100110010000001100011011011110111010101101110011101000110010101110010 J
b10011001100110011010101010101010101110111011101111001100110011001101110111011101111011101110111011111111111111110000000000000000 H
1F
0G
#600
0,
#625
1,
#635
b1 (
b1 8
#650
0,
#675
1,
#685
b10 (
b10 8
#700
0,
#725
1,
#735
b11 (
b11 8
#750
0,
#775
1,
#785
b1 <
0'
1&
b0 (
b0 8
#795
b1001000110100010101100111100010011010101111001101111011111111111011011100101110101001100001110110010101000011001000010000 K
b111000001101100011001010111010001100101011100110010000001100001011011100110010000100000011100100110010101110001011101010110010101110011011101000111001100100000011101000110100001101001011100100110010000100000011101100110010101100011011101000110111101110010 J
0F
1G
#800
0,
#825
1,
#835
10
b1001000110100010101100111100010011010101111001101111011111111111011011100101110101001100001110110010101000011001000010000 -
b1001000110100010101100111100010011010101111001101111011111111111011011100101110101001100001110110010101000011001000010000 >
1$
1D
0&
#850
0,
#875
1,
#885
1#
0$
0D
b1001000110100010101100111100010011010101111001101111011111111111011011100101110101001100001110110010101000011001000010000 %
b1001000110100010101100111100010011010101111001101111011111111111011011100101110101001100001110110010101000011001000010000 2
b1001000110100010101100111100010011010101111001101111011111111111011011100101110101001100001110110010101000011001000010000 C
#895
b0 -
b0 >
00
#900
0,
#925
1,
#935
0#
b10 <
1'
b10001000100010010001000100010001100110011001101000100010001000101010101010101011001100110011001110111011101111000100010001000 :
b10011001100110011010101010101010101110111011101111001100110011001101110111011101111011101110111011111111111111110000000000000000 9
b1001000110100010101100111100010011010101111001101111011111111111011011100101110101001100001110110010101000011001000010000 "
b1001000110100010101100111100010011010101111001101111011111111111011011100101110101001100001110110010101000011001000010000 ;
#945
b110010100100000011101100110000101101100011010010110010001100001011101000110010100100000011000100111010101100110011001100110010101110010001000000110100101110011001000000111001101110100011010010110110001101100001000000110010101101101011100000111010001111001 J
b1001000110100010101100111100010011010101111001101111011111111111011011100101110101001100001110110010101000011001000010000 H
1F
0G
#950
0,
#975
1,
#985
b1 (
b1 8
#1000
0,
#1025
1,
#1035
b10 (
b10 8
#1050
0,
#1075
1,
#1085
b11 (
b11 8
#1100
0,
#1125
1,
#1135
b1 <
0'
1&
b0 (
b0 8
#1145
b10011010101111001101111011111001001000110100010101100111000000001001101010111100110111101111100100100011010001010110011100000 K
b110110001100101011101000110010101110011001000000110000101101110011001000010000001110010011001010111000101110101011001010111001101110100011100110010000001100110011011110111010101110010011101000110100000100000011101100110010101100011011101000110111101110010 J
0F
1G
#1150
0,
#1175
1,
#1185
10
b10011010101111001101111011111001001000110100010101100111000000001001101010111100110111101111100100100011010001010110011100000 -
b10011010101111001101111011111001001000110100010101100111000000001001101010111100110111101111100100100011010001010110011100000 >
0&
1$
1D
#1200
0,
#1225
1,
#1235
1#
0$
0D
b10011010101111001101111011111001001000110100010101100111000000001001101010111100110111101111100100100011010001010110011100000 %
b10011010101111001101111011111001001000110100010101100111000000001001101010111100110111101111100100100011010001010110011100000 2
b10011010101111001101111011111001001000110100010101100111000000001001101010111100110111101111100100100011010001010110011100000 C
#1245
b0 -
b0 >
00
#1250
0,
#1275
1,
#1285
b10 <
1'
b10001000100010010001000100010001100110011001101000100010001000101010101010101011001100110011001110111011101111000100010001000 !
b10001000100010010001000100010001100110011001101000100010001000101010101010101011001100110011001110111011101111000100010001000 =
b10011001100110011010101010101010101110111011101111001100110011001101110111011101111011101110111011111111111111110000000000000000 :
b1001000110100010101100111100010011010101111001101111011111111111011011100101110101001100001110110010101000011001000010000 9
b10011010101111001101111011111001001000110100010101100111000000001001101010111100110111101111100100100011010001010110011100000 "
b10011010101111001101111011111001001000110100010101100111000000001001101010111100110111101111100100100011010001010110011100000 ;
0#
#1295
0/
b111011001100001011011000110100101100100011000010111010001100101001000000111011001100101011000110111010001101111011100100010000001100110011100100110111101101101001000000110011001101001011100100111001101110100001000000110100101101110011100000111010101110100 J
b10001000100010010001000100010001100110011001101000100010001000101010101010101011001100110011001110111011101111000100010001000 I
b10011010101111001101111011111001001000110100010101100111000000001001101010111100110111101111100100100011010001010110011100000 H
1F
0G
#1300
0,
#1325
1,
#1335
b0 <
b0 :
b0 9
b0 !
b0 =
b0 "
b0 ;
0'
#1345
b111001101110100011000010111001001110100001000000110110001101111011101110010000001110010011001010111010001110101011100100110111001110011001000000110110101101111011001000111010101101100011001010010000001110100011011110010000001101001011001000110110001100101 J
b0 I
b0 H
0F
