ANIDS/anids_defines.vh
// ANIDS Defines
// Clock Period, this is 5ns period (200MHz clock)
`define CLK_PERIOD				16'd5


// APB can work with 8, 16, 32 bit data width
`define APB_DATA_WIDTH			8
`define APB_ADDR_WIDTH			16 							// 15 bits needed, but we use 16.


// DMA Data Width is input vector size, which is 128 bits
`define DMA_DATA_WIDTH			128

// Memory Fetch Unit widths
`define MFU_DATA_WIDTH			`DMA_DATA_WIDTH
`define MFU_FEATURE_WIDTH		`MFU_DATA_WIDTH				// stored feature vector width

// Pipeline Manager widths and history depth
`define PIPELINE_VECTOR_WIDTH	`MFU_FEATURE_WIDTH			// vector width propagated through pipeline manager
`define PIPELINE_COUNTER_WIDTH	7							// counter width for indices 0..127
`define PIPELINE_HISTORY_DEPTH	2							// number of coarse vector buffers before validation
`define PIPELINE_STAGE_CYCLES	64							// 128-bit vector processed over 64 cycles
`define PIPELINE_STAGE_COUNT_W	6							// counter width for 0..63 stage timing

// Input layer widths
`define INPUT_LAYER_FEATURE_WIDTH	`PIPELINE_VECTOR_WIDTH	// full feature vector width seen by input layer
`define INPUT_LAYER_PAIR_WIDTH		2						// number of feature bits processed per counter step

// Hidden layer unit widths
`define HL_FEATURE_PAIR_WIDTH		`INPUT_LAYER_PAIR_WIDTH	// number of feature bits consumed per cycle
`define HL_WEIGHT_WIDTH				8						// signed Q0.7 weight width
`define HL_BIAS_WIDTH				8						// signed Q0.7 bias width
`define HL_RESULT_WIDTH				8						// signed Q0.7 hidden neuron output width
`define HL_PAIR_SUM_WIDTH			9						// sum of two weighted feature contributions
`define HL_ACC_WIDTH				15						// accumulation register width before truncation

// Output layer unit widths
`define OL_INPUT_WIDTH				8						// signed Q0.7 hidden-layer input width
`define OL_WEIGHT_WIDTH				8						// signed Q0.7 output-layer weight width
`define OL_BIAS_WIDTH				8						// signed Q0.7 output-layer bias width
`define OL_RESULT_WIDTH				8						// signed Q0.7 output-layer result width
`define OL_PRODUCT_WIDTH			16						// full signed 8x8 multiply width
`define OL_TRUNC_PRODUCT_WIDTH		8						// product truncated back to Q0.7
`define OL_ACC_WIDTH				15						// accumulation width before final truncation

// Loss function widths
`define LF_FEATURE_PAIR_WIDTH		`INPUT_LAYER_PAIR_WIDTH	// number of original feature bits consumed per cycle
`define LF_RESULT_IN_WIDTH			8						// compared result width
`define LF_ABS_WIDTH				8						// absolute delta width
`define LF_PAIR_SUM_WIDTH			9						// sum of two absolute deltas
`define LF_ACC_WIDTH				15						// accumulation register width before truncation

// Sigmoid LUT address mapper widths
`define MMAP_IN_WIDTH				8						// signed Q0.7 value width before LUT lookup
`define MMAP_ADDR_WIDTH				`LUT_ADDR_WIDTH		// LUT address width after mapping

// LUT Address and Data Sizes
`define LUT_ADDR_WIDTH			8
`define LUT_DATA_WIDTH			8

`define RELU_WIDTH 				8
`define LF_OUT_WIDTH			8



// Weight & Bias Counts
`define HL_WEIGHT_COUNT   		64 * 128   	// 8192
`define HL_BIAS_COUNT      		64       	// 64
`define OL_WEIGHT_COUNT    		128 * 64   	// 8192
`define OL_BIAS_COUNT      		128      	// 128


// ANIDS Control Register Addresses
`define START_REG				0
`define N_REG					1
`define THRESHOLD_REG			2
`define RESULT_REG				3


// Indirect LUT Read/Write Registers
`define LUT_ADDR				4
`define LUT_DATA				5
`define LUT_CTRL				6
`define FREE_REG				7


// Hidden Layer Register Mapping
`define HL_WEIGHT_BASE			8 // we have 128 * 64 of these
`define HL_BIAS_BASE			`HL_WEIGHT_BASE + `HL_WEIGHT_COUNT // and 64 of these


// Output Layer Register Mapping
`define OL_WEIGHT_BASE			`HL_BIAS_BASE + `HL_BIAS_COUNT
`define OL_BIAS_BASE			`OL_WEIGHT_BASE + `OL_WEIGHT_COUNT


// ANIDS memory map borders
`define ANIDS_MAP_START   		`HL_WEIGHT_BASE
`define ANIDS_MAP_END     		`OL_BIAS_BASE + `OL_BIAS_COUNT
`define REG_COUNT				`ANIDS_MAP_END 	// (correct count due to 0-based indexing)


// Pipeline Stage Cycles
`define INPUT_LAYER_CYCLES 		1
`define HIDDEN_LAYER_CYCLES 	64
`define OUTPUT_LAYER_CYCLES 	64
`define LOOKUP_LAYER_CYCLES 	64
`define LOSS_FUNCTION_CYCLES 	64
`define OUTLIER_CYCLES 			1
`define RESULT_CYCLES 			1


// Pipeline Fill and Latency in cycles (pipefill = 259, latency = 130)
`define PIPE_FILL_CYCLES 		(`INPUT_LAYER_CYCLES + `HIDDEN_LAYER_CYCLES + `OUTPUT_LAYER_CYCLES + `LOOKUP_LAYER_CYCLES + `LOSS_FUNCTION_CYCLES + `OUTLIER_CYCLES + `RESULT_CYCLES)
`define LATENCY_IN_CYCLES 		(`LOOKUP_LAYER_CYCLES + `LOSS_FUNCTION_CYCLES + `OUTLIER_CYCLES + `RESULT_CYCLES )

ANIDS/src/mem_fetch_unit.sv
// ANIDS Memory Fetch Unit
`include "anids_defines.vh"

module mem_fetch_unit (
		clk,
		resetN,
		fetch,
		valid,
		mem_data,
		ready,
		features_out,
		updated
	);

	parameter DATA_WIDTH    = `MFU_DATA_WIDTH;
	parameter FEATURE_WIDTH = `MFU_FEATURE_WIDTH;

	// ----------------------------------------------------------------------
	//                  		I/O Ports
	// ----------------------------------------------------------------------
	input  wire							clk;
	input  wire							resetN;
	input  wire							fetch;
	input  wire							valid;
	input  wire [DATA_WIDTH-1:0] 		mem_data;
	output reg 							ready;
	output reg  [FEATURE_WIDTH-1:0] 	features_out;
	output reg 							updated;

	// ----------------------------------------------------------------------
	//                  		State Machine
	// ----------------------------------------------------------------------
	localparam STATE_IDLE    = 1'b0;
	localparam STATE_PENDING = 1'b1;

	reg state;

	always @(posedge clk or negedge resetN) begin
		if (!resetN) begin
			state        <= #1 STATE_IDLE;
			ready        <= #1 1'b0;
			features_out <= #1 {FEATURE_WIDTH{1'b0}};
			updated      <= #1 1'b0;
		end
		else begin
			case (state)
				STATE_IDLE: begin
					ready   <= #1 1'b0;
					updated <= #1 1'b0;

					if (fetch) begin
						state <= #1 STATE_PENDING;
						ready <= #1 1'b1;
					end
				end

				STATE_PENDING: begin
					ready   <= #1 1'b1;
					updated <= #1 1'b0;

					if (valid) begin
						features_out <= #1 mem_data[FEATURE_WIDTH-1:0];
						state        <= #1 STATE_IDLE;
						ready        <= #1 1'b0;
						updated      <= #1 1'b1;
					end
				end

				// *** remove later? this is redundant for safety
				default: begin
					state   <= #1 STATE_IDLE;
					ready   <= #1 1'b0;
					updated <= #1 1'b0;
				end
			endcase
		end
	end

endmodule

ANIDS/src/core/pipeline_manager.v
// ANIDS Pipeline Manager
`include "anids_defines.vh"

module pipeline_manager (
		clk,
		resetN,
		start,
		N,
		mfu_features,
		mfu_updated,
		fetch,
		enable,
		output_enable,
		loss_enable,
		next_vector,
		validate_vector,
		counter
	);

	parameter VECTOR_WIDTH   = `PIPELINE_VECTOR_WIDTH;
	parameter COUNTER_WIDTH  = `PIPELINE_COUNTER_WIDTH;
	parameter FIFO_DEPTH     = 4;
	parameter FIFO_COUNT_W   = 3;
	parameter FIFO_PTR_W     = 2;
	parameter EPOCH_WIDTH    = 3;

	// ----------------------------------------------------------------------
	//                  		I/O Ports
	// ----------------------------------------------------------------------
	input  wire                         clk;
	input  wire                         resetN;
	input  wire                         start;
	input  wire [`APB_DATA_WIDTH-1:0]   N;
	input  wire [VECTOR_WIDTH-1:0]      mfu_features;
	input  wire                         mfu_updated;
	output reg                          fetch;
	output wire                         enable;
	output wire                         output_enable;
	output wire                         loss_enable;
	output wire [VECTOR_WIDTH-1:0]      next_vector;
	output wire [VECTOR_WIDTH-1:0]      validate_vector;
	output reg  [COUNTER_WIDTH-1:0]     counter;

	// ----------------------------------------------------------------------
	//                  		Vector Stage Registers
	// ----------------------------------------------------------------------
	reg [VECTOR_WIDTH-1:0] stage0_vector;
	reg [VECTOR_WIDTH-1:0] stage1_vector;
	reg [VECTOR_WIDTH-1:0] stage2_vector;
	reg                    stage0_valid;
	reg                    stage1_valid;
	reg                    stage2_valid;
	reg [EPOCH_WIDTH-1:0]  epoch_count;

	assign next_vector     = stage0_vector;
	assign validate_vector = stage2_vector;
	assign enable          = stage0_valid;
	assign output_enable   = stage1_valid;
	assign loss_enable     = stage2_valid;

	// ----------------------------------------------------------------------
	//                  		Streaming FIFO
	// ----------------------------------------------------------------------
	reg [VECTOR_WIDTH-1:0] fifo_mem [0:FIFO_DEPTH-1];
	reg [FIFO_PTR_W-1:0]   fifo_wr_ptr;
	reg [FIFO_PTR_W-1:0]   fifo_rd_ptr;
	reg [FIFO_COUNT_W-1:0] fifo_count;
	reg                    fetch_inflight;

	wire stage_active      = stage0_valid || stage1_valid || stage2_valid;
	wire [COUNTER_WIDTH-1:0] last_pair_index = ((N >> 1) - 1'b1);
	wire start_epoch       = !stage_active && (fifo_count != 0);
	wire boundary_shift    = stage_active && (counter == last_pair_index);
	wire inject_next_stage = (fifo_count != 0);
	wire pop_fifo          = start_epoch || (boundary_shift && inject_next_stage);

	// ----------------------------------------------------------------------
	//                  		Manager Logic
	// ----------------------------------------------------------------------
	always @(posedge clk or negedge resetN) begin
		if (!resetN) begin
			fetch          <= #1 1'b0;
			counter        <= #1 {COUNTER_WIDTH{1'b0}};
			stage0_vector  <= #1 {VECTOR_WIDTH{1'b0}};
			stage1_vector  <= #1 {VECTOR_WIDTH{1'b0}};
			stage2_vector  <= #1 {VECTOR_WIDTH{1'b0}};
			stage0_valid   <= #1 1'b0;
			stage1_valid   <= #1 1'b0;
			stage2_valid   <= #1 1'b0;
			epoch_count    <= #1 {EPOCH_WIDTH{1'b0}};
			fifo_wr_ptr    <= #1 {FIFO_PTR_W{1'b0}};
			fifo_rd_ptr    <= #1 {FIFO_PTR_W{1'b0}};
			fifo_count     <= #1 {FIFO_COUNT_W{1'b0}};
			fetch_inflight <= #1 1'b0;
		end
		else if (!start) begin
			fetch          <= #1 1'b0;
			counter        <= #1 {COUNTER_WIDTH{1'b0}};
			stage0_vector  <= #1 {VECTOR_WIDTH{1'b0}};
			stage1_vector  <= #1 {VECTOR_WIDTH{1'b0}};
			stage2_vector  <= #1 {VECTOR_WIDTH{1'b0}};
			stage0_valid   <= #1 1'b0;
			stage1_valid   <= #1 1'b0;
			stage2_valid   <= #1 1'b0;
			epoch_count    <= #1 {EPOCH_WIDTH{1'b0}};
			fifo_wr_ptr    <= #1 {FIFO_PTR_W{1'b0}};
			fifo_rd_ptr    <= #1 {FIFO_PTR_W{1'b0}};
			fifo_count     <= #1 {FIFO_COUNT_W{1'b0}};
			fetch_inflight <= #1 1'b0;
		end
		else begin
			fetch <= #1 1'b0;

			if (mfu_updated) begin
				fifo_mem[fifo_wr_ptr] <= #1 mfu_features;
				fifo_wr_ptr           <= #1 fifo_wr_ptr + 1'b1;
				fetch_inflight        <= #1 1'b0;
			end

			if (start_epoch) begin
				stage0_vector <= #1 fifo_mem[fifo_rd_ptr];
				stage1_vector <= #1 {VECTOR_WIDTH{1'b0}};
				stage2_vector <= #1 {VECTOR_WIDTH{1'b0}};
				stage0_valid  <= #1 1'b1;
				stage1_valid  <= #1 1'b0;
				stage2_valid  <= #1 1'b0;
				counter       <= #1 {COUNTER_WIDTH{1'b0}};
				epoch_count   <= #1 {{(EPOCH_WIDTH-1){1'b0}}, 1'b1};
			end
			else if (boundary_shift) begin
				stage2_vector <= #1 stage1_vector;
				stage1_vector <= #1 stage0_vector;
				stage0_vector <= #1 (inject_next_stage ? fifo_mem[fifo_rd_ptr] : {VECTOR_WIDTH{1'b0}});
				stage2_valid  <= #1 ((epoch_count >= 2) ? stage1_valid : 1'b0);
				stage1_valid  <= #1 ((epoch_count >= 1) ? stage0_valid : 1'b0);
				stage0_valid  <= #1 inject_next_stage;
				counter       <= #1 {COUNTER_WIDTH{1'b0}};
				if (epoch_count < ((1 << EPOCH_WIDTH) - 1))
					epoch_count <= #1 epoch_count + 1'b1;
			end
			else if (stage_active) begin
				counter <= #1 counter + 1'b1;
			end
			else begin
				counter <= #1 {COUNTER_WIDTH{1'b0}};
			end

			if (pop_fifo && mfu_updated) begin
				fifo_rd_ptr <= #1 fifo_rd_ptr + 1'b1;
				fifo_count  <= #1 fifo_count;
			end
			else if (pop_fifo) begin
				fifo_rd_ptr <= #1 fifo_rd_ptr + 1'b1;
				fifo_count  <= #1 fifo_count - 1'b1;
			end
			else if (mfu_updated) begin
				fifo_count <= #1 fifo_count + 1'b1;
			end

			if (!fetch_inflight && (fifo_count < FIFO_DEPTH)) begin
				fetch          <= #1 1'b1;
				fetch_inflight <= #1 1'b1;
			end
		end
	end

endmodule

ANIDS/tb/integration/pipeline_manager_tb.v
// ANIDS - Pipeline Manager Testbench
`timescale 1ns/100ps
`include "anids_defines.vh"

module pipeline_manager_tb;

	localparam VECTOR_WIDTH  = `PIPELINE_VECTOR_WIDTH;
	localparam COUNTER_WIDTH = `PIPELINE_COUNTER_WIDTH;

	reg                         clk;
	reg                         resetN;
	reg                         start;
	reg  [`APB_DATA_WIDTH-1:0]  N;
	reg                         valid;
	reg  [VECTOR_WIDTH-1:0]     mem_data;
	wire                        fetch;
	wire                        enable;
	wire                        output_enable;
	wire                        loss_enable;
	wire                        mfu_ready;
	wire [VECTOR_WIDTH-1:0]     mfu_features;
	wire                        mfu_updated;
	wire [VECTOR_WIDTH-1:0]     next_vector;
	wire [VECTOR_WIDTH-1:0]     validate_vector;
	wire [COUNTER_WIDTH-1:0]    counter;

	pipeline_manager #(
		.VECTOR_WIDTH  (VECTOR_WIDTH),
		.COUNTER_WIDTH (COUNTER_WIDTH)
	) dut (
		.clk             (clk),
		.resetN          (resetN),
		.start           (start),
		.N               (N),
		.mfu_features    (mfu_features),
		.mfu_updated     (mfu_updated),
		.fetch           (fetch),
		.enable          (enable),
		.output_enable   (output_enable),
		.loss_enable     (loss_enable),
		.next_vector     (next_vector),
		.validate_vector (validate_vector),
		.counter         (counter)
	);

	mem_fetch_unit #(
		.DATA_WIDTH    (VECTOR_WIDTH),
		.FEATURE_WIDTH (VECTOR_WIDTH)
	) mfu (
		.clk          (clk),
		.resetN       (resetN),
		.fetch        (fetch),
		.valid        (valid),
		.mem_data     (mem_data),
		.ready        (mfu_ready),
		.features_out (mfu_features),
		.updated      (mfu_updated)
	);

	always #2.5 clk = ~clk;

	initial begin
		$dumpfile("pipeline_manager_tb.vcd");
		$dumpvars(0, pipeline_manager_tb);

		clk      = 1'b0;
		resetN   = 1'b0;
		start    = 1'b0;
		N        = 8'd8; // four pair-steps per epoch
		valid    = 1'b0;
		mem_data = {VECTOR_WIDTH{1'b0}};
		#2;

		check_outputs(1'b0, 1'b0, 1'b0, 1'b0, 7'd0,
			128'h00000000000000000000000000000000,
			128'h00000000000000000000000000000000,
			"reset clears outputs");

		resetN <= 1'b1;
		@(posedge clk);
		#2;
		check_outputs(fetch, 1'b0, 1'b0, 1'b0, 7'd0,
			128'h00000000000000000000000000000000,
			128'h00000000000000000000000000000000,
			"idle before start");

		start <= 1'b1;
		wait (fetch === 1'b1);
		send_vector(128'h11112222333344445555666677778888);
		wait (enable === 1'b1);
		@(posedge clk);
		#2;
		check_outputs(fetch, 1'b1, 1'b0, 1'b0, counter,
			128'h11112222333344445555666677778888,
			128'h00000000000000000000000000000000,
			"first epoch starts with hidden stage only");

		send_vector(128'h9999AAAABBBBCCCCDDDDEEEEFFFF0000);
		run_to_epoch_start;
		check_outputs(fetch, 1'b1, 1'b1, 1'b0, 7'd0,
			128'h9999AAAABBBBCCCCDDDDEEEEFFFF0000,
			128'h00000000000000000000000000000000,
			"second epoch enables output stage");

		send_vector(128'h0123456789ABCDEFFEDCBA9876543210);
		run_to_epoch_start;
		check_outputs(fetch, 1'b1, 1'b1, 1'b1, 7'd0,
			128'h0123456789ABCDEFFEDCBA9876543210,
			128'h11112222333344445555666677778888,
			"third epoch enables loss stage and aligns validate vector");

		send_vector(128'h13579BDF2468ACE013579BDF2468ACE0);
		run_to_epoch_start;
		check_outputs(fetch, 1'b1, 1'b1, 1'b1, 7'd0,
			128'h13579BDF2468ACE013579BDF2468ACE0,
			128'h9999AAAABBBBCCCCDDDDEEEEFFFF0000,
			"steady-state pipeline keeps all stages enabled");

		start <= 1'b0;
		@(posedge clk);
		#2;
		check_outputs(1'b0, 1'b0, 1'b0, 1'b0, 7'd0,
			128'h00000000000000000000000000000000,
			128'h00000000000000000000000000000000,
			"start low returns module to idle");

		$display("PIPELINE_MANAGER TB PASSED");
		$finish;
	end

	task check_outputs(
		input                      expected_fetch,
		input                      expected_hidden_enable,
		input                      expected_output_enable,
		input                      expected_loss_enable,
		input [COUNTER_WIDTH-1:0]  expected_counter,
		input [VECTOR_WIDTH-1:0]   expected_next_vector,
		input [VECTOR_WIDTH-1:0]   expected_validate_vector,
		input [255:0]              test_name
	);
	begin
		if (fetch !== expected_fetch ||
			enable !== expected_hidden_enable ||
			output_enable !== expected_output_enable ||
			loss_enable !== expected_loss_enable ||
			counter !== expected_counter ||
			next_vector !== expected_next_vector ||
			validate_vector !== expected_validate_vector) begin
			$error("FAIL: %0s | fetch=%0b expected_fetch=%0b hidden=%0b expected_hidden=%0b output=%0b expected_output=%0b loss=%0b expected_loss=%0b counter=%0d expected_counter=%0d next=%032h expected_next=%032h validate=%032h expected_validate=%032h",
				test_name, fetch, expected_fetch, enable, expected_hidden_enable,
				output_enable, expected_output_enable, loss_enable, expected_loss_enable,
				counter, expected_counter, next_vector, expected_next_vector,
				validate_vector, expected_validate_vector);
			$finish;
		end
		else begin
			$display("PASS: %0s", test_name);
		end
	end
	endtask

	task send_vector(
		input [VECTOR_WIDTH-1:0] vec
	);
	begin
		wait (mfu_ready === 1'b1);
		mem_data <= vec;
		valid    <= 1'b1;
		@(posedge clk);
		#2;
		valid    <= 1'b0;
		mem_data <= {VECTOR_WIDTH{1'b0}};
	end
	endtask

	task run_to_epoch_start;
	begin
		while (counter !== 7'd0 || enable !== 1'b1) begin
			@(posedge clk);
			#2;
		end
	end
	endtask

endmodule

outputs/pipeline_manager_tb.vcd
$date
	Sat Mar 14 15:42:11 2026
$end
$version
	Icarus Verilog
$end
$timescale
	100ps
$end
$scope module pipeline_manager_tb $end
$var wire 128 ! validate_vector [127:0] $end
$var wire 1 " output_enable $end
$var wire 128 # next_vector [127:0] $end
$var wire 1 $ mfu_updated $end
$var wire 1 % mfu_ready $end
$var wire 128 & mfu_features [127:0] $end
$var wire 1 ' loss_enable $end
$var wire 1 ( fetch $end
$var wire 1 ) enable $end
$var wire 7 * counter [6:0] $end
$var parameter 32 + COUNTER_WIDTH $end
$var parameter 32 , VECTOR_WIDTH $end
$var reg 8 - N [7:0] $end
$var reg 1 . clk $end
$var reg 128 / mem_data [127:0] $end
$var reg 1 0 resetN $end
$var reg 1 1 start $end
$var reg 1 2 valid $end
$scope module dut $end
$var wire 8 3 N [7:0] $end
$var wire 1 4 boundary_shift $end
$var wire 1 . clk $end
$var wire 1 ) enable $end
$var wire 1 ' loss_enable $end
$var wire 128 5 next_vector [127:0] $end
$var wire 1 " output_enable $end
$var wire 1 6 pop_fifo $end
$var wire 1 0 resetN $end
$var wire 1 7 stage_active $end
$var wire 1 1 start $end
$var wire 1 8 start_epoch $end
$var wire 128 9 validate_vector [127:0] $end
$var wire 1 $ mfu_updated $end
$var wire 128 : mfu_features [127:0] $end
$var wire 7 ; last_pair_index [6:0] $end
$var wire 1 < inject_next_stage $end
$var parameter 32 = COUNTER_WIDTH $end
$var parameter 32 > EPOCH_WIDTH $end
$var parameter 32 ? FIFO_COUNT_W $end
$var parameter 32 @ FIFO_DEPTH $end
$var parameter 32 A FIFO_PTR_W $end
$var parameter 32 B VECTOR_WIDTH $end
$var reg 7 C counter [6:0] $end
$var reg 3 D epoch_count [2:0] $end
$var reg 1 ( fetch $end
$var reg 1 E fetch_inflight $end
$var reg 3 F fifo_count [2:0] $end
$var reg 2 G fifo_rd_ptr [1:0] $end
$var reg 2 H fifo_wr_ptr [1:0] $end
$var reg 1 I stage0_valid $end
$var reg 128 J stage0_vector [127:0] $end
$var reg 1 K stage1_valid $end
$var reg 128 L stage1_vector [127:0] $end
$var reg 1 M stage2_valid $end
$var reg 128 N stage2_vector [127:0] $end
$upscope $end
$scope module mfu $end
$var wire 1 . clk $end
$var wire 1 ( fetch $end
$var wire 128 O mem_data [127:0] $end
$var wire 1 0 resetN $end
$var wire 1 2 valid $end
$var parameter 32 P DATA_WIDTH $end
$var parameter 32 Q FEATURE_WIDTH $end
$var parameter 1 R STATE_IDLE $end
$var parameter 1 S STATE_PENDING $end
$var reg 128 T features_out [127:0] $end
$var reg 1 % ready $end
$var reg 1 U state $end
$var reg 1 $ updated $end
$upscope $end
$scope task check_outputs $end
$var reg 7 V expected_counter [6:0] $end
$var reg 1 W expected_fetch $end
$var reg 1 X expected_hidden_enable $end
$var reg 1 Y expected_loss_enable $end
$var reg 128 Z expected_next_vector [127:0] $end
$var reg 1 [ expected_output_enable $end
$var reg 128 \ expected_validate_vector [127:0] $end
$var reg 256 ] test_name [255:0] $end
$upscope $end
$scope task run_to_epoch_start $end
$upscope $end
$scope task send_vector $end
$var reg 128 ^ vec [127:0] $end
$upscope $end
$upscope $end
$enddefinitions $end
$comment Show the parameter values. $end
$dumpall
1S
0R
b10000000 Q
b10000000 P
b10000000 B
b10 A
b100 @
b11 ?
b11 >
b111 =
b10000000 ,
b111 +
$end
#0
$dumpvars
bx ^
bx ]
bx \
x[
bx Z
xY
xX
xW
bx V
xU
bx T
b0 O
bx N
xM
bx L
xK
bx J
xI
bx H
bx G
bx F
xE
bx D
bx C
x<
b11 ;
bx :
bx 9
x8
x7
x6
bx 5
x4
b1000 3
02
01
00
b0 /
0.
b1000 -
bx *
x)
x(
x'
bx &
x%
x$
bx #
x"
bx !
$end
#10
06
08
07
04
0E
0<
b0 F
b0 G
b0 H
b0 D
0'
0M
0"
0K
0)
0I
b0 !
b0 9
b0 N
b0 L
b0 #
b0 5
b0 J
b0 *
b0 C
0(
0$
b0 &
b0 :
b0 T
0%
0U
#20
10
b111001001100101011100110110010101110100001000000110001101101100011001010110000101110010011100110010000001101111011101010111010001110000011101010111010001110011 ]
b0 \
b0 Z
b0 V
0Y
0[
0X
0W
#25
1.
#45
11
b110100101100100011011000110010100100000011000100110010101100110011011110111001001100101001000000111001101110100011000010111001001110100 ]
#50
0.
#75
1.
#85
b10001000100010010001000100010001100110011001101000100010001000101010101010101011001100110011001110111011101111000100010001000 ^
1E
1(
#100
0.
#125
1.
#135
12
b10001000100010010001000100010001100110011001101000100010001000101010101010101011001100110011001110111011101111000100010001000 /
b10001000100010010001000100010001100110011001101000100010001000101010101010101011001100110011001110111011101111000100010001000 O
1%
1U
0(
#150
0.
#175
1.
#185
1$
0%
0U
b10001000100010010001000100010001100110011001101000100010001000101010101010101011001100110011001110111011101111000100010001000 &
b10001000100010010001000100010001100110011001101000100010001000101010101010101011001100110011001110111011101111000100010001000 :
b10001000100010010001000100010001100110011001101000100010001000101010101010101011001100110011001110111011101111000100010001000 T
#195
b0 /
b0 O
02
#200
0.
#225
1.
#235
16
18
0$
1<
b1 F
0E
b1 H
#250
0.
#275
1.
#285
06
17
08
1E
1(
0<
b0 F
b1 G
b1 D
1)
1I
b10001000100010010001000100010001100110011001101000100010001000101010101010101011001100110011001110111011101111000100010001000 #
b10001000100010010001000100010001100110011001101000100010001000101010101010101011001100110011001110111011101111000100010001000 5
b10001000100010010001000100010001100110011001101000100010001000101010101010101011001100110011001110111011101111000100010001000 J
#300
0.
#325
1.
#335
1%
1U
b1 *
b1 C
0(
#345
12
b10011001100110011010101010101010101110111011101111001100110011001101110111011101111011101110111011111111111111110000000000000000 /
b10011001100110011010101010101010101110111011101111001100110011001101110111011101111011101110111011111111111111110000000000000000 O
b10011001100110011010101010101010101110111011101111001100110011001101110111011101111011101110111011111111111111110000000000000000 ^
b110001101101000001000000111001101110100011000010111001001110100011100110010000001110111011010010111010001101000001000000110100001101001011001000110010001100101011011100010000001110011011101000110000101100111011001010010000001101111011011100110110001111001 ]
b10001000100010010001000100010001100110011001101000100010001000101010101010101011001100110011001110111011101111000100010001000 Z
b1 V
1X
#350
0.
#375
1.
#385
b10 *
b10 C
1$
0%
0U
b10011001100110011010101010101010101110111011101111001100110011001101110111011101111011101110111011111111111111110000000000000000 &
b10011001100110011010101010101010101110111011101111001100110011001101110111011101111011101110111011111111111111110000000000000000 :
b10011001100110011010101010101010101110111011101111001100110011001101110111011101111011101110111011111111111111110000000000000000 T
#395
b0 /
b0 O
02
#400
0.
#425
1.
#435
16
14
0$
1<
b1 F
b11 *
b11 C
0E
b10 H
#450
0.
#475
1.
#485
06
04
1E
1(
0<
b0 F
b10 G
b10 D
b0 *
b0 C
1"
1K
b10011001100110011010101010101010101110111011101111001100110011001101110111011101111011101110111011111111111111110000000000000000 #
b10011001100110011010101010101010101110111011101111001100110011001101110111011101111011101110111011111111111111110000000000000000 5
b10011001100110011010101010101010101110111011101111001100110011001101110111011101111011101110111011111111111111110000000000000000 J
b10001000100010010001000100010001100110011001101000100010001000101010101010101011001100110011001110111011101111000100010001000 L
#495
b1001000110100010101100111100010011010101111001101111011111111111011011100101110101001100001110110010101000011001000010000 ^
b110010101100011011011110110111001100100001000000110010101110000011011110110001101101000001000000110010101101110011000010110001001101100011001010111001100100000011011110111010101110100011100000111010101110100001000000111001101110100011000010110011101100101 ]
b10011001100110011010101010101010101110111011101111001100110011001101110111011101111011101110111011111111111111110000000000000000 Z
b0 V
1[
1W
#500
0.
#525
1.
#535
12
b1001000110100010101100111100010011010101111001101111011111111111011011100101110101001100001110110010101000011001000010000 /
b1001000110100010101100111100010011010101111001101111011111111111011011100101110101001100001110110010101000011001000010000 O
1%
1U
b1 *
b1 C
0(
#550
0.
#575
1.
#585
b10 *
b10 C
1$
0%
0U
b1001000110100010101100111100010011010101111001101111011111111111011011100101110101001100001110110010101000011001000010000 &
b1001000110100010101100111100010011010101111001101111011111111111011011100101110101001100001110110010101000011001000010000 :
b1001000110100010101100111100010011010101111001101111011111111111011011100101110101001100001110110010101000011001000010000 T
#595
b0 /
b0 O
02
#600
0.
#625
1.
#635
16
14
0$
1<
b1 F
b11 *
b11 C
0E
b11 H
#650
0.
#675
1.
#685
06
04
1E
1(
0<
b0 F
b11 G
b11 D
b0 *
b0 C
1'
1M
b1001000110100010101100111100010011010101111001101111011111111111011011100101110101001100001110110010101000011001000010000 #
b1001000110100010101100111100010011010101111001101111011111111111011011100101110101001100001110110010101000011001000010000 5
b1001000110100010101100111100010011010101111001101111011111111111011011100101110101001100001110110010101000011001000010000 J
b10011001100110011010101010101010101110111011101111001100110011001101110111011101111011101110111011111111111111110000000000000000 L
b10001000100010010001000100010001100110011001101000100010001000101010101010101011001100110011001110111011101111000100010001000 !
b10001000100010010001000100010001100110011001101000100010001000101010101010101011001100110011001110111011101111000100010001000 9
b10001000100010010001000100010001100110011001101000100010001000101010101010101011001100110011001110111011101111000100010001000 N
#695
b10011010101111001101111011111001001000110100010101100111000000001001101010111100110111101111100100100011010001010110011100000 ^
b111001101110100011000010110011101100101001000000110000101101110011001000010000001100001011011000110100101100111011011100111001100100000011101100110000101101100011010010110010001100001011101000110010100100000011101100110010101100011011101000110111101110010 ]
b10001000100010010001000100010001100110011001101000100010001000101010101010101011001100110011001110111011101111000100010001000 \
b1001000110100010101100111100010011010101111001101111011111111111011011100101110101001100001110110010101000011001000010000 Z
1Y
#700
0.
#725
1.
#735
12
b10011010101111001101111011111001001000110100010101100111000000001001101010111100110111101111100100100011010001010110011100000 /
b10011010101111001101111011111001001000110100010101100111000000001001101010111100110111101111100100100011010001010110011100000 O
1%
1U
b1 *
b1 C
0(
#750
0.
#775
1.
#785
b10 *
b10 C
1$
0%
0U
b10011010101111001101111011111001001000110100010101100111000000001001101010111100110111101111100100100011010001010110011100000 &
b10011010101111001101111011111001001000110100010101100111000000001001101010111100110111101111100100100011010001010110011100000 :
b10011010101111001101111011111001001000110100010101100111000000001001101010111100110111101111100100100011010001010110011100000 T
#795
b0 /
b0 O
02
#800
0.
#825
1.
#835
16
14
0$
1<
b1 F
b11 *
b11 C
0E
b0 H
#850
0.
#875
1.
#885
06
04
1E
1(
0<
b0 F
b0 G
b100 D
b0 *
b0 C
b10011010101111001101111011111001001000110100010101100111000000001001101010111100110111101111100100100011010001010110011100000 #
b10011010101111001101111011111001001000110100010101100111000000001001101010111100110111101111100100100011010001010110011100000 5
b10011010101111001101111011111001001000110100010101100111000000001001101010111100110111101111100100100011010001010110011100000 J
b1001000110100010101100111100010011010101111001101111011111111111011011100101110101001100001110110010101000011001000010000 L
b10011001100110011010101010101010101110111011101111001100110011001101110111011101111011101110111011111111111111110000000000000000 !
b10011001100110011010101010101010101110111011101111001100110011001101110111011101111011101110111011111111111111110000000000000000 9
b10011001100110011010101010101010101110111011101111001100110011001101110111011101111011101110111011111111111111110000000000000000 N
#895
01
b110100101110000011001010110110001101001011011100110010100100000011010110110010101100101011100000111001100100000011000010110110001101100001000000111001101110100011000010110011101100101011100110010000001100101011011100110000101100010011011000110010101100100 ]
b10011001100110011010101010101010101110111011101111001100110011001101110111011101111011101110111011111111111111110000000000000000 \
b10011010101111001101111011111001001000110100010101100111000000001001101010111100110111101111100100100011010001010110011100000 Z
#900
0.
#925
1.
#935
07
1%
1U
0E
b0 D
0'
0M
0"
0K
0)
0I
b0 !
b0 9
b0 N
b0 L
b0 #
b0 5
b0 J
0(
#945
b111001101110100011000010111001001110100001000000110110001101111011101110010000001110010011001010111010001110101011100100110111001110011001000000110110101101111011001000111010101101100011001010010000001110100011011110010000001101001011001000110110001100101 ]
b0 \
b0 Z
0Y
0[
0X
0W
