ANIDS/anids_defines.vh
// ANIDS Defines
// Clock Period, this is 5ns period (200MHz clock)
`define CLK_PERIOD				16'd5


// APB can work with 8, 16, 32 bit data width
`define APB_DATA_WIDTH			8
`define APB_ADDR_WIDTH			16 							// 15 bits needed, but we use 16.


// DMA Data Width is input vector size, which is 128 bits
`define DMA_DATA_WIDTH			128

// Memory Fetch Unit widths
`define MFU_DATA_WIDTH			`DMA_DATA_WIDTH
`define MFU_FEATURE_WIDTH		`MFU_DATA_WIDTH				// stored feature vector width

// Pipeline Manager widths and history depth
`define PIPELINE_VECTOR_WIDTH	`MFU_FEATURE_WIDTH			// vector width propagated through pipeline manager
`define PIPELINE_COUNTER_WIDTH	7							// counter width for indices 0..127
`define PIPELINE_HISTORY_DEPTH	2							// number of coarse vector buffers before validation
`define PIPELINE_STAGE_CYCLES	64							// 128-bit vector processed over 64 cycles
`define PIPELINE_STAGE_COUNT_W	6							// counter width for 0..63 stage timing

// Input layer widths
`define INPUT_LAYER_FEATURE_WIDTH	`PIPELINE_VECTOR_WIDTH	// full feature vector width seen by input layer
`define INPUT_LAYER_PAIR_WIDTH		2						// number of feature bits processed per counter step

// Hidden layer unit widths
`define HL_FEATURE_PAIR_WIDTH		`INPUT_LAYER_PAIR_WIDTH	// number of feature bits consumed per cycle
`define HL_WEIGHT_WIDTH				8						// signed Q0.7 weight width
`define HL_BIAS_WIDTH				8						// signed Q0.7 bias width
`define HL_RESULT_WIDTH				8						// signed Q0.7 hidden neuron output width
`define HL_PAIR_SUM_WIDTH			9						// sum of two weighted feature contributions
`define HL_ACC_WIDTH				15						// accumulation register width before truncation

// Output layer unit widths
`define OL_INPUT_WIDTH				8						// signed Q0.7 hidden-layer input width
`define OL_WEIGHT_WIDTH				8						// signed Q0.7 output-layer weight width
`define OL_BIAS_WIDTH				8						// signed Q0.7 output-layer bias width
`define OL_RESULT_WIDTH				8						// signed Q0.7 output-layer result width
`define OL_PRODUCT_WIDTH			16						// full signed 8x8 multiply width
`define OL_TRUNC_PRODUCT_WIDTH		8						// product truncated back to Q0.7
`define OL_ACC_WIDTH				15						// accumulation width before final truncation

// Loss function widths
`define LF_FEATURE_PAIR_WIDTH		`INPUT_LAYER_PAIR_WIDTH	// number of original feature bits consumed per cycle
`define LF_RESULT_IN_WIDTH			8						// compared result width
`define LF_ABS_WIDTH				8						// absolute delta width
`define LF_PAIR_SUM_WIDTH			9						// sum of two absolute deltas
`define LF_ACC_WIDTH				15						// accumulation register width before truncation

// Sigmoid LUT address mapper widths
`define MMAP_IN_WIDTH				8						// signed Q0.7 value width before LUT lookup
`define MMAP_ADDR_WIDTH				`LUT_ADDR_WIDTH		// LUT address width after mapping

// LUT Address and Data Sizes
`define LUT_ADDR_WIDTH			8
`define LUT_DATA_WIDTH			8

`define RELU_WIDTH 				8
`define LF_OUT_WIDTH			8



// Weight & Bias Counts
`define HL_WEIGHT_COUNT   		64 * 128   	// 8192
`define HL_BIAS_COUNT      		64       	// 64
`define OL_WEIGHT_COUNT    		128 * 64   	// 8192
`define OL_BIAS_COUNT      		128      	// 128


// ANIDS Control Register Addresses
`define START_REG				0
`define N_REG					1
`define THRESHOLD_REG			2
`define RESULT_REG				3


// Indirect LUT Read/Write Registers
`define LUT_ADDR				4
`define LUT_DATA				5
`define LUT_CTRL				6
`define FREE_REG				7


// Hidden Layer Register Mapping
`define HL_WEIGHT_BASE			8 // we have 128 * 64 of these
`define HL_BIAS_BASE			`HL_WEIGHT_BASE + `HL_WEIGHT_COUNT // and 64 of these


// Output Layer Register Mapping
`define OL_WEIGHT_BASE			`HL_BIAS_BASE + `HL_BIAS_COUNT
`define OL_BIAS_BASE			`OL_WEIGHT_BASE + `OL_WEIGHT_COUNT


// ANIDS memory map borders
`define ANIDS_MAP_START   		`HL_WEIGHT_BASE
`define ANIDS_MAP_END     		`OL_BIAS_BASE + `OL_BIAS_COUNT
`define REG_COUNT				`ANIDS_MAP_END 	// (correct count due to 0-based indexing)


// Pipeline Stage Cycles
`define INPUT_LAYER_CYCLES 		1
`define HIDDEN_LAYER_CYCLES 	64
`define OUTPUT_LAYER_CYCLES 	64
`define LOOKUP_LAYER_CYCLES 	64
`define LOSS_FUNCTION_CYCLES 	64
`define OUTLIER_CYCLES 			1
`define RESULT_CYCLES 			1


// Pipeline Fill and Latency in cycles (pipefill = 259, latency = 130)
`define PIPE_FILL_CYCLES 		(`INPUT_LAYER_CYCLES + `HIDDEN_LAYER_CYCLES + `OUTPUT_LAYER_CYCLES + `LOOKUP_LAYER_CYCLES + `LOSS_FUNCTION_CYCLES + `OUTLIER_CYCLES + `RESULT_CYCLES)
`define LATENCY_IN_CYCLES 		(`LOOKUP_LAYER_CYCLES + `LOSS_FUNCTION_CYCLES + `OUTLIER_CYCLES + `RESULT_CYCLES )

ANIDS/src/relu_unit.v
// ANIDS ReLU Unit
`include "anids_defines.vh"

module relu_unit (
		in_data,
		resetN,
		ready,
		out_data
	);

	parameter DATA_WIDTH = `RELU_WIDTH;

	// ----------------------------------------------------------------------
	//                  		I/O Ports
	// ----------------------------------------------------------------------
	input  wire signed [DATA_WIDTH-1:0] in_data;
	input  wire                         resetN;
	input  wire                         ready;
	output reg        [DATA_WIDTH-1:0]  out_data;


	// ----------------------------------------------------------------------
	//                  		ReLU Logic
	// ----------------------------------------------------------------------
	always @(*) begin
		if (!resetN) begin
			out_data = {DATA_WIDTH{1'b0}};
		end
		else if (!ready) begin
			out_data = {DATA_WIDTH{1'b0}};
		end
		else if (in_data[DATA_WIDTH-1]) begin
			// if the number is negative (i.e sign bit is 1)
			out_data = {DATA_WIDTH{1'b0}};
		end
		else begin
			out_data = in_data;
		end
	end

endmodule

ANIDS/tb/unit/relu_unit_tb.sv
// Purpose: verifies ReLU output clamping, reset behavior, and ready/hold control behavior.
// ANIDS - ReLU Unit Testbench
`timescale 1ns/100ps
`include "anids_defines.vh"

module relu_unit_tb;

	localparam DATA_WIDTH = `RELU_WIDTH;

	reg  signed [DATA_WIDTH-1:0] in_data;
	reg                          resetN;
	reg                          ready;
	wire        [DATA_WIDTH-1:0] out_data;

	relu_unit #(
		.DATA_WIDTH(DATA_WIDTH)
	) dut (
		.in_data  (in_data),
		.resetN   (resetN),
		.ready    (ready),
		.out_data (out_data)
	);

	initial begin
		$dumpfile("relu_unit_tb.vcd");
		$dumpvars(0, relu_unit_tb);

		in_data = '0;
		resetN  = 1'b0;
		ready   = 1'b0;

		#1;
		check_output(8'sd25,  1'b0, 1'b1, 8'd0,   "reset clears output");
		check_output(8'sd25,  1'b1, 1'b0, 8'd0,   "ready low holds reset value");
		check_output(8'sd25,  1'b1, 1'b1, 8'd25,  "ready high captures positive input");
		check_output(-8'sd7,  1'b1, 1'b0, 8'd25,  "ready low holds previous positive result");
		check_output(8'sd0,   1'b1, 1'b1, 8'd0,   "ready high captures zero input");
		check_output(8'sd64,  1'b1, 1'b0, 8'd0,   "ready low holds zero result");
		check_output(-8'sd1,  1'b1, 1'b1, 8'd0,   "negative one clamps to zero");
		check_output(-8'sd64, 1'b1, 1'b1, 8'd0,   "negative value clamps to zero");
		check_output(8'sd127, 1'b1, 1'b1, 8'd127, "max positive passes through");
		check_output(8'sd1,   1'b1, 1'b0, 8'd127, "ready low holds max positive result");

		$display("RELU_UNIT TB PASSED");
		$finish;
	end

	task check_output(
		input signed [DATA_WIDTH-1:0] test_in,
		input                         test_resetN,
		input                         test_ready,
		input        [DATA_WIDTH-1:0] expected,
		input [255:0]                 test_name
	);
	begin
		in_data = test_in;
		resetN  = test_resetN;
		ready   = test_ready;
		#1;

		if (out_data !== expected) begin
			$error("FAIL: %0s | in=%0d resetN=%0b ready=%0b out=%0d expected=%0d",
				test_name, test_in, test_resetN, test_ready, out_data, expected);
			$finish;
		end
		else begin
			$display("PASS: %0s", test_name);
		end
	end
	endtask

endmodule

outputs/relu_unit_tb.vcd
$date
	Sat Mar 07 13:10:12 2026
$end
$version
	Icarus Verilog
$end
$timescale
	100ps
$end
$scope module relu_unit_tb $end
$var wire 8 ! out_data [7:0] $end
$var parameter 32 " DATA_WIDTH $end
$var reg 8 # in_data [7:0] $end
$var reg 1 $ ready $end
$var reg 1 % resetN $end
$scope module dut $end
$var wire 8 & in_data [7:0] $end
$var wire 1 $ ready $end
$var wire 1 % resetN $end
$var parameter 32 ' DATA_WIDTH $end
$var reg 8 ( out_data [7:0] $end
$upscope $end
$scope task check_output $end
$var reg 8 ) expected [7:0] $end
$var reg 8 * test_in [7:0] $end
$var reg 256 + test_name [255:0] $end
$var reg 1 , test_ready $end
$var reg 1 - test_resetN $end
$upscope $end
$upscope $end
$enddefinitions $end
$comment Show the parameter values. $end
$dumpall
b1000 '
b1000 "
$end
#0
$dumpvars
x-
x,
bx +
bx *
bx )
b0 (
b0 &
0%
0$
b0 #
b0 !
$end
#10
1$
b11001 #
b11001 &
b1110010011001010111001101100101011101000010000001100011011011000110010101100001011100100111001100100000011011110111010101110100011100000111010101110100 +
b0 )
1,
0-
b11001 *
#20
0$
1%
b1110010011001010110000101100100011110010010000001101100011011110111011100100000011000100110110001101111011000110110101101110011001000000111000001101111011100110110100101110100011010010111011001100101001000000110100101101110011100000111010101110100 +
0,
1-
#30
b11111001 #
b11111001 &
b1110010011001010110000101100100011110010010000001101100011011110111011100100000011000100110110001101111011000110110101101110011001000000110111001100101011001110110000101110100011010010111011001100101001000000110100101101110011100000111010101110100 +
b11111001 *
#40
b11001 !
b11001 (
1$
b11001 #
b11001 &
b111000001101111011100110110100101110100011010010111011001100101001000000110100101101110011100000111010101110100001000000111000001100001011100110111001101100101011100110010000001110100011010000111001001101111011101010110011101101000 +
b11001 )
1,
b11001 *
#50
b0 !
b0 (
b0 #
b0 &
b11110100110010101110010011011110010000001101001011011100111000001110101011101000010000001110011011101000110000101111001011100110010000001111010011001010111001001101111 +
b0 )
b0 *
#60
b11111111 #
b11111111 &
b11011100110010101100111011000010111010001101001011101100110010100100000011011110110111001100101001000000110001101101100011000010110110101110000011100110010000001110100011011110010000001111010011001010111001001101111 +
b11111111 *
#70
b11000000 #
b11000000 &
b110111001100101011001110110000101110100011010010111011001100101001000000111011001100001011011000111010101100101001000000110001101101100011000010110110101110000011100110010000001110100011011110010000001111010011001010111001001101111 +
b11000000 *
#80
b1111111 !
b1111111 (
b1111111 #
b1111111 &
b11011010110000101111000001000000111000001101111011100110110100101110100011010010111011001100101001000000111000001100001011100110111001101100101011100110010000001110100011010000111001001101111011101010110011101101000 +
b1111111 )
b1111111 *
